Workbook
Name acs_19013_income_2024: income!$A$1:$OD$2
Name acs_b01001_sex_age_2024: sex_age!$A$1:$OD$50
Name acs_b02001_race_2024: race!$A$1:$OD$11
Name acs_b30001_hispanic_2024: hispanic!$A$1:$OD$32
Name combined_trends_wnba: combined_trends_wnba!$A$1:$N$53
Name conversion_gap_1: conversion_gap!$A$1:$E$12
Name interest_proxies_1: interest_proxies!$A$1:$G$573
Name missed_revenue_opportunity_1: missed_revenue_opportunity!$A$1:$E$12
Name wnba_attendance: game_attendance!$A$1:$F$14

Sheet game_attendance
A1: team | B1: num_games | C1: low | D1: high | E1: total | F1: avg
A2: Golden State Valkyries | B2: 23 | C2: 18064 | D2: 18543 | E2: 415951 | F2: 18084.826
A3: Indiana Fever | B3: 25 | C3: 15012 | D3: 17274 | E3: 413536 | F3: 16541.44
A4: New York Liberty | B4: 23 | C4: 14774 | D4: 17532 | E4: 376124 | F4: 16353.217
A5: Los Angeles Sparks | B5: 22 | C5: 10581 | D5: 18199 | E5: 273709 | F5: 12441.318
A6: Phoenix Mercury | B6: 28 | C6: 8024 | D6: 17071 | E6: 338932 | F6: 12104.714
A7: Seattle Storm | B7: 23 | C7: 9091 | D7: 18343 | E7: 272877 | F7: 11864.217
A8: Las Vegas Aces | B8: 29 | C8: 10266 | D8: 18547 | E8: 327103 | F8: 11279.414
A9: Minnesota Lynx | B9: 25 | C9: 7808 | D9: 16421 | E9: 248834 | F9: 9953.36
A10: Chicago Sky | B10: 22 | C10: 6572 | D10: 19601 | E10: 199601 | F10: 9072.7727
A11: Connecticut Sun | B11: 22 | C11: 6848 | D11: 19156 | E11: 190369 | F11: 8653.1364
A12: Dallas Wings | B12: 22 | C12: 5228 | D12: 20409 | E12: 159998 | F12: 7272.6364
A13: Washington Mystics | B13: 22 | C13: 4200 | D13: 11183 | E13: 116666 | F13: 5303
A14: Atlanta Dream | B14: 24 | C14: 3265 | D14: 17044 | E14: 106160 | F14: 4423.3333

Sheet team_market
A1: arena | B1: team | C1: capacity | D1: msa
A2: Target Center | B2: Minnesota Lynx | C2: 20000 | D2: Minneapolis-St. Paul-Bloomington, MN-WI
A3: Crypto.com Arena | B3: Los Angeles Sparks | C3: 19079 | D3: Los Angeles-Long Beach-Anaheim, CA
A4: Climate Pledge Arena | B4: Seattle Storm | C4: 18300 | D4: Seattle-Tacoma-Bellevue, WA
A5: Chase Center | B5: Golden State Valkyries | C5: 18064 | D5: San Francisco-Oakland-Fremont, CA
A6: Gainbridge Fieldhouse | B6: Indiana Fever | C6: 18000 | D6: Indianapolis-Carmel-Greenwood, IN
A7: Barclays Center | B7: New York Liberty | C7: 17732 | D7: New York-Newark-Jersey City, NY-NJ
A8: PHX Arena | B8: Phoenix Mercury | C8: 17071 | D8: Phoenix-Mesa-Chandler, AZ
A9: Michelob Ultra Arena | B9: Las Vegas Aces | C9: 12000 | D9: Las Vegas-Henderson-North Las Vegas, NV
A10: Wintrust Arena | B10: Chicago Sky | C10: 10387 | D10: Chicago-Naperville-Elgin, IL-IN
A11: Mohegan Sun Arena | B11: Connecticut Sun | C11: 9323 | D11: Hartford-East Hartford-Middletown, CT
A12: College Park Center | B12: Dallas Wings | C12: 7000 | D12: Dallas-Fort Worth-Arlington, TX
A13: CareFirst Arena | B13: Washington Mystics | C13: 4200 | D13: Washington-Arlington-Alexandria, DC-VA-MD-WV
A14: Gateway Center Arena | B14: Atlanta Dream | C14: 3500 | D14: Atlanta-Sandy Springs-Roswell, GA

Sheet market_demographics
A1: msa | B1: pop_total | C1: pop_female_18_44 | D1: pop_18_34 | E1: pct_black | F1: pct_hispanic | G1: median_income
A2: Minneapolis-St. Paul-Bloomington, MN-WI | B2: =_xlfn.XLOOKUP(A2,sex_age!B$1:OD$1,sex_age!B$2:OD$2) -> 3713668 | C2: =_xlfn.XLOOKUP(A2,sex_age!$B$1:$OD$1,sex_age!$B$27:$OD$27) -> 1861679 | D2: =SUM(_xlfn.XLOOKUP(A2,sex_age!$B$1:$OD$1,sex_age!$B$32:$OD$32),_xlfn.XLOOKUP(A2,sex_age!$B$1:$OD$1,sex_age!$B$33:$OD$33),_xlfn.XLOOKUP(A2,sex_age!$B$1:$OD$1,sex_age!$B$34:$OD$34),_xlfn.XLOOKUP(A2,sex_age!$B$1:$OD$1,sex_age!$B$35:$OD$35),_xlfn.XLOOKUP(A2,sex_age!$B$1:$OD$1,sex_age!$B$36:$OD$36),_xlfn.XLOOKUP(A2,sex_age!$B$1:$OD$1,sex_age!$B$37:$OD$37)) -> 406865 | E2: =(_xlfn.XLOOKUP(A2,race!$B$1:$OD$1,race!$B$4:$OD$4))/B2 -> 0.091683209 | F2: =(_xlfn.XLOOKUP(A2,hispanic!$B$1:$OD$1,hispanic!$B$4:$OD$4))/B2 -> 0.068313053 | G2: =_xlfn.XLOOKUP(A2,income!B$1:OD$1,income!B$2:OD$2) -> 99833
A3: Los Angeles-Long Beach-Anaheim, CA | B3: =_xlfn.XLOOKUP(A3,sex_age!B$1:OD$1,sex_age!B$2:OD$2) -> 12974487 | C3: =_xlfn.XLOOKUP(A3,sex_age!B$1:OD$1,sex_age!B$27:OD$27) -> 6548438 | D3: =SUM(_xlfn.XLOOKUP(A3,sex_age!$B$1:$OD$1,sex_age!$B$32:$OD$32),_xlfn.XLOOKUP(A3,sex_age!$B$1:$OD$1,sex_age!$B$33:$OD$33),_xlfn.XLOOKUP(A3,sex_age!$B$1:$OD$1,sex_age!$B$34:$OD$34),_xlfn.XLOOKUP(A3,sex_age!$B$1:$OD$1,sex_age!$B$35:$OD$35),_xlfn.XLOOKUP(A3,sex_age!$B$1:$OD$1,sex_age!$B$36:$OD$36),_xlfn.XLOOKUP(A3,sex_age!$B$1:$OD$1,sex_age!$B$37:$OD$37)) -> 1557498 | E3: =(_xlfn.XLOOKUP(A3,race!$B$1:$OD$1,race!$B$4:$OD$4))/B3 -> 0.061899326 | F3: =(_xlfn.XLOOKUP(A3,hispanic!$B$1:$OD$1,hispanic!$B$4:$OD$4))/B3 -> 0.44974456 | G3: =_xlfn.XLOOKUP(A3,income!B$1:OD$1,income!B$2:OD$2) -> 95958
A4: Seattle-Tacoma-Bellevue, WA | B4: =_xlfn.XLOOKUP(A4,sex_age!B$1:OD$1,sex_age!B$2:OD$2) -> 4061920 | C4: =_xlfn.XLOOKUP(A4,sex_age!B$1:OD$1,sex_age!B$27:OD$27) -> 2009740 | D4: =SUM(_xlfn.XLOOKUP(A4,sex_age!$B$1:$OD$1,sex_age!$B$32:$OD$32),_xlfn.XLOOKUP(A4,sex_age!$B$1:$OD$1,sex_age!$B$33:$OD$33),_xlfn.XLOOKUP(A4,sex_age!$B$1:$OD$1,sex_age!$B$34:$OD$34),_xlfn.XLOOKUP(A4,sex_age!$B$1:$OD$1,sex_age!$B$35:$OD$35),_xlfn.XLOOKUP(A4,sex_age!$B$1:$OD$1,sex_age!$B$36:$OD$36),_xlfn.XLOOKUP(A4,sex_age!$B$1:$OD$1,sex_age!$B$37:$OD$37)) -> 487121 | E4: =(_xlfn.XLOOKUP(A4,race!$B$1:$OD$1,race!$B$4:$OD$4))/B4 -> 0.061562266 | F4: =(_xlfn.XLOOKUP(A4,hispanic!$B$1:$OD$1,hispanic!$B$4:$OD$4))/B4 -> 0.11665247 | G4: =_xlfn.XLOOKUP(A4,income!B$1:OD$1,income!B$2:OD$2) -> 115177
A5: San Francisco-Oakland-Fremont, CA | B5: =_xlfn.XLOOKUP(A5,sex_age!B$1:OD$1,sex_age!B$2:OD$2) -> 4645029 | C5: =_xlfn.XLOOKUP(A5,sex_age!B$1:OD$1,sex_age!B$27:OD$27) -> 2330281 | D5: =SUM(_xlfn.XLOOKUP(A5,sex_age!$B$1:$OD$1,sex_age!$B$32:$OD$32),_xlfn.XLOOKUP(A5,sex_age!$B$1:$OD$1,sex_age!$B$33:$OD$33),_xlfn.XLOOKUP(A5,sex_age!$B$1:$OD$1,sex_age!$B$34:$OD$34),_xlfn.XLOOKUP(A5,sex_age!$B$1:$OD$1,sex_age!$B$35:$OD$35),_xlfn.XLOOKUP(A5,sex_age!$B$1:$OD$1,sex_age!$B$36:$OD$36),_xlfn.XLOOKUP(A5,sex_age!$B$1:$OD$1,sex_age!$B$37:$OD$37)) -> 515818 | E5: =(_xlfn.XLOOKUP(A5,race!$B$1:$OD$1,race!$B$4:$OD$4))/B5 -> 0.068411198 | F5: =(_xlfn.XLOOKUP(A5,hispanic!$B$1:$OD$1,hispanic!$B$4:$OD$4))/B5 -> 0.23200673 | G5: =_xlfn.XLOOKUP(A5,income!B$1:OD$1,income!B$2:OD$2) -> 136027
A6: Indianapolis-Carmel-Greenwood, IN | B6: =_xlfn.XLOOKUP(A6,sex_age!B$1:OD$1,sex_age!B$2:OD$2) -> 2130055 | C6: =_xlfn.XLOOKUP(A6,sex_age!B$1:OD$1,sex_age!B$27:OD$27) -> 1083136 | D6: =SUM(_xlfn.XLOOKUP(A6,sex_age!$B$1:$OD$1,sex_age!$B$32:$OD$32),_xlfn.XLOOKUP(A6,sex_age!$B$1:$OD$1,sex_age!$B$33:$OD$33),_xlfn.XLOOKUP(A6,sex_age!$B$1:$OD$1,sex_age!$B$34:$OD$34),_xlfn.XLOOKUP(A6,sex_age!$B$1:$OD$1,sex_age!$B$35:$OD$35),_xlfn.XLOOKUP(A6,sex_age!$B$1:$OD$1,sex_age!$B$36:$OD$36),_xlfn.XLOOKUP(A6,sex_age!$B$1:$OD$1,sex_age!$B$37:$OD$37)) -> 244296 | E6: =(_xlfn.XLOOKUP(A6,race!$B$1:$OD$1,race!$B$4:$OD$4))/B6 -> 0.15152332 | F6: =(_xlfn.XLOOKUP(A6,hispanic!$B$1:$OD$1,hispanic!$B$4:$OD$4))/B6 -> 0.08907047 | G6: =_xlfn.XLOOKUP(A6,income!B$1:OD$1,income!B$2:OD$2) -> 79852
A7: New York-Newark-Jersey City, NY-NJ | B7: =_xlfn.XLOOKUP(A7,sex_age!B$1:OD$1,sex_age!B$2:OD$2) -> 19798537 | C7: =_xlfn.XLOOKUP(A7,sex_age!B$1:OD$1,sex_age!B$27:OD$27) -> 10150843 | D7: =SUM(_xlfn.XLOOKUP(A7,sex_age!$B$1:$OD$1,sex_age!$B$32:$OD$32),_xlfn.XLOOKUP(A7,sex_age!$B$1:$OD$1,sex_age!$B$33:$OD$33),_xlfn.XLOOKUP(A7,sex_age!$B$1:$OD$1,sex_age!$B$34:$OD$34),_xlfn.XLOOKUP(A7,sex_age!$B$1:$OD$1,sex_age!$B$35:$OD$35),_xlfn.XLOOKUP(A7,sex_age!$B$1:$OD$1,sex_age!$B$36:$OD$36),_xlfn.XLOOKUP(A7,sex_age!$B$1:$OD$1,sex_age!$B$37:$OD$37)) -> 2253896 | E7: =(_xlfn.XLOOKUP(A7,race!$B$1:$OD$1,race!$B$4:$OD$4))/B7 -> 0.15841575 | F7: =(_xlfn.XLOOKUP(A7,hispanic!$B$1:$OD$1,hispanic!$B$4:$OD$4))/B7 -> 0.25709157 | G7: =_xlfn.XLOOKUP(A7,income!B$1:OD$1,income!B$2:OD$2) -> 99155
A8: Phoenix-Mesa-Chandler, AZ | B8: =_xlfn.XLOOKUP(A8,sex_age!B$1:OD$1,sex_age!B$2:OD$2) -> 5028754 | C8: =_xlfn.XLOOKUP(A8,sex_age!B$1:OD$1,sex_age!B$27:OD$27) -> 2518021 | D8: =SUM(_xlfn.XLOOKUP(A8,sex_age!$B$1:$OD$1,sex_age!$B$32:$OD$32),_xlfn.XLOOKUP(A8,sex_age!$B$1:$OD$1,sex_age!$B$33:$OD$33),_xlfn.XLOOKUP(A8,sex_age!$B$1:$OD$1,sex_age!$B$34:$OD$34),_xlfn.XLOOKUP(A8,sex_age!$B$1:$OD$1,sex_age!$B$35:$OD$35),_xlfn.XLOOKUP(A8,sex_age!$B$1:$OD$1,sex_age!$B$36:$OD$36),_xlfn.XLOOKUP(A8,sex_age!$B$1:$OD$1,sex_age!$B$37:$OD$37)) -> 575795 | E8: =(_xlfn.XLOOKUP(A8,race!$B$1:$OD$1,race!$B$4:$OD$4))/B8 -> 0.056570673 | F8: =(_xlfn.XLOOKUP(A8,hispanic!$B$1:$OD$1,hispanic!$B$4:$OD$4))/B8 -> 0.31065946 | G8: =_xlfn.XLOOKUP(A8,income!B$1:OD$1,income!B$2:OD$2) -> 88301
A9: Las Vegas-Henderson-North Las Vegas, NV | B9: =_xlfn.XLOOKUP(A9,sex_age!B$1:OD$1,sex_age!B$2:OD$2) -> 2329548 | C9: =_xlfn.XLOOKUP(A9,sex_age!B$1:OD$1,sex_age!B$27:OD$27) -> 1163836 | D9: =SUM(_xlfn.XLOOKUP(A9,sex_age!$B$1:$OD$1,sex_age!$B$32:$OD$32),_xlfn.XLOOKUP(A9,sex_age!$B$1:$OD$1,sex_age!$B$33:$OD$33),_xlfn.XLOOKUP(A9,sex_age!$B$1:$OD$1,sex_age!$B$34:$OD$34),_xlfn.XLOOKUP(A9,sex_age!$B$1:$OD$1,sex_age!$B$35:$OD$35),_xlfn.XLOOKUP(A9,sex_age!$B$1:$OD$1,sex_age!$B$36:$OD$36),_xlfn.XLOOKUP(A9,sex_age!$B$1:$OD$1,sex_age!$B$37:$OD$37)) -> 260368 | E9: =(_xlfn.XLOOKUP(A9,race!$B$1:$OD$1,race!$B$4:$OD$4))/B9 -> 0.12026496 | F9: =(_xlfn.XLOOKUP(A9,hispanic!$B$1:$OD$1,hispanic!$B$4:$OD$4))/B9 -> 0.31854892 | G9: =_xlfn.XLOOKUP(A9,income!B$1:OD$1,income!B$2:OD$2) -> 76472
A10: Chicago-Naperville-Elgin, IL-IN | B10: =_xlfn.XLOOKUP(A10,sex_age!B$1:OD$1,sex_age!B$2:OD$2) -> 9371595 | C10: =_xlfn.XLOOKUP(A10,sex_age!B$1:OD$1,sex_age!B$27:OD$27) -> 4757901 | D10: =SUM(_xlfn.XLOOKUP(A10,sex_age!$B$1:$OD$1,sex_age!$B$32:$OD$32),_xlfn.XLOOKUP(A10,sex_age!$B$1:$OD$1,sex_age!$B$33:$OD$33),_xlfn.XLOOKUP(A10,sex_age!$B$1:$OD$1,sex_age!$B$34:$OD$34),_xlfn.XLOOKUP(A10,sex_age!$B$1:$OD$1,sex_age!$B$35:$OD$35),_xlfn.XLOOKUP(A10,sex_age!$B$1:$OD$1,sex_age!$B$36:$OD$36),_xlfn.XLOOKUP(A10,sex_age!$B$1:$OD$1,sex_age!$B$37:$OD$37)) -> 1070706 | E10: =(_xlfn.XLOOKUP(A10,race!$B$1:$OD$1,race!$B$4:$OD$4))/B10 -> 0.15982221 | F10: =(_xlfn.XLOOKUP(A10,hispanic!$B$1:$OD$1,hispanic!$B$4:$OD$4))/B10 -> 0.24078431 | G10: =_xlfn.XLOOKUP(A10,income!B$1:OD$1,income!B$2:OD$2) -> 90887
A11: Hartford-West Hartford-East Hartford, CT | B11: =_xlfn.XLOOKUP(A11,sex_age!B$1:OD$1,sex_age!B$2:OD$2) -> 1153112 | C11: =_xlfn.XLOOKUP(A11,sex_age!B$1:OD$1,sex_age!B$27:OD$27) -> 587506 | D11: =SUM(_xlfn.XLOOKUP(A11,sex_age!$B$1:$OD$1,sex_age!$B$32:$OD$32),_xlfn.XLOOKUP(A11,sex_age!$B$1:$OD$1,sex_age!$B$33:$OD$33),_xlfn.XLOOKUP(A11,sex_age!$B$1:$OD$1,sex_age!$B$34:$OD$34),_xlfn.XLOOKUP(A11,sex_age!$B$1:$OD$1,sex_age!$B$35:$OD$35),_xlfn.XLOOKUP(A11,sex_age!$B$1:$OD$1,sex_age!$B$36:$OD$36),_xlfn.XLOOKUP(A11,sex_age!$B$1:$OD$1,sex_age!$B$37:$OD$37)) -> 128304 | E11: =(_xlfn.XLOOKUP(A11,race!$B$1:$OD$1,race!$B$4:$OD$4))/B11 -> 0.11306187 | F11: =(_xlfn.XLOOKUP(A11,hispanic!$B$1:$OD$1,hispanic!$B$4:$OD$4))/B11 -> 0.16176659 | G11: =_xlfn.XLOOKUP(A11,income!B$1:OD$1,income!B$2:OD$2) -> 95118
A12: Dallas-Fort Worth-Arlington, TX | B12: =_xlfn.XLOOKUP(A12,sex_age!B$1:OD$1,sex_age!B$2:OD$2) -> 7985590 | C12: =_xlfn.XLOOKUP(A12,sex_age!B$1:OD$1,sex_age!B$27:OD$27) -> 4031384 | D12: =SUM(_xlfn.XLOOKUP(A12,sex_age!$B$1:$OD$1,sex_age!$B$32:$OD$32),_xlfn.XLOOKUP(A12,sex_age!$B$1:$OD$1,sex_age!$B$33:$OD$33),_xlfn.XLOOKUP(A12,sex_age!$B$1:$OD$1,sex_age!$B$34:$OD$34),_xlfn.XLOOKUP(A12,sex_age!$B$1:$OD$1,sex_age!$B$35:$OD$35),_xlfn.XLOOKUP(A12,sex_age!$B$1:$OD$1,sex_age!$B$36:$OD$36),_xlfn.XLOOKUP(A12,sex_age!$B$1:$OD$1,sex_age!$B$37:$OD$37)) -> 961263 | E12: =(_xlfn.XLOOKUP(A12,race!$B$1:$OD$1,race!$B$4:$OD$4))/B12 -> 0.16310091 | F12: =(_xlfn.XLOOKUP(A12,hispanic!$B$1:$OD$1,hispanic!$B$4:$OD$4))/B12 -> 0.29691632 | G12: =_xlfn.XLOOKUP(A12,income!B$1:OD$1,income!B$2:OD$2) -> 90275
A13: Washington-Arlington-Alexandria, DC-VA-MD-WV | B13: =_xlfn.XLOOKUP(A13,sex_age!B$1:OD$1,sex_age!B$2:OD$2) -> 6318377 | C13: =_xlfn.XLOOKUP(A13,sex_age!B$1:OD$1,sex_age!B$27:OD$27) -> 3210855 | D13: =SUM(_xlfn.XLOOKUP(A13,sex_age!$B$1:$OD$1,sex_age!$B$32:$OD$32),_xlfn.XLOOKUP(A13,sex_age!$B$1:$OD$1,sex_age!$B$33:$OD$33),_xlfn.XLOOKUP(A13,sex_age!$B$1:$OD$1,sex_age!$B$34:$OD$34),_xlfn.XLOOKUP(A13,sex_age!$B$1:$OD$1,sex_age!$B$35:$OD$35),_xlfn.XLOOKUP(A13,sex_age!$B$1:$OD$1,sex_age!$B$36:$OD$36),_xlfn.XLOOKUP(A13,sex_age!$B$1:$OD$1,sex_age!$B$37:$OD$37)) -> 721366 | E13: =(_xlfn.XLOOKUP(A13,race!$B$1:$OD$1,race!$B$4:$OD$4))/B13 -> 0.24574729 | F13: =(_xlfn.XLOOKUP(A13,hispanic!$B$1:$OD$1,hispanic!$B$4:$OD$4))/B13 -> 0.18036974 | G13: =_xlfn.XLOOKUP(A13,income!B$1:OD$1,income!B$2:OD$2) -> 126684
A14: Atlanta-Sandy Springs-Roswell, GA | B14: =_xlfn.XLOOKUP(A14,sex_age!B$1:OD$1,sex_age!B$2:OD$2) -> 6256377 | C14: =_xlfn.XLOOKUP(A14,sex_age!B$1:OD$1,sex_age!B$27:OD$27) -> 3220306 | D14: =SUM(_xlfn.XLOOKUP(A14,sex_age!$B$1:$OD$1,sex_age!$B$32:$OD$32),_xlfn.XLOOKUP(A14,sex_age!$B$1:$OD$1,sex_age!$B$33:$OD$33),_xlfn.XLOOKUP(A14,sex_age!$B$1:$OD$1,sex_age!$B$34:$OD$34),_xlfn.XLOOKUP(A14,sex_age!$B$1:$OD$1,sex_age!$B$35:$OD$35),_xlfn.XLOOKUP(A14,sex_age!$B$1:$OD$1,sex_age!$B$36:$OD$36),_xlfn.XLOOKUP(A14,sex_age!$B$1:$OD$1,sex_age!$B$37:$OD$37)) -> 737974 | E14: =(_xlfn.XLOOKUP(A14,race!$B$1:$OD$1,race!$B$4:$OD$4))/B14 -> 0.33699855 | F14: =(_xlfn.XLOOKUP(A14,hispanic!$B$1:$OD$1,hispanic!$B$4:$OD$4))/B14 -> 0.12423436 | G14: =_xlfn.XLOOKUP(A14,income!B$1:OD$1,income!B$2:OD$2) -> 89724

Sheet missed_revenue_opportunity
A1: market_msa | B1: interest_norm | C1: income_norm | D1: conversion_gap | E1: missed_revenue_score
A2: Las Vegas-Henderson-North Las Vegas, NV | B2: 0.60965565 | C2: 0.56218251 | D2: -0.2645235 | E2: -0.090662187
A3: Phoenix-Mesa-Chandler, AZ | B3: 0.23142312 | C3: 0.64914318 | D3: -0.34490621 | E3: -0.051814136
A4: Atlanta-Sandy Springs-Roswell, GA | B4: 0.22789308 | C4: 0.65960434 | D4: 0.21615363 | E4: 0.032492055
A5: Indianapolis-Carmel-Greenwood, IN | B5: 1 | C5: 0.58703052 | D5: -0.46427428 | E5: -0.27254317
A6: New York-Newark-Jersey City, NY-NJ | B6: 0.1214106 | C6: 0.72893617 | D6: 0.095749259 | E6: 0.0084738649
A7: Dallas-Fort Worth-Arlington, TX | B7: 0.19338283 | C7: 0.66365501 | D7: 0.056930923 | E7: 0.0073064851
A8: Los Angeles-Long Beach-Anaheim, CA | B8: 0.1483513 | C8: 0.70543348 | D8: -0.15068878 | E8: -0.015769878
A9: San Francisco-Oakland-Fremont, CA | B9: 0.35772743 | C9: 1 | D9: -0.47176746 | E9: -0.16876416
A10: Minneapolis-St. Paul-Bloomington, MN-WI | B10: 0.37778739 | C10: 0.73392047 | D10: -0.15645164 | E10: -0.043378706
A11: Chicago-Naperville-Elgin, IL-IN | B11: 0.24129731 | C11: 0.66815412 | D11: 0.1297947 | E11: 0.020925994
A12: Washington-Arlington-Alexandria, DC-VA-MD-WV | B12: 0.21201003 | C12: 0.93131511 | D12: 0.080309005 | E12: 0.015856864

Sheet conversion_gap
A1: market_msa | B1: Team | C1: interest_norm | D1: attendance_norm | E1: conversion_gap
A2: Indianapolis-Carmel-Greenwood, IN | B2: Indiana Fever | C2: 0.45038423 | D2: 0.91465851 | E2: -0.46427428
A3: Minneapolis-St. Paul-Bloomington, MN-WI | B3: Minnesota Lynx | C3: 0.39391914 | D3: 0.55037079 | E3: -0.15645164
A4: New York-Newark-Jersey City, NY-NJ | B4: New York Liberty | C4: 1 | D4: 0.90425074 | E4: 0.095749259
A5: Las Vegas-Henderson-North Las Vegas, NV | B5: Las Vegas Aces | C5: 0.3591714 | D5: 0.6236949 | E5: -0.2645235
A6: Phoenix-Mesa-Chandler, AZ | B6: Phoenix Mercury | C6: 0.32442366 | D6: 0.66932987 | E6: -0.34490621
A7: Chicago-Naperville-Elgin, IL-IN | B7: Chicago Sky | C7: 0.63147344 | D7: 0.50167874 | E7: 0.1297947
A8: Atlanta-Sandy Springs-Roswell, GA | B8: Atlanta Dream | C8: 0.46074173 | D8: 0.2445881 | E8: 0.21615363
A9: Dallas-Fort Worth-Arlington, TX | B9: Dallas Wings | C9: 0.45907117 | D9: 0.40214024 | E9: 0.056930923
A10: Washington-Arlington-Alexandria, DC-VA-MD-WV | B10: Washington Mystics | C10: 0.37353826 | D10: 0.29322925 | E10: 0.080309005
A11: Los Angeles-Long Beach-Anaheim, CA | B11: Los Angeles Sparks | C11: 0.53725359 | D11: 0.68794237 | E11: -0.15068878
A12: San Francisco-Oakland-Fremont, CA | B12: Golden State Valkyries | C12: 0.52823254 | D12: 1 | E12: -0.47176746

Sheet combined_trends_wnba
A1: Week | B1: indiana | C1: california | D1: california2 | E1: new_york | F1: texas | G1: arizona | H1: connecticut | I1: georgia | J1: illinois | K1: minnesota | L1: nevada | M1: washington | N1: district_of_columbia
A2: 45739 | B2: 6 | C2: 3 | D2: 3 | E2: 4 | F2: 3 | G2: 3 | H2: 6 | I2: 3 | J2: 4 | K2: 4 | L2: 2 | M2: 4 | N2: 7
A3: 45746 | B3: 5 | C3: 3 | D3: 3 | E3: 4 | F3: 3 | G3: 3 | H3: 7 | I3: 4 | J3: 4 | K3: 5 | L3: 4 | M3: 5 | N3: 7
A4: 45753 | B4: 8 | C4: 4 | D4: 4 | E4: 6 | F4: 5 | G4: 5 | H4: 16 | I4: 5 | J4: 7 | K4: 8 | L4: 4 | M4: 8 | N4: 11
A5: 45760 | B5: 26 | C5: 13 | D5: 13 | E5: 18 | F5: 15 | G5: 12 | H5: 48 | I5: 16 | J5: 23 | K5: 25 | L5: 12 | M5: 22 | N5: 32
A6: 45767 | B6: 4 | C6: 3 | D6: 3 | E6: 3 | F6: 3 | G6: 2 | H6: 5 | I6: 3 | J6: 3 | K6: 3 | L6: 3 | M6: 3 | N6: 5
A7: 45774 | B7: 11 | C7: 4 | D7: 4 | E7: 5 | F7: 4 | G7: 4 | H7: 9 | I7: 5 | J7: 6 | K7: 6 | L7: 6 | M7: 6 | N7: 9
A8: 45781 | B8: 13 | C8: 7 | D8: 7 | E8: 7 | F8: 6 | G8: 8 | H8: 12 | I8: 8 | J8: 9 | K8: 8 | L8: 11 | M8: 9 | N8: 13
A9: 45788 | B9: 20 | C9: 13 | D9: 13 | E9: 13 | F9: 12 | G9: 13 | H9: 20 | I9: 14 | J9: 16 | K9: 16 | L9: 14 | M9: 14 | N9: 17
A10: 45795 | B10: 40 | C10: 23 | D10: 23 | E10: 22 | F10: 20 | G10: 24 | H10: 29 | I10: 27 | J10: 29 | K10: 27 | L10: 24 | M10: 22 | N10: 34
A11: 45802 | B11: 25 | C11: 15 | D11: 15 | E11: 17 | F11: 15 | G11: 22 | H11: 26 | I11: 21 | J11: 22 | K11: 22 | L11: 22 | M11: 21 | N11: 28
A12: 45809 | B12: 22 | C12: 13 | D12: 13 | E12: 14 | F12: 13 | G12: 18 | H12: 20 | I12: 17 | J12: 18 | K12: 20 | L12: 18 | M12: 14 | N12: 21
A13: 45816 | B13: 27 | C13: 12 | D13: 12 | E13: 16 | F13: 14 | G13: 18 | H13: 22 | I13: 19 | J13: 20 | K13: 24 | L13: 21 | M13: 17 | N13: 21
... A53: 46096 | B53: 7 | C53: 4 | D53: 4 | E53: 5 | F53: 4 | G53: 4 | H53: 6 | I53: 4 | J53: 5 | K53: 5 | L53: 5 | M53: 5 | N53: 10

Sheet interest_proxies
A1: Week | B1: market_msa | C1: interest_league | D1: interest_team | E1: interest_player | F1: pop_total | G1: median_income
A2: 45739 | B2: Indianapolis-Carmel-Greenwood, IN | C2: 6 | D2: 6 | E2: 19 | F2: 2130055 | G2: 79852
A3: 45739 | B3: Minneapolis-St. Paul-Bloomington, MN-WI | C3: 4 | D3: 6 | E3: 0 | F3: 3713668 | G3: 99833
A4: 45739 | B4: New York-Newark-Jersey City, NY-NJ | C4: 4 | D4: 49 | E4: 11 | F4: 19798537 | G4: 99155
A5: 45739 | B5: Las Vegas-Henderson-North Las Vegas, NV | C5: 2 | D5: 5 | E5: 0 | F5: 2329548 | G5: 76472
A6: 45739 | B6: Phoenix-Mesa-Chandler, AZ | C6: 3 | D6: 4 | E6: 0 | F6: 5028754 | G6: 88301
A7: 45739 | B7: Chicago-Naperville-Elgin, IL-IN | C7: 4 | D7: 25 | E7: 35 | F7: 9371595 | G7: 90887
A8: 45739 | B8: Atlanta-Sandy Springs-Roswell, GA | C8: 3 | D8: 13 | E8: 0 | F8: 6256377 | G8: 89724
A9: 45739 | B9: Dallas-Fort Worth-Arlington, TX | C9: 3 | D9: 13 | E9: 28 | F9: 7985590 | G9: 90275
A10: 45739 | B10: Washington-Arlington-Alexandria, DC-VA-MD-WV | C10: 4 | D10: 100 | E10: 0 | F10: 6318377 | G10: 126684
A11: 45739 | B11: Los Angeles-Long Beach-Anaheim, CA | C11: 3 | D11: 0 | E11: 32 | F11: 12974487 | G11: 95958
A12: 45739 | B12: San Francisco-Oakland-Fremont, CA | C12: 3 | D12: 15 | E12: 0 | F12: 4645029 | G12: 136027
A13: 45746 | B13: Indianapolis-Carmel-Greenwood, IN | C13: 5 | D13: 5 | E13: 14 | F13: 2130055 | G13: 79852
... A573: 46096 | B573: San Francisco-Oakland-Fremont, CA | C573: 4 | D573: 6 | E573: 3 | F573: 4645029 | G573: 136027

Sheet sex_age
A1: se | B1: Abilene, TX | C1: Aguadilla, PR | D1: Akron, OH | E1: Albany, GA | F1: Albany, OR | G1: Albany-Schenectady-Troy, NY | H1: Albuquerque, NM | I1: Alexandria, LA | J1: Allentown-Bethlehem-Easton, PA-NJ | K1: Altoona, PA | L1: Amarillo, TX | M1: Ames, IA | N1: Amherst Town-Northampton, MA | O1: Anchorage, AK | P1: Ann Arbor, MI | Q1: Anniston-Oxford, AL | R1: Appleton, WI | S1: Arecibo, PR | T1: Asheville, NC | U1: Athens-Clarke County, GA | V1: Atlanta-Sandy Springs-Roswell, GA | W1: Atlantic City-Hammonton, NJ | X1: Auburn-Opelika, AL | Y1: Augusta-Richmond County, GA-SC | Z1: Austin-Round Rock-San Marcos, TX | AA1: Bakersfield-Delano, CA | AB1: Baltimore-Columbia-Towson, MD | AC1: Bangor, ME | AD1: Barnstable Town, MA | AE1: Baton Rouge, LA | AF1: Battle Creek, MI | AG1: Bay City, MI | AH1: Beaumont-Port Arthur, TX | AI1: Beckley, WV | AJ1: Bellingham, WA | AK1: Bend, OR | AL1: Billings, MT | AM1: Binghamton, NY | AN1: Birmingham, AL | AO1: Bismarck, ND | AP1: Blacksburg-Christiansburg-Radford, VA | AQ1: Bloomington, IL | AR1: Bloomington, IN | AS1: Boise City, ID | AT1: Boston-Cambridge-Newton, MA-NH | AU1: Boulder, CO | AV1: Bowling Green, KY | AW1: Bozeman, MT | AX1: Bremerton-Silverdale-Port Orchard, WA | AY1: Bridgeport-Stamford-Danbury, CT | AZ1: Brownsville-Harlingen, TX | BA1: Brunswick-St. Simons, GA | BB1: Buffalo-Cheektowaga, NY | BC1: Burlington, NC | BD1: Burlington-South Burlington, VT | BE1: Canton-Massillon, OH | BF1: Cape Coral-Fort Myers, FL | BG1: Cape Girardeau, MO-IL | BH1: Carson City, NV | BI1: Casper, WY | BJ1: Cedar Rapids, IA | BK1: Chambersburg, PA | BL1: Champaign-Urbana, IL | BM1: Charleston, WV | BN1: Charleston-North Charleston, SC | BO1: Charlotte-Concord-Gastonia, NC-SC | BP1: Charlottesville, VA | BQ1: Chattanooga, TN-GA | BR1: Cheyenne, WY | BS1: Chicago-Naperville-Elgin, IL-IN | BT1: Chico, CA | BU1: Cincinnati, OH-KY-IN | BV1: Clarksville, TN-KY | BW1: Cleveland, OH | BX1: Cleveland, TN | BY1: Coeur d'Alene, ID | BZ1: College Station-Bryan, TX | CA1: Colorado Springs, CO | CB1: Columbia, MO | CC1: Columbia, SC | CD1: Columbus, GA-AL | CE1: Columbus, IN | CF1: Columbus, OH | CG1: Corpus Christi, TX | CH1: Corvallis, OR | CI1: Crestview-Fort Walton Beach-Destin, FL | CJ1: Dallas-Fort Worth-Arlington, TX | CK1: Dalton, GA | CL1: Daphne-Fairhope-Foley, AL | CM1: Davenport-Moline-Rock Island, IA-IL | CN1: Dayton-Kettering-Beavercreek, OH | CO1: Decatur, AL | CP1: Decatur, IL | CQ1: Deltona-Daytona Beach-Ormond Beach, FL | CR1: Denver-Aurora-Centennial, CO | CS1: Des Moines-West Des Moines, IA | CT1: Detroit-Warren-Dearborn, MI | CU1: Dothan, AL | CV1: Dover, DE | CW1: Dubuque, IA | CX1: Duluth, MN-WI | CY1: Durham-Chapel Hill, NC | CZ1: Eagle Pass, TX | DA1: Eau Claire, WI | DB1: El Centro, CA | DC1: Elizabethtown, KY | DD1: Elkhart-Goshen, IN | DE1: Elmira, NY | DF1: El Paso, TX | DG1: Enid, OK | DH1: Erie, PA | DI1: Eugene-Springfield, OR | DJ1: Evansville, IN | DK1: Fairbanks-College, AK | DL1: Fargo, ND-MN | DM1: Farmington, NM | DN1: Fayetteville, NC | DO1: Fayetteville-Springdale-Rogers, AR | DP1: Flagstaff, AZ | DQ1: Flint, MI | DR1: Florence, SC | DS1: Florence-Muscle Shoals, AL | DT1: Fond du Lac, WI | DU1: Fort Collins-Loveland, CO | DV1: Fort Smith, AR-OK | DW1: Fort Wayne, IN | DX1: Fresno, CA | DY1: Gadsden, AL | DZ1: Gainesville, FL | EA1: Gainesville, GA | EB1: Gettysburg, PA | EC1: Glens Falls, NY | ED1: Goldsboro, NC | EE1: Grand Forks, ND-MN | EF1: Grand Island, NE | EG1: Grand Junction, CO | EH1: Grand Rapids-Wyoming-Kentwood, MI | EI1: Grants Pass, OR | EJ1: Great Falls, MT | EK1: Greeley, CO | EL1: Green Bay, WI | EM1: Greensboro-High Point, NC | EN1: Greenville, NC | EO1: Greenville-Anderson-Greer, SC | EP1: Guayama, PR | EQ1: Gulfport-Biloxi, MS | ER1: Hagerstown-Martinsburg, MD-WV | ES1: Hammond, LA | ET1: Hanford-Corcoran, CA | EU1: Harrisburg-Carlisle, PA | EV1: Harrisonburg, VA | EW1: Hartford-West Hartford-East Hartford, CT | EX1: Hattiesburg, MS | EY1: Helena, MT | EZ1: Hickory-Lenoir-Morganton, NC | FA1: Hilton Head Island-Bluffton-Port Royal, SC | FB1: Hinesville, GA | FC1: Homosassa Springs, FL | FD1: Hot Springs, AR | FE1: Houma-Bayou Cane-Thibodaux, LA | FF1: Houston-Pasadena-The Woodlands, TX | FG1: Huntington-Ashland, WV-KY-OH | FH1: Huntsville, AL | FI1: Idaho Falls, ID | FJ1: Indianapolis-Carmel-Greenwood, IN | FK1: Iowa City, IA | FL1: Ithaca, NY | FM1: Jackson, MI | FN1: Jackson, MS | FO1: Jackson, TN | FP1: Jacksonville, FL | FQ1: Jacksonville, NC | FR1: Janesville-Beloit, WI | FS1: Jefferson City, MO | FT1: Johnson City, TN | FU1: Johnstown, PA | FV1: Jonesboro, AR | FW1: Joplin, MO-KS | FX1: Kahului-Wailuku, HI | FY1: Kalamazoo-Portage, MI | FZ1: Kankakee, IL | GA1: Kansas City, MO-KS | GB1: Kennewick-Richland, WA | GC1: Kenosha, WI | GD1: Killeen-Temple, TX | GE1: Kingsport-Bristol, TN-VA | GF1: Kingston, NY | GG1: Kiryas Joel-Poughkeepsie-Newburgh, NY | GH1: Knoxville, TN | GI1: Kokomo, IN | GJ1: La Crosse-Onalaska, WI-MN | GK1: Lafayette, LA | GL1: Lafayette-West Lafayette, IN | GM1: Lake Charles, LA | GN1: Lake Havasu City-Kingman, AZ | GO1: Lakeland-Winter Haven, FL | GP1: Lancaster, PA | GQ1: Lansing-East Lansing, MI | GR1: Laredo, TX | GS1: Las Cruces, NM | GT1: Las Vegas-Henderson-North Las Vegas, NV | GU1: Lawrence, KS | GV1: Lawton, OK | GW1: Lebanon, PA | GX1: Lewiston, ID-WA | GY1: Lewiston-Auburn, ME | GZ1: Lexington-Fayette, KY | HA1: Lexington Park, MD | HB1: Lima, OH | HC1: Lincoln, NE | HD1: Little Rock-North Little Rock-Conway, AR | HE1: Logan, UT-ID | HF1: Longview, TX | HG1: Longview-Kelso, WA | HH1: Los Angeles-Long Beach-Anaheim, CA | HI1: Louisville/Jefferson County, KY-IN | HJ1: Lubbock, TX | HK1: Lynchburg, VA | HL1: Macon-Bibb County, GA | HM1: Madison, WI | HN1: Manchester-Nashua, NH | HO1: Manhattan, KS | HP1: Mankato, MN | HQ1: Mansfield, OH | HR1: Mayagüez, PR | HS1: McAllen-Edinburg-Mission, TX | HT1: Medford, OR | HU1: Memphis, TN-MS-AR | HV1: Merced, CA | HW1: Miami-Fort Lauderdale-West Palm Beach, FL | HX1: Michigan City-La Porte, IN | HY1: Midland, MI | HZ1: Midland, TX | IA1: Milwaukee-Waukesha, WI | IB1: Minneapolis-St. Paul-Bloomington, MN-WI | IC1: Minot, ND | ID1: Missoula, MT | IE1: Mobile, AL | IF1: Modesto, CA | IG1: Monroe, LA | IH1: Monroe, MI | II1: Montgomery, AL | IJ1: Morgantown, WV | IK1: Morristown, TN | IL1: Mount Vernon-Anacortes, WA | IM1: Muncie, IN | IN1: Muskegon-Norton Shores, MI | IO1: Myrtle Beach-Conway-North Myrtle Beach, SC | IP1: Napa, CA | IQ1: Naples-Marco Island, FL | IR1: Nashville-Davidson--Murfreesboro--Franklin, TN | IS1: New Haven, CT | IT1: New Orleans-Metairie, LA | IU1: New York-Newark-Jersey City, NY-NJ | IV1: Niles, MI | IW1: North Port-Bradenton-Sarasota, FL | IX1: Norwich-New London-Willimantic, CT | IY1: Ocala, FL | IZ1: Odessa, TX | JA1: Ogden, UT | JB1: Oklahoma City, OK | JC1: Olympia-Lacey-Tumwater, WA | JD1: Omaha, NE-IA | JE1: Orlando-Kissimmee-Sanford, FL | JF1: Oshkosh-Neenah, WI | JG1: Owensboro, KY | JH1: Oxnard-Thousand Oaks-Ventura, CA | JI1: Paducah, KY-IL | JJ1: Palm Bay-Melbourne-Titusville, FL | JK1: Panama City-Panama City Beach, FL | JL1: Parkersburg-Vienna, WV | JM1: Pensacola-Ferry Pass-Brent, FL | JN1: Peoria, IL | JO1: Philadelphia-Camden-Wilmington, PA-NJ-DE-MD | JP1: Phoenix-Mesa-Chandler, AZ | JQ1: Pinehurst-Southern Pines, NC | JR1: Pittsburgh, PA | JS1: Pittsfield, MA | JT1: Pocatello, ID | JU1: Ponce, PR | JV1: Portland-South Portland, ME | JW1: Portland-Vancouver-Hillsboro, OR-WA | JX1: Port St. Lucie, FL | JY1: Prescott Valley-Prescott, AZ | JZ1: Providence-Warwick, RI-MA | KA1: Provo-Orem-Lehi, UT | KB1: Pueblo, CO | KC1: Punta Gorda, FL | KD1: Racine-Mount Pleasant, WI | KE1: Raleigh-Cary, NC | KF1: Rapid City, SD | KG1: Reading, PA | KH1: Redding, CA | KI1: Reno, NV | KJ1: Richmond, VA | KK1: Riverside-San Bernardino-Ontario, CA | KL1: Roanoke, VA | KM1: Rochester, MN | KN1: Rochester, NY | KO1: Rockford, IL | KP1: Rocky Mount, NC | KQ1: Rome, GA | KR1: Sacramento-Roseville-Folsom, CA | KS1: Saginaw, MI | KT1: St. Cloud, MN | KU1: St. George, UT | KV1: St. Joseph, MO-KS | KW1: St. Louis, MO-IL | KX1: Salem, OR | KY1: Salinas, CA | KZ1: Salisbury, MD | LA1: Salt Lake City-Murray, UT | LB1: San Angelo, TX | LC1: San Antonio-New Braunfels, TX | LD1: San Diego-Chula Vista-Carlsbad, CA | LE1: Sandusky, OH | LF1: San Francisco-Oakland-Fremont, CA | LG1: San Jose-Sunnyvale-Santa Clara, CA | LH1: San Juan-Bayamón-Caguas, PR | LI1: San Luis Obispo-Paso Robles, CA | LJ1: Santa Cruz-Watsonville, CA | LK1: Santa Fe, NM | LL1: Santa Maria-Santa Barbara, CA | LM1: Santa Rosa-Petaluma, CA | LN1: Savannah, GA | LO1: Scranton--Wilkes-Barre, PA | LP1: Seattle-Tacoma-Bellevue, WA | LQ1: Sebastian-Vero Beach-West Vero Corridor, FL | LR1: Sebring, FL | LS1: Sheboygan, WI | LT1: Sherman-Denison, TX | LU1: Shreveport-Bossier City, LA | LV1: Sierra Vista-Douglas, AZ | LW1: Sioux City, IA-NE-SD | LX1: Sioux Falls, SD-MN | LY1: Slidell-Mandeville-Covington, LA | LZ1: South Bend-Mishawaka, IN-MI | MA1: Spartanburg, SC | MB1: Spokane-Spokane Valley, WA | MC1: Springfield, IL | MD1: Springfield, MA | ME1: Springfield, MO | MF1: Springfield, OH | MG1: State College, PA | MH1: Staunton-Stuarts Draft, VA | MI1: Stockton-Lodi, CA | MJ1: Sumter, SC | MK1: Syracuse, NY | ML1: Tallahassee, FL | MM1: Tampa-St. Petersburg-Clearwater, FL | MN1: Terre Haute, IN | MO1: Texarkana, TX-AR | MP1: Toledo, OH | MQ1: Topeka, KS | MR1: Traverse City, MI | MS1: Trenton-Princeton, NJ | MT1: Tucson, AZ | MU1: Tulsa, OK | MV1: Tuscaloosa, AL | MW1: Twin Falls, ID | MX1: Tyler, TX | MY1: Urban Honolulu, HI | MZ1: Utica-Rome, NY | NA1: Valdosta, GA | NB1: Vallejo, CA | NC1: Victoria, TX | ND1: Vineland, NJ | NE1: Virginia Beach-Chesapeake-Norfolk, VA-NC | NF1: Visalia, CA | NG1: Waco, TX | NH1: Walla Walla, WA | NI1: Warner Robins, GA | NJ1: Washington-Arlington-Alexandria, DC-VA-MD-WV | NK1: Waterbury-Shelton, CT | NL1: Waterloo-Cedar Falls, IA | NM1: Watertown-Fort Drum, NY | NN1: Wausau, WI | NO1: Weirton-Steubenville, WV-OH | NP1: Wenatchee-East Wenatchee, WA | NQ1: Wheeling, WV-OH | NR1: Wichita, KS | NS1: Wichita Falls, TX | NT1: Wildwood-The Villages, FL | NU1: Williamsport, PA | NV1: Wilmington, NC | NW1: Winchester, VA-WV | NX1: Winston-Salem, NC | NY1: Worcester, MA | NZ1: Yakima, WA | OA1: York-Hanover, PA | OB1: Youngstown-Warren, OH | OC1: Yuba City, CA | OD1: Yuma, AZ
A2: Total: | B2: 180408 | C2: 251769 | D2: 699820 | E2: 146018 | F2: 130706 | G2: 906052 | H2: 921482 | I2: 149622 | J2: 873603 | K2: 121277 | L2: 271917 | M2: 127134 | N2: 162028 | O2: 401964 | P2: 369822 | Q2: 116090 | R2: 245768 | S2: 180767 | T2: 414711 | U2: 220197 | V2: 6256377 | W2: 371211 | X2: 199825 | Y2: 624181 | Z2: 2426592 | AA2: 915075 | AB2: 2849436 | AC2: 154710 | AD2: 231668 | AE2: 875313 | AF2: 133778 | AG2: 103008 | AH2: 396827 | AI2: 112714 | AJ2: 230503 | AK2: 257814 | AL2: 189255 | AM2: 245242 | AN2: 1184613 | AO2: 136216 | AP2: 181664 | AQ2: 171556 | AR2: 162569 | AS2: 811115 | AT2: 4953354 | AU2: 328961 | AV2: 186959 | AW2: 124074 | AX2: 277881 | AY2: 956330 | AZ2: 426120 | BA2: 115074 | BB2: 1161343 | BC2: 176893 | BD2: 227846 | BE2: 400372 | BF2: 817666 | BG2: 98169 | BH2: 58384 | BI2: 79977 | BJ2: 276624 | BK2: 157379 | BL2: 238842 | BM2: 205398 | BN2: 834267 | BO2: 2768407 | BP2: 224335 | BQ2: 575812 | BR2: 101060 | BS2: 9371595 | BT2: 207929 | BU2: 2270706 | BV2: 334564 | BW2: 2171526 | BX2: 128963 | BY2: 181996 | BZ2: 278335 | CA2: 767824 | CB2: 215014 | CC2: 849181 | CD2: 325615 | CE2: 83536 | CF2: 2175788 | CG2: 448012 | CH2: 96303 | CI2: 299547 | CJ2: 7985590 | CK2: 144160 | CL2: 246989 | CM2: 381503 | CN2: 816080 | CO2: 157747 | CP2: 101849 | CQ2: 706150 | CR2: 3002721 | CS2: 731120 | CT2: 4376828 | CU2: 152674 | CV2: 187604 | CW2: 99030 | CX2: 280870 | CY2: 601724 | CZ2: 58082 | DA2: 173915 | DB2: 180202 | DC2: 127049 | DD2: 207132 | DE2: 82147 | DF2: 874182 | DG2: 62146 | DH2: 269052 | DI2: 384207 | DJ2: 270494 | DK2: 95460 | DL2: 259459 | DM2: 120942 | DN2: 392380 | DO2: 577726 | DP2: 144508 | DQ2: 403305 | DR2: 199675 | DS2: 153852 | DT2: 104137 | DU2: 367368 | DV2: 229899 | DW2: 455416 | DX2: 1177665 | DY2: 103105 | DZ2: 349923 | EA2: 212705 | EB2: 106115 | EC2: 126039 | ED2: 118652 | EE2: 103628 | EF2: 76794 | EG2: 158601 | EH2: 1162152 | EI2: 88179 | EJ2: 84606 | EK2: 350396 | EL2: 331145 | EM2: 786419 | EN2: 177193 | EO2: 961939 | EP2: 66202 | EQ2: 421201 | ER2: 302649 | ES2: 136738 | ET2: 153298 | EU2: 604155 | EV2: 136992 | EW2: 1153112 | EX2: 155434 | EY2: 93906 | EZ2: 368316 | FA2: 227455 | FB2: 85771 | FC2: 162472 | FD2: 100035 | FE2: 202438 | FF2: 7442788 | FG2: 370729 | FH2: 516951 | FI2: 165361 | FJ2: 2130055 | FK2: 179200 | FL2: 104537 | FM2: 160060 | FN2: 611324 | FO2: 181719 | FP2: 1683960 | FQ2: 207906 | FR2: 164350 | FS2: 150437 | FT2: 210729 | FU2: 131538 | FV2: 135792 | FW2: 203626 | FX2: 164589 | FY2: 262375 | FZ2: 106635 | GA2: 2218142 | GB2: 311807 | GC2: 168438 | GD2: 494360 | GE2: 310842 | GF2: 182601 | GG2: 704836 | GH2: 932241 | GI2: 83752 | GJ2: 170190 | GK2: 413428 | GL2: 226805 | GM2: 244027 | GN2: 220517 | GO2: 790694 | GP2: 557931 | GQ2: 472669 | GR2: 269294 | GS2: 224266 | GT2: 2329548 | GU2: 120302 | GV2: 127310 | GW2: 144186 | GX2: 65164 | GY2: 113423 | GZ2: 522560 | HA2: 209439 | HB2: 101348 | HC2: 344337 | HD2: 758629 | HE2: 155102 | HF2: 291044 | HG2: 112360 | HH2: 12974487 | HI2: 1372558 | HJ2: 358708 | HK2: 263798 | HL2: 234943 | HM2: 691830 | HN2: 426378 | HO2: 133965 | HP2: 104282 | HQ2: 125099 | HR2: 209892 | HS2: 891977 | HT2: 222645 | HU2: 1341924 | HV2: 290201 | HW2: 6249291 | HX2: 111917 | HY2: 83757 | HZ2: 180019 | IA2: 1568938 | IB2: 3713668 | IC2: 76484 | ID2: 125631 | IE2: 412590 | IF2: 553990 | IG2: 223674 | IH2: 155505 | II2: 386024 | IJ2: 141323 | IK2: 122533 | IL2: 131328 | IM2: 112280 | IN2: 175961 | IO2: 383016 | IP2: 134869 | IQ2: 398291 | IR2: 2079596 | IS2: 570598 | IT2: 981662 | IU2: 19798537 | IV2: 153288 | IW2: 889339 | IX2: 279971 | IY2: 400078 | IZ2: 164654 | JA2: 653374 | JB2: 1463267 | JC2: 299067 | JD2: 982064 | JE2: 2793746 | JF2: 171769 | JG2: 112762 | JH2: 837469 | JI2: 102748 | JJ2: 632780 | JK2: 211922 | JL2: 88460 | JM2: 524395 | JN2: 365202 | JO2: 6272014 | JP2: 5028754 | JQ2: 104876 | JR2: 2439940 | JS2: 129430 | JT2: 89454 | JU2: 270459 | JV2: 562843 | JW2: 2520987 | JX2: 522676 | JY2: 245480 | JZ2: 1684071 | KA2: 717986 | KB2: 169356 | KC2: 201064 | KD2: 197532 | KE2: 1487302 | KF2: 152950 | KG2: 433015 | KH2: 181436 | KI2: 563020 | KJ2: 1341248 | KK2: 4675704 | KL2: 314986 | KM2: 228522 | KN2: 1058413 | KO2: 336522 | KP2: 144952 | KQ2: 99693 | KR2: 2426388 | KS2: 188665 | KT2: 202458 | KU2: 196431 | KV2: 120012 | KW2: 2810850 | KX2: 438906 | KY2: 437613 | KZ2: 129736 | LA2: 1275870 | LB2: 120986 | LC2: 2662733 | LD2: 3288774 | LE2: 114575 | LF2: 4645029 | LG2: 1969337 | LH2: 2052186 | LI2: 281555 | LJ2: 264926 | LK2: 156105 | LL2: 443701 | LM2: 485040 | LN2: 418285 | LO2: 569788 | LP2: 4061920 | LQ2: 166936 | LR2: 105702 | LS2: 117991 | LT2: 143337 | LU2: 386819 | LV2: 125566 | LW2: 144682 | LX2: 298181 | LY2: 272421 | LZ2: 324560 | MA2: 374737 | MB2: 597123 | MC2: 207042 | MD2: 462815 | ME2: 486785 | MF2: 135158 | MG2: 158576 | MH2: 126822 | MI2: 797334 | MJ2: 104725 | MK2: 656410 | ML2: 391730 | MM2: 3304691 | MN2: 168719 | MO2: 146296 | MP2: 602322 | MQ2: 232468 | MR2: 155449 | MS2: 385864 | MT2: 1060490 | MU2: 1037534 | MV2: 278526 | MW2: 118907 | MX2: 241740 | MY2: 1001146 | MZ2: 288881 | NA2: 150188 | NB2: 451918 | NC2: 98554 | ND2: 153305 | NE2: 1787235 | NF2: 478693 | NG2: 302045 | NH2: 62161 | NI2: 198209 | NJ2: 6318377 | NK2: 454969 | NL2: 168637 | NM2: 115040 | NN2: 138403 | NO2: 114754 | NP2: 124538 | NQ2: 136920 | NR2: 652622 | NS2: 149358 | NT2: 143408 | NU2: 113489 | NV2: 453347 | NW2: 146386 | NX2: 689766 | NY2: 867788 | NZ2: 257152 | OA2: 462924 | OB2: 427420 | OC2: 183364 | OD2: 211741
A3: Male: | B3: 91928 | C3: 121763 | D3: 341672 | E3: 68992 | F3: 65202 | G3: 446223 | H3: 454609 | I3: 74183 | J3: 432307 | K3: 59834 | L3: 136515 | M3: 66260 | N3: 75413 | O3: 206814 | P3: 184472 | Q3: 56174 | R3: 123857 | S3: 85915 | T3: 200585 | U3: 106519 | V3: 3036071 | W3: 180426 | X3: 98089 | Y3: 304383 | Z3: 1226850 | AA3: 465565 | AB3: 1376674 | AC3: 76849 | AD3: 111539 | AE3: 429375 | AF3: 66004 | AG3: 51098 | AH3: 201348 | AI3: 56800 | AJ3: 114239 | AK3: 128711 | AL3: 94065 | AM3: 121542 | AN3: 571470 | AO3: 68633 | AP3: 91355 | AQ3: 83855 | AR3: 81314 | AS3: 407870 | AT3: 2422844 | AU3: 165850 | AV3: 92772 | AW3: 64951 | AX3: 142590 | AY3: 469672 | AZ3: 210378 | BA3: 55017 | BB3: 566263 | BC3: 84742 | BD3: 112320 | BE3: 196306 | BF3: 402006 | BG3: 48202 | BH3: 30377 | BI3: 40441 | BJ3: 137510 | BK3: 77811 | BL3: 118854 | BM3: 100276 | BN3: 408201 | BO3: 1351259 | BP3: 107855 | BQ3: 280915 | BR3: 51357 | BS3: 4613694 | BT3: 103536 | BU3: 1121000 | BV3: 168283 | BW3: 1058278 | BX3: 63138 | BY3: 90899 | BZ3: 139879 | CA3: 390315 | CB3: 104673 | CC3: 411321 | CD3: 159736 | CE3: 42297 | CF3: 1078242 | CG3: 223223 | CH3: 48531 | CI3: 151773 | CJ3: 3954206 | CK3: 72055 | CL3: 120360 | CM3: 188896 | CN3: 398724 | CO3: 78295 | CP3: 49036 | CQ3: 344959 | CR3: 1513294 | CS3: 364958 | CT3: 2145311 | CU3: 73689 | CV3: 90210 | CW3: 49148 | CX3: 142558 | CY3: 288699 | CZ3: 29073 | DA3: 87781 | DB3: 92641 | DC3: 62959 | DD3: 102892 | DE3: 40844 | DF3: 435242 | DG3: 31128 | DH3: 133693 | DI3: 189618 | DJ3: 132776 | DK3: 52108 | DL3: 130898 | DM3: 59628 | DN3: 194403 | DO3: 290060 | DP3: 71308 | DQ3: 195402 | DR3: 94186 | DS3: 74147 | DT3: 51843 | DU3: 183519 | DV3: 113308 | DW3: 224529 | DX3: 588769 | DY3: 50075 | DZ3: 169664 | EA3: 106430 | EB3: 52832 | EC3: 63668 | ED3: 59094 | EE3: 53374 | EF3: 39262 | EG3: 78451 | EH3: 582691 | EI3: 43030 | EJ3: 43121 | EK3: 177898 | EL3: 166326 | EM3: 377782 | EN3: 83197 | EO3: 469120 | EP3: 32074 | EQ3: 206624 | ER3: 152858 | ES3: 66771 | ET3: 84750 | EU3: 298627 | EV3: 67354 | EW3: 565606 | EX3: 73967 | EY3: 46733 | EZ3: 183017 | FA3: 112883 | FB3: 43453 | FC3: 79798 | FD3: 48267 | FE3: 100217 | FF3: 3697808 | FG3: 182466 | FH3: 255573 | FI3: 83286 | FJ3: 1046919 | FK3: 89099 | FL3: 50893 | FM3: 82097 | FN3: 293506 | FO3: 87267 | FP3: 822744 | FQ3: 114477 | FR3: 81804 | FS3: 76643 | FT3: 103494 | FU3: 65599 | FV3: 66152 | FW3: 100213 | FX3: 81991 | FY3: 128637 | FZ3: 52797 | GA3: 1096131 | GB3: 158285 | GC3: 83494 | GD3: 246621 | GE3: 153389 | GF3: 90817 | GG3: 351185 | GH3: 459458 | GI3: 40525 | GJ3: 84407 | GK3: 201830 | GL3: 116253 | GM3: 119751 | GN3: 111453 | GO3: 389873 | GP3: 274372 | GQ3: 232167 | GR3: 133726 | GS3: 110735 | GT3: 1165712 | GU3: 59656 | GV3: 65841 | GW3: 71185 | GX3: 32320 | GY3: 55895 | GZ3: 257124 | HA3: 105079 | HB3: 50605 | HC3: 173391 | HD3: 367547 | HE3: 78131 | HF3: 144582 | HG3: 56077 | HH3: 6426049 | HI3: 674888 | HJ3: 178045 | HK3: 127396 | HL3: 112820 | HM3: 347291 | HN3: 213975 | HO3: 70216 | HP3: 52728 | HQ3: 64040 | HR3: 99646 | HS3: 440466 | HT3: 109169 | HU3: 641979 | HV3: 147232 | HW3: 3062310 | HX3: 58096 | HY3: 41776 | HZ3: 92062 | IA3: 769287 | IB3: 1851989 | IC3: 39782 | ID3: 63159 | IE3: 197311 | IF3: 276407 | IG3: 108248 | IH3: 77504 | II3: 184023 | IJ3: 73592 | IK3: 60229 | IL3: 65387 | IM3: 54278 | IN3: 87788 | IO3: 185457 | IP3: 67434 | IQ3: 196300 | IR3: 1022167 | IS3: 275802 | IT3: 472931 | IU3: 9647694 | IV3: 75376 | IW3: 428920 | IX3: 140096 | IY3: 193338 | IZ3: 84466 | JA3: 331220 | JB3: 723471 | JC3: 146977 | JD3: 489981 | JE3: 1371906 | JF3: 87239 | JG3: 55315 | JH3: 416606 | JI3: 50367 | JJ3: 311716 | JK3: 106100 | JL3: 43408 | JM3: 262307 | JN3: 179904 | JO3: 3046206 | JP3: 2510733 | JQ3: 51351 | JR3: 1199000 | JS3: 63381 | JT3: 44850 | JU3: 128612 | JV3: 275553 | JW3: 1255791 | JX3: 257453 | JY3: 120844 | JZ3: 825294 | KA3: 364551 | KB3: 84054 | KC3: 98902 | KD3: 98405 | KE3: 729358 | KF3: 78284 | KG3: 214748 | KH3: 89288 | KI3: 286904 | KJ3: 651491 | KK3: 2342638 | KL3: 151863 | KM3: 112663 | KN3: 517728 | KO3: 165410 | KP3: 69276 | KQ3: 48820 | KR3: 1194559 | KS3: 92054 | KT3: 102408 | KU3: 97874 | KV3: 61062 | KW3: 1371757 | KX3: 219536 | KY3: 223242 | KZ3: 64134 | LA3: 645743 | LB3: 60480 | LC3: 1323954 | LD3: 1662238 | LE3: 56710 | LF3: 2314748 | LG3: 1003293 | LH3: 962432 | LI3: 141966 | LJ3: 132027 | LK3: 76208 | LL3: 222371 | LM3: 238643 | LN3: 202819 | LO3: 282767 | LP3: 2052180 | LQ3: 80832 | LR3: 51698 | LS3: 59992 | LT3: 70117 | LU3: 186329 | LV3: 63772 | LW3: 73040 | LX3: 150871 | LY3: 133315 | LZ3: 159295 | MA3: 182445 | MB3: 298250 | MC3: 100036 | MD3: 225126 | ME3: 239162 | MF3: 66310 | MG3: 83539 | MH3: 62926 | MI3: 399104 | MJ3: 50561 | MK3: 321414 | ML3: 189015 | MM3: 1615614 | MN3: 85823 | MO3: 72964 | MP3: 294452 | MQ3: 114348 | MR3: 77438 | MS3: 190728 | MT3: 524257 | MU3: 512706 | MV3: 134700 | MW3: 59428 | MX3: 117074 | MY3: 505293 | MZ3: 144481 | NA3: 72185 | NB3: 225472 | NC3: 48602 | ND3: 78123 | NE3: 877211 | NF3: 239638 | NG3: 147860 | NH3: 31546 | NI3: 96254 | NJ3: 3107522 | NK3: 222483 | NL3: 83085 | NM3: 60361 | NN3: 69850 | NO3: 56450 | NP3: 63418 | NQ3: 69363 | NR3: 324999 | NS3: 77088 | NT3: 71000 | NU3: 56006 | NV3: 218532 | NW3: 73606 | NX3: 333335 | NY3: 431017 | NZ3: 128913 | OA3: 230316 | OB3: 210044 | OC3: 92245 | OD3: 109174
A4: Under 5 years | B4: 5805 | C4: 3845 | D4: 18026 | E4: 4553 | F4: 3662 | G4: 22469 | H4: 23029 | I4: 4814 | J4: 22726 | K4: 3083 | L4: 8498 | M4: 2944 | N4: 2467 | O4: 12938 | P4: 8673 | Q4: 3472 | R4: 6976 | S4: 2696 | T4: 9477 | U4: 5533 | V4: 185569 | W4: 9094 | X4: 5375 | Y4: 18846 | Z4: 71601 | AA4: 32913 | AB4: 82965 | AC4: 3322 | AD4: 4080 | AE4: 27266 | AF4: 3968 | AG4: 2468 | AH4: 12891 | AI4: 2781 | AJ4: 5297 | AK4: 6003 | AL4: 5202 | AM4: 5994 | AN4: 35116 | AO4: 3768 | AP4: 3574 | AQ4: 4499 | AR4: 3550 | AS4: 23235 | AT4: 127203 | AU4: 6431 | AV4: 5970 | AW4: 2850 | AX4: 7533 | AY4: 26149 | AZ4: 15370 | BA4: 2907 | BB4: 30619 | BC4: 5107 | BD4: 5319 | BE4: 11035 | BF4: 18652 | BG4: 2913 | BH4: 1379 | BI4: 2274 | BJ4: 8028 | BK4: 4416 | BL4: 6304 | BM4: 5126 | BN4: 24779 | BO4: 84123 | BP4: 5836 | BQ4: 16471 | BR4: 2781 | BS4: 260700 | BT4: 5550 | BU4: 68650 | BV4: 13719 | BW4: 58438 | BX4: 3596 | BY4: 5160 | BZ4: 7689 | CA4: 23932 | CB4: 5837 | CC4: 24202 | CD4: 10491 | CE4: 2710 | CF4: 68823 | CG4: 13861 | CH4: 1860 | CI4: 9237 | CJ4: 260307 | CK4: 4450 | CL4: 6492 | CM4: 10843 | CN4: 23720 | CO4: 4942 | CP4: 3171 | CQ4: 15352 | CR4: 83630 | CS4: 23838 | CT4: 124692 | CU4: 4471 | CV4: 5607 | CW4: 3022 | CX4: 6708 | CY4: 15758 | CZ4: 2616 | DA4: 4577 | DB4: 6443 | DC4: 3911 | DD4: 7734 | DE4: 2137 | DF4: 29448 | DG4: 1934 | DH4: 7072 | DI4: 8357 | DJ4: 7754 | DK4: 3527 | DL4: 8290 | DM4: 3436 | DN4: 14751 | DO4: 19206 | DP4: 3430 | DQ4: 11452 | DR4: 5971 | DS4: 4309 | DT4: 2763 | DU4: 8149 | DV4: 7169 | DW4: 15430 | DX4: 41656 | DY4: 3030 | DZ4: 8411 | EA4: 6562 | EB4: 2521 | EC4: 2847 | ED4: 3858 | EE4: 3334 | EF4: 2976 | EG4: 3901 | EH4: 34689 | EI4: 2038 | EJ4: 2460 | EK4: 12141 | EL4: 9454 | EM4: 22009 | EN4: 4902 | EO4: 28041 | EP4: 1178 | EQ4: 12719 | ER4: 8585 | ES4: 4898 | ET4: 5505 | EU4: 17209 | EV4: 4092 | EW4: 29230 | EX4: 4771 | EY4: 2447 | EZ4: 9849 | FA4: 5416 | FB4: 3902 | FC4: 3006 | FD4: 2556 | FE4: 6373 | FF4: 250813 | FG4: 9778 | FH4: 14880 | FI4: 5984 | FJ4: 68650 | FK4: 5174 | FL4: 1928 | FM4: 4303 | FN4: 18948 | FO4: 5333 | FP4: 48990 | FQ4: 8542 | FR4: 4841 | FS4: 4435 | FT4: 4836 | FU4: 3191 | FV4: 4556 | FW4: 6418 | FX4: 4582 | FY4: 7274 | FZ4: 3089 | GA4: 68334 | GB4: 10901 | GC4: 4458 | GD4: 18688 | GE4: 7265 | GF4: 4075 | GG4: 20766 | GH4: 24875 | GI4: 2510 | GJ4: 4412 | GK4: 13750 | GL4: 6251 | GM4: 8190 | GN4: 4538 | GO4: 22700 | GP4: 17876 | GQ4: 12371 | GR4: 11062 | GS4: 6726 | GT4: 66860 | GU4: 2684 | GV4: 4234 | GW4: 4134 | GX4: 1770 | GY4: 3043 | GZ4: 15468 | HA4: 6210 | HB4: 3107 | HC4: 10205 | HD4: 23124 | HE4: 6015 | HF4: 8993 | HG4: 3278 | HH4: 340660 | HI4: 41254 | HJ4: 11444 | HK4: 6418 | HL4: 7258 | HM4: 17978 | HN4: 10888 | HO4: 4792 | HP4: 2660 | HQ4: 3544 | HR4: 3170 | HS4: 35616 | HT4: 5586 | HU4: 44209 | HV4: 10545 | HW4: 168822 | HX4: 3106 | HY4: 2289 | HZ4: 7712 | IA4: 46372 | IB4: 112823 | IC4: 2632 | ID4: 3074 | IE4: 13436 | IF4: 18670 | IG4: 6960 | IH4: 4050 | II4: 12346 | IJ4: 3294 | IK4: 3255 | IL4: 3566 | IM4: 2764 | IN4: 5113 | IO4: 8275 | IP4: 3049 | IQ4: 8255 | IR4: 65158 | IS4: 14503 | IT4: 29478 | IU4: 573248 | IV4: 4121 | IW4: 17245 | IX4: 6861 | IY4: 9744 | IZ4: 7289 | JA4: 22831 | JB4: 45735 | JC4: 8185 | JD4: 32664 | JE4: 77448 | JF4: 4586 | JG4: 3581 | JH4: 22417 | JI4: 2914 | JJ4: 14086 | JK4: 5863 | JL4: 2358 | JM4: 14583 | JN4: 11044 | JO4: 175431 | JP4: 143528 | JQ4: 3102 | JR4: 60557 | JS4: 2594 | JT4: 2768 | JU4: 4667 | JV4: 13100 | JW4: 65116 | JX4: 12139 | JY4: 4616 | JZ4: 42135 | KA4: 31041 | KB4: 4558 | KC4: 2869 | KD4: 5817 | KE4: 43883 | KF4: 4456 | KG4: 12122 | KH4: 4791 | KI4: 15206 | KJ4: 38550 | KK4: 145131 | KL4: 7803 | KM4: 7148 | KN4: 27240 | KO4: 10194 | KP4: 4153 | KQ4: 3000 | KR4: 69101 | KS4: 5281 | KT4: 6543 | KU4: 5870 | KV4: 3496 | KW4: 79579 | KX4: 12779 | KY4: 14373 | KZ4: 4060 | LA4: 42023 | LB4: 3862 | LC4: 84528 | LD4: 93974 | LE4: 2530 | LF4: 118706 | LG4: 53117 | LH4: 33288 | LI4: 6202 | LJ4: 5840 | LK4: 2904 | LL4: 13760 | LM4: 11480 | LN4: 12863 | LO4: 15025 | LP4: 115944 | LQ4: 3283 | LR4: 2086 | LS4: 3202 | LT4: 4433 | LU4: 12144 | LV4: 3195 | LW4: 4932 | LX4: 10360 | LY4: 7934 | LZ4: 9693 | MA4: 11421 | MB4: 16817 | MC4: 5857 | MD4: 12408 | ME4: 14513 | MF4: 3989 | MG4: 2908 | MH4: 3295 | MI4: 26263 | MJ4: 3571 | MK4: 17463 | ML4: 10231 | MM4: 83232 | MN4: 4633 | MO4: 4250 | MP4: 17540 | MQ4: 6795 | MR4: 3699 | MS4: 11119 | MT4: 26598 | MU4: 33207 | MV4: 7864 | MW4: 3912 | MX4: 7732 | MY4: 29195 | MZ4: 7953 | NA4: 4983 | NB4: 13190 | NC4: 3306 | ND4: 4834 | NE4: 54341 | NF4: 17659 | NG4: 9507 | NH4: 1508 | NI4: 6091 | NJ4: 192077 | NK4: 11854 | NL4: 5072 | NM4: 4269 | NN4: 3806 | NO4: 2772 | NP4: 3723 | NQ4: 3366 | NR4: 20654 | NS4: 4547 | NT4: 1122 | NU4: 2990 | NV4: 10356 | NW4: 3921 | NX4: 19344 | NY4: 23089 | NZ4: 9295 | OA4: 12934 | OB4: 11770 | OC4: 6353 | OD4: 7143
A5: 5 to 9 years | B5: 6278 | C5: 5333 | D5: 20721 | E5: 4534 | F5: 4204 | G5: 26263 | H5: 26240 | I5: 5057 | J5: 25089 | K5: 3270 | L5: 9662 | M5: 3192 | N5: 3205 | O5: 14228 | P5: 9195 | Q5: 3442 | R5: 8143 | S5: 3833 | T5: 11474 | U5: 6596 | V5: 202535 | W5: 10054 | X5: 5375 | Y5: 19768 | Z5: 73158 | AA5: 36390 | AB5: 86911 | AC5: 4012 | AD5: 4632 | AE5: 30286 | AF5: 4477 | AG5: 3112 | AH5: 14086 | AI5: 3167 | AJ5: 6615 | AK5: 6959 | AL5: 6259 | AM5: 6089 | AN5: 37525 | AO5: 4485 | AP5: 3792 | AQ5: 4626 | AR5: 3821 | AS5: 25872 | AT5: 134486 | AU5: 7985 | AV5: 5854 | AW5: 3008 | AX5: 7990 | AY5: 28432 | AZ5: 17970 | BA5: 2706 | BB5: 33547 | BC5: 5174 | BD5: 5657 | BE5: 11995 | BF5: 18498 | BG5: 2823 | BH5: 1548 | BI5: 2681 | BJ5: 7920 | BK5: 5560 | BL5: 6572 | BM5: 5243 | BN5: 25514 | BO5: 87779 | BP5: 6287 | BQ5: 16657 | BR5: 3333 | BS5: 291451 | BT5: 6495 | BU5: 75205 | BV5: 13610 | BW5: 63981 | BX5: 3861 | BY5: 6352 | BZ5: 8423 | CA5: 24287 | CB5: 6748 | CC5: 26155 | CD5: 12153 | CE5: 2710 | CF5: 71690 | CG5: 15825 | CH5: 1958 | CI5: 9586 | CJ5: 278758 | CK5: 4655 | CL5: 7226 | CM5: 12628 | CN5: 26165 | CO5: 5010 | CP5: 3352 | CQ5: 16855 | CR5: 85777 | CS5: 25612 | CT5: 132702 | CU5: 5294 | CV5: 6987 | CW5: 3599 | CX5: 7455 | CY5: 15096 | CZ5: 2089 | DA5: 4688 | DB5: 6339 | DC5: 4109 | DD5: 7635 | DE5: 2285 | DF5: 29778 | DG5: 2417 | DH5: 6918 | DI5: 9346 | DJ5: 8587 | DK5: 3391 | DL5: 8652 | DM5: 4164 | DN5: 14671 | DO5: 20457 | DP5: 4045 | DQ5: 12498 | DR5: 6276 | DS5: 4366 | DT5: 2641 | DU5: 9132 | DV5: 8500 | DW5: 15941 | DX5: 44849 | DY5: 3138 | DZ5: 8297 | EA5: 6660 | EB5: 2943 | EC5: 3271 | ED5: 4150 | EE5: 3383 | EF5: 2967 | EG5: 4457 | EH5: 38552 | EI5: 2073 | EJ5: 2858 | EK5: 11992 | EL5: 10328 | EM5: 25496 | EN5: 5157 | EO5: 30737 | EP5: 1213 | EQ5: 12693 | ER5: 9073 | ES5: 4385 | ET5: 5672 | EU5: 18007 | EV5: 3681 | EW5: 30311 | EX5: 4849 | EY5: 2724 | EZ5: 10217 | FA5: 5160 | FB5: 3134 | FC5: 4160 | FD5: 2903 | FE5: 6319 | FF5: 274657 | FG5: 11665 | FH5: 15446 | FI5: 7679 | FJ5: 73856 | FK5: 5792 | FL5: 2082 | FM5: 5025 | FN5: 18673 | FO5: 5161 | FP5: 52784 | FQ5: 7256 | FR5: 5751 | FS5: 4353 | FT5: 5573 | FU5: 3702 | FV5: 4611 | FW5: 7228 | FX5: 4401 | FY5: 7891 | FZ5: 3264 | GA5: 74452 | GB5: 11989 | GC5: 5209 | GD5: 19523 | GE5: 7612 | GF5: 4096 | GG5: 21313 | GH5: 26443 | GI5: 2772 | GJ5: 4562 | GK5: 13923 | GL5: 6015 | GM5: 8058 | GN5: 5252 | GO5: 23574 | GP5: 18071 | GQ5: 13500 | GR5: 12878 | GS5: 6582 | GT5: 71228 | GU5: 3441 | GV5: 4083 | GW5: 4430 | GX5: 1883 | GY5: 3247 | GZ5: 16862 | HA5: 7704 | HB5: 3471 | HC5: 10710 | HD5: 24772 | HE5: 7046 | HF5: 9427 | HG5: 3762 | HH5: 367253 | HI5: 42864 | HJ5: 12245 | HK5: 7740 | HL5: 7078 | HM5: 19589 | HN5: 11278 | HO5: 4105 | HP5: 2915 | HQ5: 3606 | HR5: 4170 | HS5: 37595 | HT5: 7093 | HU5: 47495 | HV5: 11693 | HW5: 170581 | HX5: 3507 | HY5: 2473 | HZ5: 8230 | IA5: 50285 | IB5: 122710 | IC5: 2750 | ID5: 2775 | IE5: 12719 | IF5: 20448 | IG5: 7599 | IH5: 4853 | II5: 12641 | IJ5: 3168 | IK5: 3790 | IL5: 3944 | IM5: 2920 | IN5: 5457 | IO5: 8580 | IP5: 3700 | IQ5: 8308 | IR5: 66579 | IS5: 14988 | IT5: 29624 | IU5: 574452 | IV5: 4955 | IW5: 18389 | IX5: 7262 | IY5: 9082 | IZ5: 7681 | JA5: 27719 | JB5: 50379 | JC5: 8596 | JD5: 34860 | JE5: 85453 | JF5: 5042 | JG5: 3921 | JH5: 24851 | JI5: 3522 | JJ5: 15897 | JK5: 5863 | JL5: 2810 | JM5: 16938 | JN5: 12552 | JO5: 184851 | JP5: 156347 | JQ5: 3073 | JR5: 65222 | JS5: 3039 | JT5: 3378 | JU5: 6329 | JV5: 14285 | JW5: 72664 | JX5: 13324 | JY5: 5039 | JZ5: 44710 | KA5: 31378 | KB5: 5018 | KC5: 3490 | KD5: 6843 | KE5: 48472 | KF5: 4776 | KG5: 13929 | KH5: 5491 | KI5: 16575 | KJ5: 40683 | KK5: 160115 | KL5: 8179 | KM5: 7637 | KN5: 29877 | KO5: 10732 | KP5: 4977 | KQ5: 3115 | KR5: 73919 | KS5: 5540 | KT5: 6891 | KU5: 6596 | KV5: 3895 | KW5: 86449 | KX5: 14356 | KY5: 15858 | KZ5: 4234 | LA5: 45580 | LB5: 4591 | LC5: 92593 | LD5: 95405 | LE5: 3030 | LF5: 122288 | LG5: 56332 | LH5: 44479 | LI5: 6500 | LJ5: 6761 | LK5: 3712 | LL5: 13800 | LM5: 13048 | LN5: 13954 | LO5: 15794 | LP5: 122214 | LQ5: 3606 | LR5: 2466 | LS5: 3353 | LT5: 4873 | LU5: 12040 | LV5: 4055 | LW5: 5001 | LX5: 10675 | LY5: 9723 | LZ5: 10566 | MA5: 12620 | MB5: 18887 | MC5: 6355 | MD5: 12496 | ME5: 16115 | MF5: 4593 | MG5: 3437 | MH5: 3761 | MI5: 28725 | MJ5: 3461 | MK5: 18812 | ML5: 10354 | MM5: 87568 | MN5: 4905 | MO5: 4520 | MP5: 19631 | MQ5: 7530 | MR5: 3649 | MS5: 11954 | MT5: 30295 | MU5: 34904 | MV5: 8748 | MW5: 4370 | MX5: 9001 | MY5: 29982 | MZ5: 8764 | NA5: 4413 | NB5: 13894 | NC5: 3175 | ND5: 5407 | NE5: 55858 | NF5: 19840 | NG5: 10366 | NH5: 1824 | NI5: 7446 | NJ5: 203096 | NK5: 12597 | NL5: 5279 | NM5: 4155 | NN5: 4036 | NO5: 3243 | NP5: 4080 | NQ5: 3897 | NR5: 21645 | NS5: 4807 | NT5: 1512 | NU5: 3728 | NV5: 10364 | NW5: 4783 | NX5: 20200 | NY5: 24398 | NZ5: 10535 | OA5: 14163 | OB5: 12050 | OC5: 7345 | OD5: 7640
A6: 10 to 14 years | B6: 5839 | C6: 6601 | D6: 19913 | E6: 5553 | F6: 4109 | G6: 24133 | H6: 30002 | I6: 5528 | J6: 26988 | K6: 3897 | L6: 10186 | M6: 3038 | N6: 3586 | O6: 14081 | P6: 10175 | Q6: 3598 | R6: 8423 | S6: 4658 | T6: 10045 | U6: 6321 | V6: 221291 | W6: 11465 | X6: 6368 | Y6: 21137 | Z6: 79205 | AA6: 40352 | AB6: 94075 | AC6: 4016 | AD6: 4609 | AE6: 28391 | AF6: 4438 | AG6: 2826 | AH6: 14789 | AI6: 3973 | AJ6: 6185 | AK6: 7873 | AL6: 6328 | AM6: 7857 | AN6: 40814 | AO6: 5061 | AP6: 4483 | AQ6: 5879 | AR6: 4005 | AS6: 29919 | AT6: 138278 | AU6: 8936 | AV6: 6382 | AW6: 4029 | AX6: 7792 | AY6: 31319 | AZ6: 17698 | BA6: 4180 | BB6: 33909 | BC6: 6145 | BD6: 6090 | BE6: 12897 | BF6: 21618 | BG6: 3320 | BH6: 1933 | BI6: 2986 | BJ6: 9864 | BK6: 4474 | BL6: 6706 | BM6: 6747 | BN6: 26045 | BO6: 96366 | BP6: 5967 | BQ6: 18139 | BR6: 3353 | BS6: 304545 | BT6: 6000 | BU6: 76097 | BV6: 11484 | BW6: 65913 | BX6: 3970 | BY6: 5696 | BZ6: 7879 | CA6: 26280 | CB6: 5925 | CC6: 27741 | CD6: 10491 | CE6: 3193 | CF6: 74424 | CG6: 14906 | CH6: 2463 | CI6: 9303 | CJ6: 298968 | CK6: 5413 | CL6: 8054 | CM6: 12393 | CN6: 25653 | CO6: 5693 | CP6: 3292 | CQ6: 18296 | CR6: 95065 | CS6: 26360 | CT6: 140516 | CU6: 4634 | CV6: 5507 | CW6: 2737 | CX6: 8242 | CY6: 18420 | CZ6: 3144 | DA6: 5590 | DB6: 8684 | DC6: 4959 | DD6: 8441 | DE6: 2748 | DF6: 36102 | DG6: 2323 | DH6: 9236 | DI6: 10536 | DJ6: 8718 | DK6: 3386 | DL6: 8577 | DM6: 4609 | DN6: 13383 | DO6: 20370 | DP6: 4106 | DQ6: 13464 | DR6: 7054 | DS6: 4533 | DT6: 3638 | DU6: 10585 | DV6: 7207 | DW6: 17125 | DX6: 50942 | DY6: 3405 | DZ6: 10226 | EA6: 7807 | EB6: 3245 | EC6: 3466 | ED6: 3849 | EE6: 3326 | EF6: 2941 | EG6: 4869 | EH6: 39078 | EI6: 2941 | EJ6: 2894 | EK6: 13748 | EL6: 11277 | EM6: 24109 | EN6: 5639 | EO6: 30955 | EP6: 2068 | EQ6: 15214 | ER6: 10110 | ES6: 5040 | ET6: 6184 | EU6: 19628 | EV6: 4253 | EW6: 34178 | EX6: 5617 | EY6: 2884 | EZ6: 11243 | FA6: 6312 | FB6: 3449 | FC6: 3352 | FD6: 2809 | FE6: 7696 | FF6: 283814 | FG6: 11022 | FH6: 16582 | FI6: 7032 | FJ6: 77618 | FK6: 4471 | FL6: 2128 | FM6: 4757 | FN6: 22329 | FO6: 6722 | FP6: 55620 | FQ6: 6871 | FR6: 4966 | FS6: 5061 | FT6: 5573 | FU6: 3675 | FV6: 5306 | FW6: 6958 | FX6: 6000 | FY6: 8420 | FZ6: 3691 | GA6: 77836 | GB6: 13267 | GC6: 5559 | GD6: 17618 | GE6: 9284 | GF6: 4717 | GG6: 23958 | GH6: 28497 | GI6: 2759 | GJ6: 5644 | GK6: 14833 | GL6: 7440 | GM6: 9436 | GN6: 4979 | GO6: 26989 | GP6: 18885 | GQ6: 13840 | GR6: 11603 | GS6: 8411 | GT6: 79375 | GU6: 2767 | GV6: 4598 | GW6: 5093 | GX6: 1951 | GY6: 3586 | GZ6: 16153 | HA6: 6788 | HB6: 3477 | HC6: 11794 | HD6: 26318 | HE6: 6101 | HF6: 11192 | HG6: 3692 | HH6: 416259 | HI6: 45747 | HJ6: 12195 | HK6: 7347 | HL6: 8851 | HM6: 20863 | HN6: 12729 | HO6: 4451 | HP6: 3379 | HQ6: 4183 | HR6: 5595 | HS6: 43415 | HT6: 6454 | HU6: 48808 | HV6: 12912 | HW6: 183995 | HX6: 3450 | HY6: 2853 | HZ6: 7062 | IA6: 51783 | IB6: 126723 | IC6: 2486 | ID6: 3804 | IE6: 14274 | IF6: 22476 | IG6: 7906 | IH6: 4708 | II6: 12986 | IJ6: 3585 | IK6: 4036 | IL6: 4071 | IM6: 2900 | IN6: 6017 | IO6: 10078 | IP6: 3910 | IQ6: 10200 | IR6: 68996 | IS6: 16850 | IT6: 31812 | IU6: 623285 | IV6: 4514 | IW6: 21973 | IX6: 8436 | IY6: 12880 | IZ6: 6535 | JA6: 28307 | JB6: 52512 | JC6: 9934 | JD6: 36800 | JE6: 86534 | JF6: 5016 | JG6: 4072 | JH6: 28229 | JI6: 3139 | JJ6: 17620 | JK6: 7073 | JL6: 2507 | JM6: 15397 | JN6: 12057 | JO6: 199877 | JP6: 169314 | JQ6: 3634 | JR6: 67055 | JS6: 2846 | JT6: 3277 | JU6: 7843 | JV6: 15148 | JW6: 77201 | JX6: 14427 | JY6: 5912 | JZ6: 49441 | KA6: 34208 | KB6: 5789 | KC6: 3444 | KD6: 6245 | KE6: 51491 | KF6: 4473 | KG6: 13738 | KH6: 6169 | KI6: 17135 | KJ6: 41831 | KK6: 178034 | KL6: 10040 | KM6: 8137 | KN6: 31781 | KO6: 12320 | KP6: 4303 | KQ6: 3363 | KR6: 82940 | KS6: 6234 | KT6: 7089 | KU6: 7599 | KV6: 3877 | KW6: 91407 | KX6: 15280 | KY6: 16768 | KZ6: 3948 | LA6: 48998 | LB6: 3792 | LC6: 95201 | LD6: 103193 | LE6: 3309 | LF6: 133317 | LG6: 61020 | LH6: 53216 | LI6: 7768 | LJ6: 7509 | LK6: 3527 | LL6: 14472 | LM6: 13645 | LN6: 13173 | LO6: 17511 | LP6: 122453 | LQ6: 3551 | LR6: 2629 | LS6: 4000 | LT6: 5068 | LU6: 14825 | LV6: 3447 | LW6: 5923 | LX6: 11623 | LY6: 8837 | LZ6: 10703 | MA6: 12203 | MB6: 18631 | MC6: 6812 | MD6: 15510 | ME6: 15619 | MF6: 4263 | MG6: 3236 | MH6: 3275 | MI6: 32757 | MJ6: 3556 | MK6: 20533 | ML6: 11152 | MM6: 98198 | MN6: 5341 | MO6: 5757 | MP6: 19034 | MQ6: 8123 | MR6: 4755 | MS6: 12818 | MT6: 30017 | MU6: 38823 | MV6: 7924 | MW6: 5164 | MX6: 7950 | MY6: 30289 | MZ6: 9180 | NA6: 5928 | NB6: 14769 | NC6: 3817 | ND6: 5384 | NE6: 57380 | NF6: 22070 | NG6: 10126 | NH6: 1959 | NI6: 7044 | NJ6: 211834 | NK6: 13814 | NL6: 5295 | NM6: 3629 | NN6: 4981 | NO6: 3184 | NP6: 4666 | NQ6: 3664 | NR6: 25335 | NS6: 5049 | NT6: 1395 | NU6: 2985 | NV6: 12340 | NW6: 4661 | NX6: 23521 | NY6: 27295 | NZ6: 11383 | OA6: 15488 | OB6: 12817 | OC6: 6518 | OD6: 7189
A7: 15 to 17 years | B7: 3702 | C7: 4380 | D7: 12989 | E7: 3390 | F7: 2888 | G7: 15816 | H7: 18292 | I7: 3312 | J7: 17284 | K7: 2235 | L7: 6365 | M7: 2120 | N7: 2639 | O7: 8251 | P7: 6485 | Q7: 2290 | R7: 5390 | S7: 3272 | T7: 7215 | U7: 4114 | V7: 140302 | W7: 6863 | X7: 3862 | Y7: 13380 | Z7: 46853 | AA7: 23674 | AB7: 56165 | AC7: 2739 | AD7: 3435 | AE7: 18681 | AF7: 3087 | AG7: 2096 | AH7: 8385 | AI7: 2237 | AJ7: 3884 | AK7: 4602 | AL7: 3909 | AM7: 4480 | AN7: 24515 | AO7: 2840 | AP7: 2696 | AQ7: 3221 | AR7: 2576 | AS7: 18429 | AT7: 89637 | AU7: 5988 | AV7: 3732 | AW7: 2072 | AX7: 4780 | AY7: 20629 | AZ7: 11476 | BA7: 2146 | BB7: 20912 | BC7: 3547 | BD7: 4105 | BE7: 8260 | BF7: 13171 | BG7: 1887 | BH7: 1094 | BI7: 1867 | BJ7: 5519 | BK7: 3376 | BL7: 4247 | BM7: 4003 | BN7: 15617 | BO7: 58786 | BP7: 3890 | BQ7: 11112 | BR7: 2036 | BS7: 195324 | BT7: 3888 | BU7: 48185 | BV7: 6754 | BW7: 41972 | BX7: 2625 | BY7: 3864 | BZ7: 4848 | CA7: 15461 | CB7: 3946 | CC7: 17726 | CD7: 6451 | CE7: 1680 | CF7: 43758 | CG7: 9780 | CH7: 1618 | CI7: 5668 | CJ7: 183770 | CK7: 3438 | CL7: 4941 | CM7: 7915 | CN7: 16302 | CO7: 3309 | CP7: 2029 | CQ7: 11310 | CR7: 58897 | CS7: 15879 | CT7: 88358 | CU7: 3306 | CV7: 3691 | CW7: 1921 | CX7: 5149 | CY7: 10622 | CZ7: 1433 | DA7: 3203 | DB7: 4481 | DC7: 2464 | DD7: 5104 | DE7: 1522 | DF7: 20489 | DG7: 1413 | DH7: 5252 | DI7: 6304 | DJ7: 5328 | DK7: 1944 | DL7: 4582 | DM7: 2939 | DN7: 7931 | DO7: 12829 | DP7: 2681 | DQ7: 8475 | DR7: 4331 | DS7: 2676 | DT7: 2290 | DU7: 6464 | DV7: 4966 | DW7: 10147 | DX7: 29557 | DY7: 2092 | DZ7: 5458 | EA7: 5247 | EB7: 1987 | EC7: 2070 | ED7: 2406 | EE7: 1821 | EF7: 2012 | EG7: 3156 | EH7: 24405 | EI7: 1605 | EJ7: 1677 | EK7: 7858 | EL7: 7077 | EM7: 15979 | EN7: 3385 | EO7: 19194 | EP7: 1236 | EQ7: 9096 | ER7: 6369 | ES7: 2936 | ET7: 3621 | EU7: 11453 | EV7: 2432 | EW7: 21794 | EX7: 3293 | EY7: 1879 | EZ7: 6997 | FA7: 3618 | FB7: 1500 | FC7: 2349 | FD7: 1818 | FE7: 4417 | FF7: 173441 | FG7: 7907 | FH7: 10024 | FI7: 4549 | FJ7: 46716 | FK7: 3059 | FL7: 1390 | FM7: 3146 | FN7: 13570 | FO7: 3763 | FP7: 33438 | FQ7: 3629 | FR7: 3535 | FS7: 3160 | FT7: 3911 | FU7: 2428 | FV7: 3078 | FW7: 4459 | FX7: 2939 | FY7: 5044 | FZ7: 2361 | GA7: 47890 | GB7: 7739 | GC7: 3490 | GD7: 10408 | GE7: 5764 | GF7: 3010 | GG7: 15423 | GH7: 17852 | GI7: 1717 | GJ7: 3561 | GK7: 9189 | GL7: 4282 | GM7: 5320 | GN7: 3430 | GO7: 15890 | GP7: 11493 | GQ7: 8733 | GR7: 7271 | GS7: 4842 | GT7: 46862 | GU7: 1750 | GV7: 2464 | GW7: 2892 | GX7: 1384 | GY7: 2247 | GZ7: 10032 | HA7: 4758 | HB7: 2181 | HC7: 7092 | HD7: 16190 | HE7: 4140 | HF7: 6513 | HG7: 2218 | HH7: 251611 | HI7: 27705 | HJ7: 7498 | HK7: 4679 | HL7: 5141 | HM7: 12756 | HN7: 7989 | HO7: 2179 | HP7: 2094 | HQ7: 2537 | HR7: 3654 | HS7: 24038 | HT7: 4078 | HU7: 29520 | HV7: 7812 | HW7: 112896 | HX7: 2144 | HY7: 1607 | HZ7: 4254 | IA7: 32219 | IB7: 77096 | IC7: 1613 | ID7: 2110 | IE7: 8453 | IF7: 13655 | IG7: 4945 | IH7: 3005 | II7: 7947 | IJ7: 2107 | IK7: 2445 | IL7: 2483 | IM7: 1905 | IN7: 3644 | IO7: 6272 | IP7: 2765 | IQ7: 6082 | IR7: 42563 | IS7: 10751 | IT7: 18401 | IU7: 371871 | IV7: 3109 | IW7: 13558 | IX7: 5248 | IY7: 6925 | IZ7: 3910 | JA7: 18007 | JB7: 31814 | JC7: 5505 | JD7: 21963 | JE7: 54552 | JF7: 3122 | JG7: 2308 | JH7: 17470 | JI7: 1996 | JJ7: 10929 | JK7: 3974 | JL7: 1685 | JM7: 10066 | JN7: 7629 | JO7: 122324 | JP7: 105582 | JQ7: 2167 | JR7: 42333 | JS7: 2244 | JT7: 2113 | JU7: 4949 | JV7: 9636 | JW7: 47924 | JX7: 9310 | JY7: 3743 | JZ7: 31196 | KA7: 20329 | KB7: 3490 | KC7: 2338 | KD7: 4229 | KE7: 32128 | KF7: 2974 | KG7: 9088 | KH7: 3589 | KI7: 10718 | KJ7: 25768 | KK7: 108746 | KL7: 6071 | KM7: 4770 | KN7: 19788 | KO7: 7312 | KP7: 3257 | KQ7: 2346 | KR7: 49652 | KS7: 3710 | KT7: 4188 | KU7: 4673 | KV7: 2274 | KW7: 56078 | KX7: 9818 | KY7: 9960 | KZ7: 2510 | LA7: 30767 | LB7: 2463 | LC7: 57834 | LD7: 60050 | LE7: 2013 | LF7: 82003 | LG7: 38688 | LH7: 36438 | LI7: 4587 | LJ7: 4873 | LK7: 2567 | LL7: 8820 | LM7: 9047 | LN7: 8361 | LO7: 11107 | LP7: 73114 | LQ7: 2306 | LR7: 1635 | LS7: 2527 | LT7: 3057 | LU7: 8265 | LV7: 2423 | LW7: 3529 | LX7: 6578 | LY7: 6404 | LZ7: 6691 | MA7: 7902 | MB7: 11627 | MC7: 4295 | MD7: 9408 | ME7: 9840 | MF7: 2952 | MG7: 2413 | MH7: 2462 | MI7: 19374 | MJ7: 2187 | MK7: 12279 | ML7: 6820 | MM7: 58762 | MN7: 3180 | MO7: 3096 | MP7: 12180 | MQ7: 5146 | MR7: 2855 | MS7: 7785 | MT7: 19620 | MU7: 22876 | MV7: 4940 | MW7: 2989 | MX7: 5214 | MY7: 16564 | MZ7: 5701 | NA7: 2768 | NB7: 8815 | NC7: 2165 | ND7: 3331 | NE7: 33237 | NF7: 13018 | NG7: 6591 | NH7: 1228 | NI7: 4796 | NJ7: 127493 | NK7: 9026 | NL7: 3200 | NM7: 2144 | NN7: 3015 | NO7: 2026 | NP7: 2646 | NQ7: 2432 | NR7: 14916 | NS7: 2974 | NT7: 925 | NU7: 2153 | NV7: 7365 | NW7: 3267 | NX7: 14357 | NY7: 17134 | NZ7: 6693 | OA7: 9663 | OB7: 8175 | OC7: 4277 | OD7: 4628
A8: 18 and 19 years | B8: 3236 | C8: 3059 | D8: 9011 | E8: 2038 | F8: 1527 | G8: 15000 | H8: 11674 | I8: 1756 | J8: 13079 | K8: 2024 | L8: 3971 | M8: 6315 | N8: 5688 | O8: 5281 | P8: 9507 | Q8: 1972 | R8: 2932 | S8: 2200 | T8: 4520 | U8: 5731 | V8: 84283 | W8: 4257 | X8: 5411 | Y8: 8882 | Z8: 32442 | AA8: 13548 | AB8: 35840 | AC8: 2778 | AD8: 2283 | AE8: 13548 | AF8: 1683 | AG8: 1120 | AH8: 4619 | AI8: 1386 | AJ8: 3640 | AK8: 2351 | AL8: 2080 | AM8: 5048 | AN8: 15021 | AO8: 1761 | AP8: 7510 | AQ8: 3693 | AR8: 5709 | AS8: 11003 | AT8: 70919 | AU8: 8471 | AV8: 3062 | AW8: 2560 | AX8: 2986 | AY8: 13138 | AZ8: 7136 | BA8: 1443 | BB8: 14892 | BC8: 2886 | BD8: 4476 | BE8: 4834 | BF8: 8762 | BG8: 1603 | BH8: 671 | BI8: 1062 | BJ8: 3270 | BK8: 1740 | BL8: 7609 | BM8: 2337 | BN8: 10571 | BO8: 34460 | BP8: 4344 | BQ8: 7099 | BR8: 1296 | BS8: 121268 | BT8: 3528 | BU8: 30817 | BV8: 4597 | BW8: 25241 | BX8: 1698 | BY8: 1941 | BZ8: 10276 | CA8: 11420 | CB8: 4962 | CC8: 14057 | CD8: 4599 | CE8: 967 | CF8: 29661 | CG8: 6053 | CH8: 3055 | CI8: 3049 | CJ8: 108447 | CK8: 1887 | CL8: 2526 | CM8: 4986 | CN8: 11021 | CO8: 1581 | CP8: 1231 | CQ8: 8446 | CR8: 34602 | CS8: 8825 | CT8: 49024 | CU8: 1631 | CV8: 2733 | CW8: 1640 | CX8: 4511 | CY8: 10623 | CZ8: 940 | DA8: 2781 | DB8: 2864 | DC8: 1559 | DD8: 2827 | DE8: 997 | DF8: 13991 | DG8: 831 | DH8: 4392 | DI8: 6947 | DJ8: 3371 | DK8: 1365 | DL8: 5352 | DM8: 1637 | DN8: 6399 | DO8: 9682 | DP8: 3701 | DQ8: 4764 | DR8: 2463 | DS8: 2042 | DT8: 1262 | DU8: 7114 | DV8: 2836 | DW8: 5699 | DX8: 17081 | DY8: 1074 | DZ8: 8431 | EA8: 2565 | EB8: 1878 | EC8: 1232 | ED8: 1586 | EE8: 2269 | EF8: 985 | EG8: 2361 | EH8: 16724 | EI8: 894 | EJ8: 924 | EK8: 4745 | EL8: 4211 | EM8: 13059 | EN8: 4350 | EO8: 14101 | EP8: 900 | EQ8: 5479 | ER8: 3441 | ES8: 2075 | ET8: 2241 | EU8: 8390 | EV8: 3864 | EW8: 16842 | EX8: 2450 | EY8: 980 | EZ8: 4126 | FA8: 4083 | FB8: 1510 | FC8: 1321 | FD8: 1162 | FE8: 2491 | FF8: 99967 | FG8: 4462 | FH8: 6957 | FI8: 2218 | FJ8: 25563 | FK8: 4312 | FL8: 5717 | FM8: 1947 | FN8: 8396 | FO8: 2457 | FP8: 19765 | FQ8: 7126 | FR8: 2048 | FS8: 2088 | FT8: 2852 | FU8: 1756 | FV8: 2133 | FW8: 2652 | FX8: 1575 | FY8: 4529 | FZ8: 1561 | GA8: 25766 | GB8: 4212 | GC8: 2561 | GD8: 7949 | GE8: 3442 | GF8: 2283 | GG8: 10745 | GH8: 12312 | GI8: 880 | GJ8: 2805 | GK8: 4469 | GL8: 8482 | GM8: 2955 | GN8: 1904 | GO8: 10177 | GP8: 7521 | GQ8: 9548 | GR8: 4808 | GS8: 4289 | GT8: 26287 | GU8: 3216 | GV8: 2810 | GW8: 1769 | GX8: 843 | GY8: 1746 | GZ8: 7968 | HA8: 2687 | HB8: 1541 | HC8: 6550 | HD8: 9284 | HE8: 2949 | HF8: 4267 | HG8: 1097 | HH8: 165244 | HI8: 15395 | HJ8: 7448 | HK8: 5191 | HL8: 3243 | HM8: 10799 | HN8: 4827 | HO8: 3590 | HP8: 3065 | HQ8: 1527 | HR8: 3159 | HS8: 15196 | HT8: 2438 | HU8: 16227 | HV8: 5819 | HW8: 70173 | HX8: 1236 | HY8: 954 | HZ8: 2434 | IA8: 20119 | IB8: 45274 | IC8: 1138 | ID8: 1878 | IE8: 4986 | IF8: 7911 | IG8: 2984 | IH8: 1684 | II8: 5214 | IJ8: 4139 | IK8: 1365 | IL8: 1389 | IM8: 2884 | IN8: 2036 | IO8: 5806 | IP8: 1663 | IQ8: 3757 | IR8: 25700 | IS8: 8978 | IT8: 11301 | IU8: 231046 | IV8: 1746 | IW8: 7463 | IX8: 3990 | IY8: 3719 | IZ8: 2334 | JA8: 9334 | JB8: 21218 | JC8: 3076 | JD8: 12816 | JE8: 36116 | JF8: 2421 | JG8: 1259 | JH8: 10763 | JI8: 1035 | JJ8: 6881 | JK8: 2125 | JL8: 947 | JM8: 8419 | JN8: 4424 | JO8: 83973 | JP8: 67099 | JQ8: 977 | JR8: 30399 | JS8: 2060 | JT8: 1358 | JU8: 3343 | JV8: 6263 | JW8: 27202 | JX8: 5248 | JY8: 2945 | JZ8: 24387 | KA8: 14216 | KB8: 2007 | KC8: 1605 | KD8: 2339 | KE8: 20152 | KF8: 2067 | KG8: 6754 | KH8: 2013 | KI8: 6640 | KJ8: 17930 | KK8: 66861 | KL8: 3628 | KM8: 2376 | KN8: 16277 | KO8: 4206 | KP8: 1745 | KQ8: 1602 | KR8: 32248 | KS8: 2646 | KT8: 3753 | KU8: 2779 | KV8: 1643 | KW8: 34058 | KX8: 6244 | KY8: 6938 | KZ8: 2528 | LA8: 17914 | LB8: 1970 | LC8: 38547 | LD8: 47994 | LE8: 1302 | LF8: 51308 | LG8: 25053 | LH8: 24887 | LI8: 7241 | LJ8: 6072 | LK8: 1569 | LL8: 9560 | LM8: 5770 | LN8: 5906 | LO8: 7720 | LP8: 44017 | LQ8: 1658 | LR8: 871 | LS8: 1379 | LT8: 1868 | LU8: 4417 | LV8: 1661 | LW8: 2156 | LX8: 3314 | LY8: 3183 | LZ8: 5369 | MA8: 4844 | MB8: 7462 | MC8: 2348 | MD8: 6984 | ME8: 6539 | MF8: 1577 | MG8: 5934 | MH8: 1215 | MI8: 11332 | MJ8: 1263 | MK8: 11823 | ML8: 9406 | MM8: 37418 | MN8: 2935 | MO8: 2064 | MP8: 9147 | MQ8: 2832 | MR8: 1718 | MS8: 6049 | MT8: 16336 | MU8: 13451 | MV8: 8056 | MW8: 1687 | MX8: 3476 | MY8: 11327 | MZ8: 3991 | NA8: 2935 | NB8: 5314 | NC8: 1238 | ND8: 1872 | NE8: 25471 | NF8: 7564 | NG8: 5737 | NH8: 1228 | NI8: 2851 | NJ8: 78490 | NK8: 5240 | NL8: 2686 | NM8: 1570 | NN8: 1470 | NO8: 1430 | NP8: 1478 | NQ8: 1915 | NR8: 8776 | NS8: 3231 | NT8: 601 | NU8: 1975 | NV8: 4849 | NW8: 2008 | NX8: 8897 | NY8: 12383 | NZ8: 3867 | OA8: 5502 | OB8: 4640 | OC8: 2568 | OD8: 3196
A9: 20 years | B9: 1569 | C9: 1667 | D9: 5527 | E9: 1070 | F9: 685 | G9: 8104 | H9: 5462 | I9: 1159 | J9: 6203 | K9: 654 | L9: 1905 | M9: 3498 | N9: 3349 | O9: 3221 | P9: 4370 | Q9: 935 | R9: 1477 | S9: 1566 | T9: 2294 | U9: 3710 | V9: 36866 | W9: 2485 | X9: 3542 | Y9: 5330 | Z9: 15166 | AA9: 6907 | AB9: 17432 | AC9: 1346 | AD9: 1275 | AE9: 6790 | AF9: 1246 | AG9: 516 | AH9: 2310 | AI9: 724 | AJ9: 2626 | AK9: 969 | AL9: 649 | AM9: 2542 | AN9: 7348 | AO9: 976 | AP9: 3526 | AQ9: 1956 | AR9: 2972 | AS9: 6048 | AT9: 33157 | AU9: 4712 | AV9: 1885 | AW9: 2016 | AX9: 2898 | AY9: 5875 | AZ9: 3761 | BA9: 517 | BB9: 7392 | BC9: 1186 | BD9: 2586 | BE9: 2207 | BF9: 4403 | BG9: 942 | BH9: 141 | BI9: 299 | BJ9: 2115 | BK9: 1032 | BL9: 4895 | BM9: 1238 | BN9: 5078 | BO9: 15495 | BP9: 1867 | BQ9: 3542 | BR9: 705 | BS9: 56407 | BT9: 2066 | BU9: 17693 | BV9: 2949 | BW9: 12793 | BX9: 891 | BY9: 1178 | BZ9: 7340 | CA9: 5912 | CB9: 3105 | CC9: 8040 | CD9: 2244 | CE9: 594 | CF9: 14873 | CG9: 3049 | CH9: 1591 | CI9: 1207 | CJ9: 50071 | CK9: 949 | CL9: 1348 | CM9: 2407 | CN9: 5545 | CO9: 1343 | CP9: 607 | CQ9: 3449 | CR9: 16544 | CS9: 4295 | CT9: 25383 | CU9: 1148 | CV9: 1475 | CW9: 779 | CX9: 2745 | CY9: 5565 | CZ9: 620 | DA9: 1873 | DB9: 1447 | DC9: 694 | DD9: 1092 | DE9: 435 | DF9: 6719 | DG9: 322 | DH9: 1980 | DI9: 3936 | DJ9: 1661 | DK9: 863 | DL9: 2723 | DM9: 887 | DN9: 4403 | DO9: 5347 | DP9: 2373 | DQ9: 2597 | DR9: 1224 | DS9: 1217 | DT9: 588 | DU9: 4615 | DV9: 1474 | DW9: 2685 | DX9: 8796 | DY9: 430 | DZ9: 5528 | EA9: 1419 | EB9: 862 | EC9: 544 | ED9: 959 | EE9: 1580 | EF9: 372 | EG9: 1250 | EH9: 7929 | EI9: 444 | EJ9: 548 | EK9: 2079 | EL9: 2207 | EM9: 6001 | EN9: 2301 | EO9: 6850 | EP9: 391 | EQ9: 2968 | ER9: 2094 | ES9: 1168 | ET9: 1703 | EU9: 3511 | EV9: 1759 | EW9: 8469 | EX9: 1379 | EY9: 567 | EZ9: 2711 | FA9: 1811 | FB9: 953 | FC9: 574 | FD9: 635 | FE9: 892 | FF9: 45127 | FG9: 2337 | FH9: 3830 | FI9: 943 | FJ9: 11691 | FK9: 2436 | FL9: 2515 | FM9: 1236 | FN9: 4097 | FO9: 1657 | FP9: 9758 | FQ9: 6193 | FR9: 896 | FS9: 1164 | FT9: 1646 | FU9: 1018 | FV9: 830 | FW9: 1434 | FX9: 704 | FY9: 3826 | FZ9: 808 | GA9: 11938 | GB9: 1665 | GC9: 1126 | GD9: 4942 | GE9: 1776 | GF9: 815 | GG9: 4592 | GH9: 7761 | GI9: 299 | GJ9: 1876 | GK9: 2156 | GL9: 4690 | GM9: 1464 | GN9: 822 | GO9: 5195 | GP9: 3860 | GQ9: 5571 | GR9: 2580 | GS9: 2235 | GT9: 14401 | GU9: 2833 | GV9: 1239 | GW9: 814 | GX9: 337 | GY9: 981 | GZ9: 4379 | HA9: 1156 | HB9: 984 | HC9: 3875 | HD9: 5620 | HE9: 1793 | HF9: 3217 | HG9: 548 | HH9: 81174 | HI9: 7278 | HJ9: 4659 | HK9: 2596 | HL9: 1732 | HM9: 5975 | HN9: 2314 | HO9: 3054 | HP9: 1367 | HQ9: 726 | HR9: 2088 | HS9: 7698 | HT9: 1235 | HU9: 8303 | HV9: 2468 | HW9: 34330 | HX9: 798 | HY9: 466 | HZ9: 1092 | IA9: 10860 | IB9: 21091 | IC9: 637 | ID9: 980 | IE9: 2940 | IF9: 4354 | IG9: 1866 | IH9: 818 | II9: 2271 | IJ9: 1950 | IK9: 918 | IL9: 438 | IM9: 1628 | IN9: 1040 | IO9: 2558 | IP9: 1128 | IQ9: 2235 | IR9: 14102 | IS9: 4096 | IT9: 5261 | IU9: 105432 | IV9: 965 | IW9: 3387 | IX9: 2289 | IY9: 1657 | IZ9: 1206 | JA9: 5006 | JB9: 11008 | JC9: 1590 | JD9: 5583 | JE9: 16987 | JF9: 1307 | JG9: 1033 | JH9: 5347 | JI9: 683 | JJ9: 3695 | JK9: 976 | JL9: 519 | JM9: 3376 | JN9: 2505 | JO9: 37885 | JP9: 34137 | JQ9: 564 | JR9: 14597 | JS9: 1198 | JT9: 541 | JU9: 1870 | JV9: 3233 | JW9: 13685 | JX9: 2987 | JY9: 1065 | JZ9: 12484 | KA9: 7428 | KB9: 873 | KC9: 930 | KD9: 1024 | KE9: 8417 | KF9: 848 | KG9: 2980 | KH9: 858 | KI9: 3872 | KJ9: 8491 | KK9: 33734 | KL9: 1851 | KM9: 1247 | KN9: 7751 | KO9: 1806 | KP9: 831 | KQ9: 593 | KR9: 16852 | KS9: 1487 | KT9: 1706 | KU9: 1410 | KV9: 723 | KW9: 16359 | KX9: 2965 | KY9: 3567 | KZ9: 1308 | LA9: 8083 | LB9: 1121 | LC9: 17340 | LD9: 26398 | LE9: 724 | LF9: 23521 | LG9: 11824 | LH9: 14039 | LI9: 3989 | LJ9: 3138 | LK9: 857 | LL9: 5628 | LM9: 2195 | LN9: 3608 | LO9: 4348 | LP9: 21759 | LQ9: 713 | LR9: 533 | LS9: 722 | LT9: 657 | LU9: 2290 | LV9: 916 | LW9: 1189 | LX9: 1481 | LY9: 1724 | LZ9: 2881 | MA9: 1856 | MB9: 4008 | MC9: 1509 | MD9: 4361 | ME9: 3665 | MF9: 1111 | MG9: 4315 | MH9: 621 | MI9: 5949 | MJ9: 574 | MK9: 5085 | ML9: 5995 | MM9: 18405 | MN9: 1752 | MO9: 537 | MP9: 5257 | MQ9: 1405 | MR9: 879 | MS9: 3293 | MT9: 9489 | MU9: 6744 | MV9: 4732 | MW9: 596 | MX9: 1719 | MY9: 6431 | MZ9: 1793 | NA9: 1597 | NB9: 3057 | NC9: 434 | ND9: 881 | NE9: 15172 | NF9: 3912 | NG9: 3339 | NH9: 654 | NI9: 1513 | NJ9: 35240 | NK9: 2335 | NL9: 1795 | NM9: 1121 | NN9: 591 | NO9: 824 | NP9: 428 | NQ9: 869 | NR9: 4432 | NS9: 1209 | NT9: 200 | NU9: 873 | NV9: 2556 | NW9: 700 | NX9: 4179 | NY9: 6447 | NZ9: 1653 | OA9: 2512 | OB9: 2052 | OC9: 1657 | OD9: 1533
A10: 21 years | B10: 1804 | C10: 1437 | D10: 4365 | E10: 790 | F10: 615 | G10: 6229 | H10: 5116 | I10: 546 | J10: 6118 | K10: 704 | L10: 1682 | M10: 3255 | N10: 2776 | O10: 3088 | P10: 6078 | Q10: 928 | R10: 1844 | S10: 1119 | T10: 2772 | U10: 4362 | V10: 39930 | W10: 2156 | X10: 2765 | Y10: 3838 | Z10: 14068 | AA10: 6343 | AB10: 16760 | AC10: 1239 | AD10: 946 | AE10: 6922 | AF10: 882 | AG10: 618 | AH10: 3523 | AI10: 672 | AJ10: 2306 | AK10: 774 | AL10: 1327 | AM10: 3291 | AN10: 6908 | AO10: 826 | AP10: 4188 | AQ10: 2141 | AR10: 3373 | AS10: 5219 | AT10: 32573 | AU10: 3671 | AV10: 1813 | AW10: 1828 | AX10: 2037 | AY10: 5618 | AZ10: 3127 | BA10: 576 | BB10: 8428 | BC10: 1041 | BD10: 2381 | BE10: 2183 | BF10: 4390 | BG10: 1136 | BH10: 332 | BI10: 403 | BJ10: 1715 | BK10: 520 | BL10: 4541 | BM10: 1383 | BN10: 6000 | BO10: 16146 | BP10: 1571 | BQ10: 3411 | BR10: 946 | BS10: 54827 | BT10: 2853 | BU10: 14432 | BV10: 2973 | BW10: 12770 | BX10: 862 | BY10: 799 | BZ10: 5942 | CA10: 6681 | CB10: 3334 | CC10: 7804 | CD10: 2092 | CE10: 612 | CF10: 14120 | CG10: 2843 | CH10: 1983 | CI10: 1593 | CJ10: 48238 | CK10: 1060 | CL10: 912 | CM10: 2625 | CN10: 6392 | CO10: 648 | CP10: 545 | CQ10: 4071 | CR10: 16429 | CS10: 3857 | CT10: 23878 | CU10: 933 | CV10: 1217 | CW10: 662 | CX10: 2265 | CY10: 4746 | CZ10: 441 | DA10: 1471 | DB10: 1641 | DC10: 873 | DD10: 1617 | DE10: 722 | DF10: 8526 | DG10: 659 | DH10: 2078 | DI10: 3385 | DJ10: 1863 | DK10: 1251 | DL10: 3132 | DM10: 863 | DN10: 4671 | DO10: 4553 | DP10: 1887 | DQ10: 2145 | DR10: 1227 | DS10: 854 | DT10: 789 | DU10: 3407 | DV10: 1636 | DW10: 3192 | DX10: 8606 | DY10: 387 | DZ10: 5872 | EA10: 1453 | EB10: 846 | EC10: 533 | ED10: 803 | EE10: 1165 | EF10: 623 | EG10: 954 | EH10: 8071 | EI10: 264 | EJ10: 729 | EK10: 2647 | EL10: 1747 | EM10: 5408 | EN10: 2207 | EO10: 8092 | EP10: 517 | EQ10: 2044 | ER10: 1839 | ES10: 860 | ET10: 1203 | EU10: 3194 | EV10: 2659 | EW10: 7923 | EX10: 1223 | EY10: 415 | EZ10: 2223 | FA10: 2127 | FB10: 1054 | FC10: 644 | FD10: 283 | FE10: 1808 | FF10: 47001 | FG10: 2554 | FH10: 3390 | FI10: 756 | FJ10: 13039 | FK10: 2971 | FL10: 2264 | FM10: 1116 | FN10: 3448 | FO10: 797 | FP10: 9260 | FQ10: 5068 | FR10: 1113 | FS10: 808 | FT10: 1441 | FU10: 840 | FV10: 972 | FW10: 1263 | FX10: 632 | FY10: 2636 | FZ10: 663 | GA10: 11314 | GB10: 2413 | GC10: 1004 | GD10: 4994 | GE10: 1774 | GF10: 1402 | GG10: 5634 | GH10: 6648 | GI10: 450 | GJ10: 1538 | GK10: 2509 | GL10: 5107 | GM10: 1590 | GN10: 979 | GO10: 5230 | GP10: 3836 | GQ10: 6697 | GR10: 2557 | GS10: 2811 | GT10: 13823 | GU10: 2381 | GV10: 897 | GW10: 1086 | GX10: 239 | GY10: 953 | GZ10: 4536 | HA10: 1245 | HB10: 633 | HC10: 3549 | HD10: 4134 | HE10: 2137 | HF10: 1676 | HG10: 696 | HH10: 82910 | HI10: 8188 | HJ10: 5530 | HK10: 2568 | HL10: 1408 | HM10: 7148 | HN10: 2337 | HO10: 3788 | HP10: 2125 | HQ10: 744 | HR10: 1937 | HS10: 7531 | HT10: 1069 | HU10: 8090 | HV10: 2040 | HW10: 33194 | HX10: 645 | HY10: 496 | HZ10: 975 | IA10: 9080 | IB10: 21398 | IC10: 899 | ID10: 677 | IE10: 2018 | IF10: 3983 | IG10: 1665 | IH10: 985 | II10: 2611 | IJ10: 2922 | IK10: 728 | IL10: 586 | IM10: 1699 | IN10: 1090 | IO10: 1550 | IP10: 557 | IQ10: 1839 | IR10: 11394 | IS10: 3804 | IT10: 5753 | IU10: 111971 | IV10: 768 | IW10: 5138 | IX10: 1930 | IY10: 2068 | IZ10: 999 | JA10: 4466 | JB10: 11855 | JC10: 1781 | JD10: 6092 | JE10: 17085 | JF10: 1675 | JG10: 806 | JH10: 5426 | JI10: 644 | JJ10: 2563 | JK10: 972 | JL10: 419 | JM10: 4132 | JN10: 1757 | JO10: 38136 | JP10: 33418 | JQ10: 436 | JR10: 13551 | JS10: 701 | JT10: 938 | JU10: 1921 | JV10: 2459 | JW10: 14140 | JX10: 2839 | JY10: 1201 | JZ10: 11680 | KA10: 9444 | KB10: 896 | KC10: 678 | KD10: 1679 | KE10: 8776 | KF10: 1591 | KG10: 2908 | KH10: 1225 | KI10: 3799 | KJ10: 8100 | KK10: 36633 | KL10: 1673 | KM10: 967 | KN10: 7609 | KO10: 2214 | KP10: 775 | KQ10: 684 | KR10: 16010 | KS10: 1400 | KT10: 2442 | KU10: 1451 | KV10: 917 | KW10: 15427 | KX10: 3312 | KY10: 2936 | KZ10: 1291 | LA10: 10036 | LB10: 937 | LC10: 18885 | LD10: 26710 | LE10: 640 | LF10: 24312 | LG10: 11907 | LH10: 14697 | LI10: 3844 | LJ10: 2562 | LK10: 619 | LL10: 5409 | LM10: 3019 | LN10: 3100 | LO10: 3258 | LP10: 21553 | LQ10: 929 | LR10: 308 | LS10: 873 | LT10: 1226 | LU10: 1899 | LV10: 824 | LW10: 944 | LX10: 1935 | LY10: 1430 | LZ10: 2353 | MA10: 2841 | MB10: 4012 | MC10: 1219 | MD10: 3014 | ME10: 4605 | MF10: 739 | MG10: 4523 | MH10: 932 | MI10: 5931 | MJ10: 893 | MK10: 4660 | ML10: 5397 | MM10: 18798 | MN10: 2043 | MO10: 1507 | MP10: 4962 | MQ10: 1692 | MR10: 969 | MS10: 2696 | MT10: 9646 | MU10: 6641 | MV10: 3875 | MW10: 1104 | MX10: 1843 | MY10: 8061 | MZ10: 2306 | NA10: 1408 | NB10: 3052 | NC10: 520 | ND10: 991 | NE10: 12865 | NF10: 3105 | NG10: 3575 | NH10: 682 | NI10: 1158 | NJ10: 36120 | NK10: 2555 | NL10: 2235 | NM10: 1330 | NN10: 698 | NO10: 1075 | NP10: 801 | NQ10: 806 | NR10: 4087 | NS10: 1164 | NT10: 353 | NU10: 848 | NV10: 2990 | NW10: 885 | NX10: 3567 | NY10: 5278 | NZ10: 1568 | OA10: 2663 | OB10: 2704 | OC10: 1197 | OD10: 2219
A11: 22 to 24 years | B11: 5705 | C11: 5104 | D11: 14075 | E11: 2801 | F11: 2285 | G11: 20477 | H11: 18549 | I11: 2912 | J11: 16065 | K11: 1866 | L11: 5425 | M11: 5045 | N11: 4454 | O11: 9291 | P11: 12878 | Q11: 2414 | R11: 4209 | S11: 3227 | T11: 5811 | U11: 5859 | V11: 125706 | W11: 6546 | X11: 5898 | Y11: 11756 | Z11: 51986 | AA11: 20376 | AB11: 51700 | AC11: 3111 | AD11: 3731 | AE11: 22796 | AF11: 2029 | AG11: 1693 | AH11: 7090 | AI11: 1704 | AJ11: 6040 | AK11: 4567 | AL11: 3432 | AM11: 6085 | AN11: 21693 | AO11: 2763 | AP11: 5816 | AQ11: 6086 | AR11: 6452 | AS11: 15133 | AT11: 102145 | AU11: 9188 | AV11: 5369 | AW11: 4456 | AX11: 6924 | AY11: 18952 | AZ11: 10313 | BA11: 1899 | BB11: 20453 | BC11: 3511 | BD11: 5095 | BE11: 7306 | BF11: 12080 | BG11: 2084 | BH11: 1383 | BI11: 1498 | BJ11: 4978 | BK11: 2693 | BL11: 8898 | BM11: 3122 | BN11: 15577 | BO11: 52876 | BP11: 4969 | BQ11: 9700 | BR11: 1947 | BS11: 187313 | BT11: 6633 | BU11: 43241 | BV11: 9962 | BW11: 38445 | BX11: 2397 | BY11: 2996 | BZ11: 11577 | CA11: 20343 | CB11: 6639 | CC11: 18405 | CD11: 7799 | CE11: 1527 | CF11: 40159 | CG11: 9605 | CH11: 4354 | CI11: 6988 | CJ11: 164690 | CK11: 3079 | CL11: 3788 | CM11: 6424 | CN11: 15425 | CO11: 3031 | CP11: 1836 | CQ11: 12144 | CR11: 56237 | CS11: 14417 | CT11: 80063 | CU11: 2067 | CV11: 3604 | CW11: 2037 | CX11: 6212 | CY11: 11716 | CZ11: 1339 | DA11: 4301 | DB11: 3717 | DC11: 2658 | DD11: 4202 | DE11: 1246 | DF11: 21720 | DG11: 1279 | DH11: 5495 | DI11: 10006 | DJ11: 5085 | DK11: 3561 | DL11: 7430 | DM11: 1852 | DN11: 12126 | DO11: 13192 | DP11: 4820 | DQ11: 7317 | DR11: 3445 | DS11: 3553 | DT11: 1914 | DU11: 10844 | DV11: 3875 | DW11: 8613 | DX11: 23238 | DY11: 2182 | DZ11: 11266 | EA11: 4496 | EB11: 1930 | EC11: 2206 | ED11: 2977 | EE11: 3684 | EF11: 1292 | EG11: 2494 | EH11: 25938 | EI11: 1285 | EJ11: 2032 | EK11: 6087 | EL11: 6302 | EM11: 14993 | EN11: 6035 | EO11: 18504 | EP11: 1464 | EQ11: 8146 | ER11: 5147 | ES11: 2434 | ET11: 4001 | EU11: 11511 | EV11: 3097 | EW11: 24839 | EX11: 3464 | EY11: 1265 | EZ11: 6340 | FA11: 5089 | FB11: 3058 | FC11: 1911 | FD11: 1668 | FE11: 3473 | FF11: 152253 | FG11: 7392 | FH11: 9952 | FI11: 3283 | FJ11: 41644 | FK11: 6757 | FL11: 3580 | FM11: 3072 | FN11: 11698 | FO11: 3572 | FP11: 30047 | FQ11: 12771 | FR11: 3030 | FS11: 2871 | FT11: 4459 | FU11: 2298 | FV11: 3020 | FW11: 4090 | FX11: 2537 | FY11: 8260 | FZ11: 2219 | GA11: 42583 | GB11: 6595 | GC11: 3487 | GD11: 12479 | GE11: 5039 | GF11: 3516 | GG11: 15141 | GH11: 19451 | GI11: 1638 | GJ11: 3867 | GK11: 7863 | GL11: 8531 | GM11: 4213 | GN11: 2979 | GO11: 13762 | GP11: 9342 | GQ11: 11824 | GR11: 5721 | GS11: 6450 | GT11: 41137 | GU11: 5176 | GV11: 3725 | GW11: 2416 | GX11: 1165 | GY11: 1914 | GZ11: 13569 | HA11: 3752 | HB11: 1808 | HC11: 11317 | HD11: 16570 | HE11: 6383 | HF11: 5286 | HG11: 1849 | HH11: 251651 | HI11: 25721 | HJ11: 11074 | HK11: 5327 | HL11: 4299 | HM11: 19639 | HN11: 8518 | HO11: 6503 | HP11: 3251 | HQ11: 2846 | HR11: 4789 | HS11: 19913 | HT11: 3505 | HU11: 25513 | HV11: 6529 | HW11: 109660 | HX11: 2273 | HY11: 1359 | HZ11: 3401 | IA11: 28077 | IB11: 67717 | IC11: 2070 | ID11: 4241 | IE11: 8027 | IF11: 10490 | IG11: 3815 | IH11: 2691 | II11: 7466 | IJ11: 4517 | IK11: 1961 | IL11: 2384 | IM11: 3761 | IN11: 3172 | IO11: 5076 | IP11: 2370 | IQ11: 5334 | IR11: 43173 | IS11: 12381 | IT11: 16628 | IU11: 372613 | IV11: 2791 | IW11: 11464 | IX11: 6571 | IY11: 5803 | IZ11: 3772 | JA11: 13839 | JB11: 31966 | JC11: 4920 | JD11: 19386 | JE11: 55725 | JF11: 4345 | JG11: 1686 | JH11: 16036 | JI11: 1494 | JJ11: 10583 | JK11: 4128 | JL11: 1419 | JM11: 11644 | JN11: 6344 | JO11: 116952 | JP11: 102191 | JQ11: 1334 | JR11: 41199 | JS11: 2381 | JT11: 1878 | JU11: 5499 | JV11: 9806 | JW11: 44361 | JX11: 7487 | JY11: 3447 | JZ11: 31743 | KA11: 29087 | KB11: 3538 | KC11: 2050 | KD11: 3516 | KE11: 28212 | KF11: 2977 | KG11: 8033 | KH11: 2841 | KI11: 10252 | KJ11: 25243 | KK11: 93794 | KL11: 5259 | KM11: 4070 | KN11: 19147 | KO11: 6221 | KP11: 2486 | KQ11: 2002 | KR11: 44824 | KS11: 3070 | KT11: 5370 | KU11: 3481 | KV11: 2572 | KW11: 50658 | KX11: 9423 | KY11: 9393 | KZ11: 3011 | LA11: 28759 | LB11: 2582 | LC11: 57823 | LD11: 72310 | LE11: 1836 | LF11: 77841 | LG11: 39572 | LH11: 38911 | LI11: 7453 | LJ11: 6703 | LK11: 2671 | LL11: 12262 | LM11: 8287 | LN11: 7473 | LO11: 9883 | LP11: 80973 | LQ11: 2157 | LR11: 1360 | LS11: 2175 | LT11: 2339 | LU11: 7254 | LV11: 2175 | LW11: 2958 | LX11: 5700 | LY11: 4424 | LZ11: 6524 | MA11: 6826 | MB11: 11175 | MC11: 3237 | MD11: 8657 | ME11: 11946 | MF11: 2118 | MG11: 5703 | MH11: 2051 | MI11: 15339 | MJ11: 2601 | MK11: 12559 | ML11: 11763 | MM11: 54384 | MN11: 4242 | MO11: 2706 | MP11: 11928 | MQ11: 3915 | MR11: 2074 | MS11: 7586 | MT11: 26533 | MU11: 19992 | MV11: 6374 | MW11: 1910 | MX11: 4348 | MY11: 23313 | MZ11: 5522 | NA11: 4705 | NB11: 8459 | NC11: 2369 | ND11: 3022 | NE11: 39344 | NF11: 10167 | NG11: 7992 | NH11: 1549 | NI11: 3939 | NJ11: 118770 | NK11: 8705 | NL11: 4348 | NM11: 4335 | NN11: 2505 | NO11: 1842 | NP11: 2562 | NQ11: 2640 | NR11: 14202 | NS11: 4400 | NT11: 1022 | NU11: 1708 | NV11: 9466 | NW11: 2160 | NX11: 13363 | NY11: 16476 | NZ11: 5630 | OA11: 8180 | OB11: 7937 | OC11: 3441 | OD11: 5674
A12: 25 to 29 years | B12: 7135 | C12: 8483 | D12: 23224 | E12: 4333 | F12: 4469 | G12: 29103 | H12: 31228 | I12: 4969 | J12: 25928 | K12: 3485 | L12: 9469 | M12: 5167 | N12: 4063 | O12: 16073 | P12: 14219 | Q12: 3561 | R12: 7831 | S12: 6298 | T12: 12135 | U12: 7269 | V12: 211788 | W12: 10647 | X12: 6876 | Y12: 20457 | Z12: 101479 | AA12: 35483 | AB12: 91296 | AC12: 4697 | AD12: 5403 | AE12: 29594 | AF12: 4030 | AG12: 3230 | AH12: 13853 | AI12: 3316 | AJ12: 8278 | AK12: 8045 | AL12: 6034 | AM12: 7247 | AN12: 37606 | AO12: 4390 | AP12: 5889 | AQ12: 5639 | AR12: 6212 | AS12: 28601 | AT12: 183119 | AU12: 12241 | AV12: 6477 | AW12: 6281 | AX12: 10824 | AY12: 27461 | AZ12: 15074 | BA12: 3401 | BB12: 37822 | BC12: 5284 | BD12: 8114 | BE12: 11949 | BF12: 21511 | BG12: 3085 | BH12: 1939 | BI12: 2464 | BJ12: 8958 | BK12: 4627 | BL12: 8378 | BM12: 6095 | BN12: 29159 | BO12: 94097 | BP12: 7232 | BQ12: 19143 | BR12: 3628 | BS12: 327140 | BT12: 7239 | BU12: 75646 | BV12: 16281 | BW12: 69415 | BX12: 3997 | BY12: 5512 | BZ12: 10563 | CA12: 33117 | CB12: 7688 | CC12: 27401 | CD12: 12289 | CE12: 3076 | CF12: 80424 | CG12: 15280 | CH12: 3721 | CI12: 11272 | CJ12: 291227 | CK12: 4786 | CL12: 6589 | CM12: 11276 | CN12: 27138 | CO12: 4761 | CP12: 2867 | CQ12: 19333 | CR12: 125417 | CS12: 26354 | CT12: 148965 | CU12: 4394 | CV12: 5918 | CW12: 3202 | CX12: 8366 | CY12: 20966 | CZ12: 2429 | DA12: 5987 | DB12: 6893 | DC12: 4375 | DD12: 6686 | DE12: 2570 | DF12: 35899 | DG12: 2066 | DH12: 8248 | DI12: 12950 | DJ12: 8749 | DK12: 5039 | DL12: 10517 | DM12: 3698 | DN12: 18342 | DO12: 21641 | DP12: 5479 | DQ12: 12918 | DR12: 5748 | DS12: 4651 | DT12: 3137 | DU12: 14624 | DV12: 7448 | DW12: 15979 | DX12: 42709 | DY12: 3134 | DZ12: 12736 | EA12: 7151 | EB12: 2774 | EC12: 3853 | ED12: 4340 | EE12: 4318 | EF12: 2300 | EG12: 5006 | EH12: 43295 | EI12: 2222 | EJ12: 3128 | EK12: 12496 | EL12: 10639 | EM12: 24478 | EN12: 5708 | EO12: 31001 | EP12: 2689 | EQ12: 12896 | ER12: 10302 | ES12: 4669 | ET12: 7637 | EU12: 19512 | EV12: 3933 | EW12: 37513 | EX12: 5234 | EY12: 2732 | EZ12: 11227 | FA12: 6517 | FB12: 4644 | FC12: 3358 | FD12: 2533 | FE12: 6357 | FF12: 256892 | FG12: 11209 | FH12: 18470 | FI12: 5386 | FJ12: 73841 | FK12: 7272 | FL12: 3378 | FM12: 5583 | FN12: 19286 | FO12: 5515 | FP12: 55744 | FQ12: 10472 | FR12: 5104 | FS12: 5016 | FT12: 6884 | FU12: 3578 | FV12: 4686 | FW12: 6531 | FX12: 4252 | FY12: 9400 | FZ12: 3383 | GA12: 76356 | GB12: 10729 | GC12: 5555 | GD12: 20579 | GE12: 9282 | GF12: 5665 | GG12: 21562 | GH12: 30711 | GI12: 2786 | GJ12: 5264 | GK12: 13177 | GL12: 8534 | GM12: 7866 | GN12: 5633 | GO12: 25091 | GP12: 17417 | GQ12: 16838 | GR12: 10108 | GS12: 8538 | GT12: 82296 | GU12: 4687 | GV12: 5678 | GW12: 4025 | GX12: 1885 | GY12: 3375 | GZ12: 19416 | HA12: 6747 | HB12: 3273 | HC12: 12952 | HD12: 25387 | HE12: 6513 | HF12: 9298 | HG12: 3440 | HH12: 485872 | HI12: 45886 | HJ12: 13401 | HK12: 8587 | HL12: 7339 | HM12: 27571 | HN12: 15292 | HO12: 7235 | HP12: 3318 | HQ12: 4692 | HR12: 6811 | HS12: 32264 | HT12: 6500 | HU12: 45195 | HV12: 10849 | HW12: 192007 | HX12: 4125 | HY12: 2489 | HZ12: 7053 | IA12: 53073 | IB12: 127001 | IC12: 3432 | ID12: 5147 | IE12: 13498 | IF12: 19417 | IG12: 6963 | IH12: 4643 | II12: 12414 | IJ12: 6079 | IK12: 3826 | IL12: 4089 | IM12: 3575 | IN12: 5903 | IO12: 9483 | IP12: 4150 | IQ12: 9025 | IR12: 75913 | IS12: 18930 | IT12: 30433 | IU12: 682920 | IV12: 4307 | IW12: 20293 | IX12: 10004 | IY12: 10543 | IZ12: 6599 | JA12: 24196 | JB12: 52263 | JC12: 10484 | JD12: 34146 | JE12: 99090 | JF12: 6256 | JG12: 3496 | JH12: 27845 | JI12: 2816 | JJ12: 18230 | JK12: 7151 | JL12: 2449 | JM12: 19333 | JN12: 10860 | JO12: 207819 | JP12: 186740 | JQ12: 2643 | JR12: 77497 | JS12: 3274 | JT12: 3308 | JU12: 9398 | JV12: 17450 | JW12: 90554 | JX12: 13513 | JY12: 5651 | JZ12: 55483 | KA12: 32085 | KB12: 5638 | KC12: 3975 | KD12: 6030 | KE12: 49770 | KF12: 5112 | KG12: 13546 | KH12: 5499 | KI12: 21135 | KJ12: 45466 | KK12: 168693 | KL12: 9251 | KM12: 7239 | KN12: 33454 | KO12: 10174 | KP12: 4290 | KQ12: 3197 | KR12: 80149 | KS12: 6042 | KT12: 6875 | KU12: 6161 | KV12: 3827 | KW12: 90011 | KX12: 15646 | KY12: 15178 | KZ12: 4561 | LA12: 53713 | LB12: 4453 | LC12: 97794 | LD12: 132016 | LE12: 3110 | LF12: 162124 | LG12: 80295 | LH12: 71131 | LI12: 7927 | LJ12: 8120 | LK12: 4068 | LL12: 15857 | LM12: 14280 | LN12: 15097 | LO12: 17306 | LP12: 168372 | LQ12: 3453 | LR12: 2574 | LS12: 3837 | LT12: 4208 | LU12: 11945 | LV12: 4026 | LW12: 4735 | LX12: 10758 | LY12: 7300 | LZ12: 10440 | MA12: 12468 | MB12: 21388 | MC12: 5854 | MD12: 15281 | ME12: 16793 | MF12: 4064 | MG12: 5644 | MH12: 3874 | MI12: 27328 | MJ12: 3797 | MK12: 19972 | ML12: 13188 | MM12: 104580 | MN12: 5756 | MO12: 4819 | MP12: 20009 | MQ12: 6780 | MR12: 4162 | MS12: 12143 | MT12: 36970 | MU12: 34678 | MV12: 9335 | MW12: 3701 | MX12: 7782 | MY12: 37156 | MZ12: 8663 | NA12: 5370 | NB12: 15535 | NC12: 3008 | ND12: 5454 | NE12: 66766 | NF12: 16755 | NG12: 9984 | NH12: 1964 | NI12: 6542 | NJ12: 213308 | NK12: 14588 | NL12: 5375 | NM12: 5760 | NN12: 4267 | NO12: 3231 | NP12: 4022 | NQ12: 4120 | NR12: 22877 | NS12: 5881 | NT12: 1969 | NU12: 3203 | NV12: 12748 | NW12: 4635 | NX12: 20743 | NY12: 27705 | NZ12: 8939 | OA12: 13917 | OB12: 13395 | OC12: 6323 | OD12: 8218
A13: 30 to 34 years | B13: 6910 | C13: 7418 | D13: 22785 | E13: 4309 | F13: 4665 | G13: 29771 | H13: 33192 | I13: 5275 | J13: 28464 | K13: 4017 | L13: 9793 | M13: 3757 | N13: 3906 | O13: 16951 | P13: 13008 | Q13: 3169 | R13: 8227 | S13: 5871 | T13: 13496 | U13: 6772 | V13: 219229 | W13: 11011 | X13: 6352 | Y13: 21472 | Z13: 112984 | AA13: 36788 | AB13: 100359 | AC13: 5274 | AD13: 5409 | AE13: 29152 | AF13: 4168 | AG13: 3182 | AH13: 14394 | AI13: 3590 | AJ13: 8168 | AK13: 9293 | AL13: 6413 | AM13: 6723 | AN13: 39505 | AO13: 4953 | AP13: 5553 | AQ13: 5379 | AR13: 5327 | AS13: 28705 | AT13: 185587 | AU13: 11713 | AV13: 6255 | AW13: 4993 | AX13: 10775 | AY13: 28378 | AZ13: 13491 | BA13: 3138 | BB13: 40688 | BC13: 5717 | BD13: 7928 | BE13: 12312 | BF13: 22588 | BG13: 2905 | BH13: 2206 | BI13: 2931 | BJ13: 9371 | BK13: 5178 | BL13: 7631 | BM13: 6103 | BN13: 31377 | BO13: 99088 | BP13: 7259 | BQ13: 19757 | BR13: 3734 | BS13: 336511 | BT13: 6898 | BU13: 76976 | BV13: 14229 | BW13: 71455 | BX13: 4023 | BY13: 6065 | BZ13: 9180 | CA13: 32054 | CB13: 7218 | CC13: 27723 | CD13: 12108 | CE13: 2982 | CF13: 85726 | CG13: 15569 | CH13: 2869 | CI13: 11611 | CJ13: 299933 | CK13: 5209 | CL13: 6797 | CM13: 11678 | CN13: 27583 | CO13: 4788 | CP13: 2925 | CQ13: 20591 | CR13: 137845 | CS13: 26954 | CT13: 153258 | CU13: 4569 | CV13: 6173 | CW13: 3102 | CX13: 8784 | CY13: 22455 | CZ13: 1953 | DA13: 5770 | DB13: 7592 | DC13: 4284 | DD13: 6440 | DE13: 2882 | DF13: 33781 | DG13: 2094 | DH13: 8936 | DI13: 12727 | DJ13: 8771 | DK13: 4466 | DL13: 10536 | DM13: 4065 | DN13: 15610 | DO13: 21813 | DP13: 4974 | DQ13: 12625 | DR13: 5835 | DS13: 4302 | DT13: 2822 | DU13: 13530 | DV13: 7586 | DW13: 15469 | DX13: 44956 | DY13: 3076 | DZ13: 11530 | EA13: 7206 | EB13: 3017 | EC13: 4159 | ED13: 4238 | EE13: 3919 | EF13: 2519 | EG13: 5185 | EH13: 43283 | EI13: 2641 | EJ13: 3082 | EK13: 14593 | EL13: 10969 | EM13: 24272 | EN13: 5470 | EO13: 31986 | EP13: 2334 | EQ13: 13419 | ER13: 10845 | ES13: 4873 | ET13: 7448 | EU13: 20795 | EV13: 4310 | EW13: 38057 | EX13: 4896 | EY13: 2968 | EZ13: 11373 | FA13: 5745 | FB13: 3672 | FC13: 4040 | FD13: 2788 | FE13: 6855 | FF13: 274205 | FG13: 10958 | FH13: 18651 | FI13: 5805 | FJ13: 76445 | FK13: 5967 | FL13: 2716 | FM13: 5736 | FN13: 19705 | FO13: 5621 | FP13: 59926 | FQ13: 8549 | FR13: 5136 | FS13: 5194 | FT13: 6736 | FU13: 3567 | FV13: 4726 | FW13: 6354 | FX13: 4868 | FY13: 8562 | FZ13: 3347 | GA13: 79125 | GB13: 11524 | GC13: 5582 | GD13: 19442 | GE13: 9331 | GF13: 6078 | GG13: 21872 | GH13: 30742 | GI13: 2560 | GJ13: 5179 | GK13: 14554 | GL13: 7492 | GM13: 8442 | GN13: 6260 | GO13: 27820 | GP13: 18375 | GQ13: 15586 | GR13: 9210 | GS13: 6926 | GT13: 89618 | GU13: 3971 | GV13: 5463 | GW13: 4247 | GX13: 1998 | GY13: 3641 | GZ13: 17901 | HA13: 7214 | HB13: 3143 | HC13: 11390 | HD13: 25405 | HE13: 5160 | HF13: 9117 | HG13: 3750 | HH13: 523102 | HI13: 47746 | HJ13: 12454 | HK13: 7864 | HL13: 7496 | HM13: 25231 | HN13: 16029 | HO13: 5356 | HP13: 3344 | HQ13: 4446 | HR13: 5942 | HS13: 29913 | HT13: 7191 | HU13: 45471 | HV13: 11047 | HW13: 215072 | HX13: 4250 | HY13: 2800 | HZ13: 7738 | IA13: 53759 | IB13: 136604 | IC13: 3303 | ID13: 4886 | IE13: 13653 | IF13: 20394 | IG13: 7246 | IH13: 5052 | II13: 12699 | IJ13: 5569 | IK13: 3723 | IL13: 4305 | IM13: 3231 | IN13: 6091 | IO13: 10126 | IP13: 4101 | IQ13: 9524 | IR13: 79348 | IS13: 18582 | IT13: 34266 | IU13: 727005 | IV13: 4549 | IW13: 21237 | IX13: 9558 | IY13: 11099 | IZ13: 7500 | JA13: 23577 | JB13: 52078 | JC13: 11189 | JD13: 34764 | JE13: 105907 | JF13: 6065 | JG13: 3896 | JH13: 28780 | JI13: 2993 | JJ13: 19141 | JK13: 7825 | JL13: 2569 | JM13: 19233 | JN13: 11661 | JO13: 225169 | JP13: 188439 | JQ13: 3215 | JR13: 84022 | JS13: 3398 | JT13: 3146 | JU13: 8547 | JV13: 19091 | JW13: 102319 | JX13: 15013 | JY13: 5851 | JZ13: 59825 | KA13: 24670 | KB13: 5793 | KC13: 4318 | KD13: 6035 | KE13: 54162 | KF13: 5139 | KG13: 14102 | KH13: 5930 | KI13: 22318 | KJ13: 48900 | KK13: 175559 | KL13: 9443 | KM13: 7547 | KN13: 35786 | KO13: 10307 | KP13: 4388 | KQ13: 3249 | KR13: 88577 | KS13: 5884 | KT13: 6436 | KU13: 5564 | KV13: 4011 | KW13: 94346 | KX13: 15699 | KY13: 15849 | KZ13: 4664 | LA13: 52738 | LB13: 4415 | LC13: 101638 | LD13: 139943 | LE13: 2967 | LF13: 193043 | LG13: 89156 | LH13: 66855 | LI13: 8475 | LJ13: 7985 | LK13: 4515 | LL13: 14643 | LM13: 16113 | LN13: 15692 | LO13: 19064 | LP13: 189184 | LQ13: 3973 | LR13: 2432 | LS13: 3485 | LT13: 4548 | LU13: 12857 | LV13: 4258 | LW13: 4752 | LX13: 11125 | LY13: 7598 | LZ13: 10451 | MA13: 13034 | MB13: 22745 | MC13: 6113 | MD13: 15575 | ME13: 15861 | MF13: 4024 | MG13: 5642 | MH13: 4363 | MI13: 28555 | MJ13: 3575 | MK13: 20811 | ML13: 12236 | MM13: 113556 | MN13: 5940 | MO13: 5203 | MP13: 20148 | MQ13: 6625 | MR13: 4730 | MS13: 12320 | MT13: 34998 | MU13: 35908 | MV13: 9068 | MW13: 4024 | MX13: 7762 | MY13: 37710 | MZ13: 8911 | NA13: 4860 | NB13: 16986 | NC13: 3331 | ND13: 6183 | NE13: 67067 | NF13: 17260 | NG13: 9066 | NH13: 2121 | NI13: 6877 | NJ13: 230119 | NK13: 15061 | NL13: 5086 | NM13: 4689 | NN13: 4318 | NO13: 3303 | NP13: 4277 | NQ13: 4401 | NR13: 22043 | NS13: 5574 | NT13: 2690 | NU13: 3755 | NV13: 12901 | NW13: 4633 | NX13: 21116 | NY13: 29678 | NZ13: 8666 | OA13: 15116 | OB13: 13413 | OC13: 6875 | OD13: 7865
... A50: 85 years and over | B50: 2368 | C50: 4392 | D50: 10502 | E50: 1757 | F50: 1859 | G50: 12919 | H50: 11363 | I50: 1580 | J50: 14157 | K50: 2241 | L50: 3172 | M50: 1319 | N50: 1996 | O50: 2270 | P50: 3729 | Q50: 1494 | R50: 2820 | S50: 3350 | T50: 6440 | U50: 1870 | V50: 48817 | W50: 4857 | X50: 1563 | Y50: 6554 | Z50: 16874 | AA50: 6458 | AB50: 34649 | AC50: 2181 | AD50: 5510 | AE50: 7132 | AF50: 1738 | AG50: 1650 | AH50: 4652 | AI50: 1307 | AJ50: 2486 | AK50: 2731 | AL50: 2607 | AM50: 4676 | AN50: 13698 | AO50: 1806 | AP50: 1775 | AQ50: 1682 | AR50: 1654 | AS50: 7644 | AT50: 66489 | AU50: 4077 | AV50: 1814 | AW50: 847 | AX50: 2962 | AY50: 14687 | AZ50: 4154 | BA50: 1765 | BB50: 18195 | BC50: 2111 | BD50: 2450 | BE50: 6089 | BF50: 14868 | BG50: 1277 | BH50: 1163 | BI50: 843 | BJ50: 3929 | BK50: 2796 | BL50: 2357 | BM50: 3446 | BN50: 7864 | BO50: 25705 | BP50: 3172 | BQ50: 7423 | BR50: 1192 | BS50: 113908 | BT50: 2180 | BU50: 26009 | BV50: 2001 | BW50: 33287 | BX50: 1735 | BY50: 1911 | BZ50: 2438 | CA50: 6468 | CB50: 2033 | CC50: 8667 | CD50: 3473 | CE50: 1117 | CF50: 19967 | CG50: 5578 | CH50: 1487 | CI50: 2996 | CJ50: 58346 | CK50: 1309 | CL50: 2854 | CM50: 5614 | CN50: 11390 | CO50: 1686 | CP50: 1839 | CQ50: 11501 | CR50: 26317 | CS50: 7867 | CT50: 58302 | CU50: 2131 | CV50: 2045 | CW50: 1752 | CX50: 4372 | CY50: 6102 | CZ50: 482 | DA50: 2334 | DB50: 1995 | DC50: 1506 | DD50: 2757 | DE50: 1405 | DF50: 8119 | DG50: 777 | DH50: 3786 | DI50: 4985 | DJ50: 3887 | DK50: 488 | DL50: 2966 | DM50: 1407 | DN50: 3499 | DO50: 4540 | DP50: 898 | DQ50: 5802 | DR50: 2122 | DS50: 2125 | DT50: 1440 | DU50: 4276 | DV50: 2522 | DW50: 5404 | DX50: 10680 | DY50: 1137 | DZ50: 4324 | EA50: 2127 | EB50: 1622 | EC50: 2009 | ED50: 1064 | EE50: 1399 | EF50: 1008 | EG50: 2123 | EH50: 13209 | EI50: 1363 | EJ50: 944 | EK50: 2605 | EL50: 3653 | EM50: 9654 | EN50: 1627 | EO50: 10139 | EP50: 1140 | EQ50: 3881 | ER50: 3300 | ES50: 1002 | ET50: 1266 | EU50: 9819 | EV50: 1521 | EW50: 18535 | EX50: 1206 | EY50: 863 | EZ50: 4852 | FA50: 2880 | FB50: 366 | FC50: 3622 | FD50: 1189 | FE50: 2106 | FF50: 52653 | FG50: 4838 | FH50: 5562 | FI50: 1242 | FJ50: 22010 | FK50: 1946 | FL50: 1036 | FM50: 2137 | FN50: 7032 | FO50: 2153 | FP50: 18756 | FQ50: 951 | FR50: 2196 | FS50: 1780 | FT50: 2633 | FU50: 2654 | FV50: 1560 | FW50: 2243 | FX50: 2327 | FY50: 3112 | FZ50: 1123 | GA50: 25042 | GB50: 2704 | GC50: 1455 | GD50: 3967 | GE50: 4265 | GF50: 3049 | GG50: 9146 | GH50: 11663 | GI50: 1460 | GJ50: 2824 | GK50: 4154 | GL50: 2368 | GM50: 2521 | GN50: 3379 | GO50: 10049 | GP50: 10281 | GQ50: 5687 | GR50: 1869 | GS50: 2465 | GT50: 19133 | GU50: 990 | GV50: 1212 | GW50: 2809 | GX50: 1258 | GY50: 1529 | GZ50: 5106 | HA50: 2096 | HB50: 1612 | HC50: 3524 | HD50: 8233 | HE50: 1059 | HF50: 3651 | HG50: 1355 | HH50: 161485 | HI50: 15022 | HJ50: 4093 | HK50: 3440 | HL50: 2887 | HM50: 7784 | HN50: 5245 | HO50: 1121 | HP50: 1471 | HQ50: 1714 | HR50: 5121 | HS50: 7338 | HT50: 3960 | HU50: 13074 | HV50: 2425 | HW50: 105346 | HX50: 1528 | HY50: 1301 | HZ50: 1330 | IA50: 21908 | IB50: 41031 | IC50: 1061 | ID50: 1176 | IE50: 4355 | IF50: 5853 | IG50: 2990 | IH50: 2010 | II50: 4172 | IJ50: 1164 | IK50: 1360 | IL50: 1743 | IM50: 1511 | IN50: 2217 | IO50: 3949 | IP50: 2314 | IQ50: 8967 | IR50: 17301 | IS50: 9346 | IT50: 11837 | IU50: 277541 | IV50: 2813 | IW50: 21130 | IX50: 4057 | IY50: 7717 | IZ50: 1106 | JA50: 4142 | JB50: 12863 | JC50: 3676 | JD50: 9563 | JE50: 29559 | JF50: 2495 | JG50: 1380 | JH50: 11247 | JI50: 1528 | JJ50: 11591 | JK50: 2427 | JL50: 1238 | JM50: 5914 | JN50: 5647 | JO50: 83322 | JP50: 54542 | JQ50: 1535 | JR50: 43146 | JS50: 2723 | JT50: 805 | JU50: 4655 | JV50: 7998 | JW50: 27269 | JX50: 9137 | JY50: 3946 | JZ50: 23576 | KA50: 3363 | KB50: 2252 | KC50: 4810 | KD50: 2486 | KE50: 12490 | KF50: 2061 | KG50: 7039 | KH50: 2561 | KI50: 5225 | KJ50: 14720 | KK50: 42937 | KL50: 5329 | KM50: 3593 | KN50: 16222 | KO50: 5284 | KP50: 2428 | KQ50: 1140 | KR50: 29741 | KS50: 2940 | KT50: 2601 | KU50: 2366 | KV50: 1511 | KW50: 37285 | KX50: 5280 | KY50: 4931 | KZ50: 1357 | LA50: 9104 | LB50: 1451 | LC50: 23851 | LD50: 36947 | LE50: 1997 | LF50: 64135 | LG50: 24212 | LH50: 39712 | LI50: 3634 | LJ50: 3577 | LK50: 2436 | LL50: 6310 | LM50: 7590 | LN50: 4236 | LO50: 10078 | LP50: 42358 | LQ50: 4759 | LR50: 2654 | LS50: 1779 | LT50: 1855 | LU50: 5366 | LV50: 1304 | LW50: 1568 | LX50: 3209 | LY50: 3381 | LZ50: 4239 | MA50: 4332 | MB50: 7626 | MC50: 3104 | MD50: 7186 | ME50: 5678 | MF50: 1978 | MG50: 2074 | MH50: 2167 | MI50: 7263 | MJ50: 1738 | MK50: 9445 | ML50: 3534 | MM50: 47682 | MN50: 2419 | MO50: 1709 | MP50: 6795 | MQ50: 3208 | MR50: 2565 | MS50: 5098 | MT50: 15156 | MU50: 11574 | MV50: 2703 | MW50: 1212 | MX50: 2954 | MY50: 19326 | MZ50: 4579 | NA50: 1343 | NB50: 5593 | NC50: 1361 | ND50: 1618 | NE50: 18523 | NF50: 3940 | NG50: 3626 | NH50: 1137 | NI50: 1714 | NJ50: 61605 | NK50: 7246 | NL50: 2461 | NM50: 1288 | NN50: 2156 | NO50: 2266 | NP50: 1897 | NQ50: 2231 | NR50: 8590 | NS50: 1648 | NT50: 3677 | NU50: 2052 | NV50: 5307 | NW50: 2016 | NX50: 9310 | NY50: 11132 | NZ50: 2673 | OA50: 6537 | OB50: 7869 | OC50: 1679 | OD50: 2613

Sheet race
A1: Label (Grouping) | B1: Abilene, TX | C1: Aguadilla, PR | D1: Akron, OH | E1: Albany, GA | F1: Albany, OR | G1: Albany-Schenectady-Troy, NY | H1: Albuquerque, NM | I1: Alexandria, LA | J1: Allentown-Bethlehem-Easton, PA-NJ | K1: Altoona, PA | L1: Amarillo, TX | M1: Ames, IA | N1: Amherst Town-Northampton, MA | O1: Anchorage, AK | P1: Ann Arbor, MI | Q1: Anniston-Oxford, AL | R1: Appleton, WI | S1: Arecibo, PR | T1: Asheville, NC | U1: Athens-Clarke County, GA | V1: Atlanta-Sandy Springs-Roswell, GA | W1: Atlantic City-Hammonton, NJ | X1: Auburn-Opelika, AL | Y1: Augusta-Richmond County, GA-SC | Z1: Austin-Round Rock-San Marcos, TX | AA1: Bakersfield-Delano, CA | AB1: Baltimore-Columbia-Towson, MD | AC1: Bangor, ME | AD1: Barnstable Town, MA | AE1: Baton Rouge, LA | AF1: Battle Creek, MI | AG1: Bay City, MI | AH1: Beaumont-Port Arthur, TX | AI1: Beckley, WV | AJ1: Bellingham, WA | AK1: Bend, OR | AL1: Billings, MT | AM1: Binghamton, NY | AN1: Birmingham, AL | AO1: Bismarck, ND | AP1: Blacksburg-Christiansburg-Radford, VA | AQ1: Bloomington, IL | AR1: Bloomington, IN | AS1: Boise City, ID | AT1: Boston-Cambridge-Newton, MA-NH | AU1: Boulder, CO | AV1: Bowling Green, KY | AW1: Bozeman, MT | AX1: Bremerton-Silverdale-Port Orchard, WA | AY1: Bridgeport-Stamford-Danbury, CT | AZ1: Brownsville-Harlingen, TX | BA1: Brunswick-St. Simons, GA | BB1: Buffalo-Cheektowaga, NY | BC1: Burlington, NC | BD1: Burlington-South Burlington, VT | BE1: Canton-Massillon, OH | BF1: Cape Coral-Fort Myers, FL | BG1: Cape Girardeau, MO-IL | BH1: Carson City, NV | BI1: Casper, WY | BJ1: Cedar Rapids, IA | BK1: Chambersburg, PA | BL1: Champaign-Urbana, IL | BM1: Charleston, WV | BN1: Charleston-North Charleston, SC | BO1: Charlotte-Concord-Gastonia, NC-SC | BP1: Charlottesville, VA | BQ1: Chattanooga, TN-GA | BR1: Cheyenne, WY | BS1: Chicago-Naperville-Elgin, IL-IN | BT1: Chico, CA | BU1: Cincinnati, OH-KY-IN | BV1: Clarksville, TN-KY | BW1: Cleveland, OH | BX1: Cleveland, TN | BY1: Coeur d'Alene, ID | BZ1: College Station-Bryan, TX | CA1: Colorado Springs, CO | CB1: Columbia, MO | CC1: Columbia, SC | CD1: Columbus, GA-AL | CE1: Columbus, IN | CF1: Columbus, OH | CG1: Corpus Christi, TX | CH1: Corvallis, OR | CI1: Crestview-Fort Walton Beach-Destin, FL | CJ1: Dallas-Fort Worth-Arlington, TX | CK1: Dalton, GA | CL1: Daphne-Fairhope-Foley, AL | CM1: Davenport-Moline-Rock Island, IA-IL | CN1: Dayton-Kettering-Beavercreek, OH | CO1: Decatur, AL | CP1: Decatur, IL | CQ1: Deltona-Daytona Beach-Ormond Beach, FL | CR1: Denver-Aurora-Centennial, CO | CS1: Des Moines-West Des Moines, IA | CT1: Detroit-Warren-Dearborn, MI | CU1: Dothan, AL | CV1: Dover, DE | CW1: Dubuque, IA | CX1: Duluth, MN-WI | CY1: Durham-Chapel Hill, NC | CZ1: Eagle Pass, TX | DA1: Eau Claire, WI | DB1: El Centro, CA | DC1: Elizabethtown, KY | DD1: Elkhart-Goshen, IN | DE1: Elmira, NY | DF1: El Paso, TX | DG1: Enid, OK | DH1: Erie, PA | DI1: Eugene-Springfield, OR | DJ1: Evansville, IN | DK1: Fairbanks-College, AK | DL1: Fargo, ND-MN | DM1: Farmington, NM | DN1: Fayetteville, NC | DO1: Fayetteville-Springdale-Rogers, AR | DP1: Flagstaff, AZ | DQ1: Flint, MI | DR1: Florence, SC | DS1: Florence-Muscle Shoals, AL | DT1: Fond du Lac, WI | DU1: Fort Collins-Loveland, CO | DV1: Fort Smith, AR-OK | DW1: Fort Wayne, IN | DX1: Fresno, CA | DY1: Gadsden, AL | DZ1: Gainesville, FL | EA1: Gainesville, GA | EB1: Gettysburg, PA | EC1: Glens Falls, NY | ED1: Goldsboro, NC | EE1: Grand Forks, ND-MN | EF1: Grand Island, NE | EG1: Grand Junction, CO | EH1: Grand Rapids-Wyoming-Kentwood, MI | EI1: Grants Pass, OR | EJ1: Great Falls, MT | EK1: Greeley, CO | EL1: Green Bay, WI | EM1: Greensboro-High Point, NC | EN1: Greenville, NC | EO1: Greenville-Anderson-Greer, SC | EP1: Guayama, PR | EQ1: Gulfport-Biloxi, MS | ER1: Hagerstown-Martinsburg, MD-WV | ES1: Hammond, LA | ET1: Hanford-Corcoran, CA | EU1: Harrisburg-Carlisle, PA | EV1: Harrisonburg, VA | EW1: Hartford-West Hartford-East Hartford, CT | EX1: Hattiesburg, MS | EY1: Helena, MT | EZ1: Hickory-Lenoir-Morganton, NC | FA1: Hilton Head Island-Bluffton-Port Royal, SC | FB1: Hinesville, GA | FC1: Homosassa Springs, FL | FD1: Hot Springs, AR | FE1: Houma-Bayou Cane-Thibodaux, LA | FF1: Houston-Pasadena-The Woodlands, TX | FG1: Huntington-Ashland, WV-KY-OH | FH1: Huntsville, AL | FI1: Idaho Falls, ID | FJ1: Indianapolis-Carmel-Greenwood, IN | FK1: Iowa City, IA | FL1: Ithaca, NY | FM1: Jackson, MI | FN1: Jackson, MS | FO1: Jackson, TN | FP1: Jacksonville, FL | FQ1: Jacksonville, NC | FR1: Janesville-Beloit, WI | FS1: Jefferson City, MO | FT1: Johnson City, TN | FU1: Johnstown, PA | FV1: Jonesboro, AR | FW1: Joplin, MO-KS | FX1: Kahului-Wailuku, HI | FY1: Kalamazoo-Portage, MI | FZ1: Kankakee, IL | GA1: Kansas City, MO-KS | GB1: Kennewick-Richland, WA | GC1: Kenosha, WI | GD1: Killeen-Temple, TX | GE1: Kingsport-Bristol, TN-VA | GF1: Kingston, NY | GG1: Kiryas Joel-Poughkeepsie-Newburgh, NY | GH1: Knoxville, TN | GI1: Kokomo, IN | GJ1: La Crosse-Onalaska, WI-MN | GK1: Lafayette, LA | GL1: Lafayette-West Lafayette, IN | GM1: Lake Charles, LA | GN1: Lake Havasu City-Kingman, AZ | GO1: Lakeland-Winter Haven, FL | GP1: Lancaster, PA | GQ1: Lansing-East Lansing, MI | GR1: Laredo, TX | GS1: Las Cruces, NM | GT1: Las Vegas-Henderson-North Las Vegas, NV | GU1: Lawrence, KS | GV1: Lawton, OK | GW1: Lebanon, PA | GX1: Lewiston, ID-WA | GY1: Lewiston-Auburn, ME | GZ1: Lexington-Fayette, KY | HA1: Lexington Park, MD | HB1: Lima, OH | HC1: Lincoln, NE | HD1: Little Rock-North Little Rock-Conway, AR | HE1: Logan, UT-ID | HF1: Longview, TX | HG1: Longview-Kelso, WA | HH1: Los Angeles-Long Beach-Anaheim, CA | HI1: Louisville/Jefferson County, KY-IN | HJ1: Lubbock, TX | HK1: Lynchburg, VA | HL1: Macon-Bibb County, GA | HM1: Madison, WI | HN1: Manchester-Nashua, NH | HO1: Manhattan, KS | HP1: Mankato, MN | HQ1: Mansfield, OH | HR1: Mayagüez, PR | HS1: McAllen-Edinburg-Mission, TX | HT1: Medford, OR | HU1: Memphis, TN-MS-AR | HV1: Merced, CA | HW1: Miami-Fort Lauderdale-West Palm Beach, FL | HX1: Michigan City-La Porte, IN | HY1: Midland, MI | HZ1: Midland, TX | IA1: Milwaukee-Waukesha, WI | IB1: Minneapolis-St. Paul-Bloomington, MN-WI | IC1: Minot, ND | ID1: Missoula, MT | IE1: Mobile, AL | IF1: Modesto, CA | IG1: Monroe, LA | IH1: Monroe, MI | II1: Montgomery, AL | IJ1: Morgantown, WV | IK1: Morristown, TN | IL1: Mount Vernon-Anacortes, WA | IM1: Muncie, IN | IN1: Muskegon-Norton Shores, MI | IO1: Myrtle Beach-Conway-North Myrtle Beach, SC | IP1: Napa, CA | IQ1: Naples-Marco Island, FL | IR1: Nashville-Davidson--Murfreesboro--Franklin, TN | IS1: New Haven, CT | IT1: New Orleans-Metairie, LA | IU1: New York-Newark-Jersey City, NY-NJ | IV1: Niles, MI | IW1: North Port-Bradenton-Sarasota, FL | IX1: Norwich-New London-Willimantic, CT | IY1: Ocala, FL | IZ1: Odessa, TX | JA1: Ogden, UT | JB1: Oklahoma City, OK | JC1: Olympia-Lacey-Tumwater, WA | JD1: Omaha, NE-IA | JE1: Orlando-Kissimmee-Sanford, FL | JF1: Oshkosh-Neenah, WI | JG1: Owensboro, KY | JH1: Oxnard-Thousand Oaks-Ventura, CA | JI1: Paducah, KY-IL | JJ1: Palm Bay-Melbourne-Titusville, FL | JK1: Panama City-Panama City Beach, FL | JL1: Parkersburg-Vienna, WV | JM1: Pensacola-Ferry Pass-Brent, FL | JN1: Peoria, IL | JO1: Philadelphia-Camden-Wilmington, PA-NJ-DE-MD | JP1: Phoenix-Mesa-Chandler, AZ | JQ1: Pinehurst-Southern Pines, NC | JR1: Pittsburgh, PA | JS1: Pittsfield, MA | JT1: Pocatello, ID | JU1: Ponce, PR | JV1: Portland-South Portland, ME | JW1: Portland-Vancouver-Hillsboro, OR-WA | JX1: Port St. Lucie, FL | JY1: Prescott Valley-Prescott, AZ | JZ1: Providence-Warwick, RI-MA | KA1: Provo-Orem-Lehi, UT | KB1: Pueblo, CO | KC1: Punta Gorda, FL | KD1: Racine-Mount Pleasant, WI | KE1: Raleigh-Cary, NC | KF1: Rapid City, SD | KG1: Reading, PA | KH1: Redding, CA | KI1: Reno, NV | KJ1: Richmond, VA | KK1: Riverside-San Bernardino-Ontario, CA | KL1: Roanoke, VA | KM1: Rochester, MN | KN1: Rochester, NY | KO1: Rockford, IL | KP1: Rocky Mount, NC | KQ1: Rome, GA | KR1: Sacramento-Roseville-Folsom, CA | KS1: Saginaw, MI | KT1: St. Cloud, MN | KU1: St. George, UT | KV1: St. Joseph, MO-KS | KW1: St. Louis, MO-IL | KX1: Salem, OR | KY1: Salinas, CA | KZ1: Salisbury, MD | LA1: Salt Lake City-Murray, UT | LB1: San Angelo, TX | LC1: San Antonio-New Braunfels, TX | LD1: San Diego-Chula Vista-Carlsbad, CA | LE1: Sandusky, OH | LF1: San Francisco-Oakland-Fremont, CA | LG1: San Jose-Sunnyvale-Santa Clara, CA | LH1: San Juan-Bayamón-Caguas, PR | LI1: San Luis Obispo-Paso Robles, CA | LJ1: Santa Cruz-Watsonville, CA | LK1: Santa Fe, NM | LL1: Santa Maria-Santa Barbara, CA | LM1: Santa Rosa-Petaluma, CA | LN1: Savannah, GA | LO1: Scranton--Wilkes-Barre, PA | LP1: Seattle-Tacoma-Bellevue, WA | LQ1: Sebastian-Vero Beach-West Vero Corridor, FL | LR1: Sebring, FL | LS1: Sheboygan, WI | LT1: Sherman-Denison, TX | LU1: Shreveport-Bossier City, LA | LV1: Sierra Vista-Douglas, AZ | LW1: Sioux City, IA-NE-SD | LX1: Sioux Falls, SD-MN | LY1: Slidell-Mandeville-Covington, LA | LZ1: South Bend-Mishawaka, IN-MI | MA1: Spartanburg, SC | MB1: Spokane-Spokane Valley, WA | MC1: Springfield, IL | MD1: Springfield, MA | ME1: Springfield, MO | MF1: Springfield, OH | MG1: State College, PA | MH1: Staunton-Stuarts Draft, VA | MI1: Stockton-Lodi, CA | MJ1: Sumter, SC | MK1: Syracuse, NY | ML1: Tallahassee, FL | MM1: Tampa-St. Petersburg-Clearwater, FL | MN1: Terre Haute, IN | MO1: Texarkana, TX-AR | MP1: Toledo, OH | MQ1: Topeka, KS | MR1: Traverse City, MI | MS1: Trenton-Princeton, NJ | MT1: Tucson, AZ | MU1: Tulsa, OK | MV1: Tuscaloosa, AL | MW1: Twin Falls, ID | MX1: Tyler, TX | MY1: Urban Honolulu, HI | MZ1: Utica-Rome, NY | NA1: Valdosta, GA | NB1: Vallejo, CA | NC1: Victoria, TX | ND1: Vineland, NJ | NE1: Virginia Beach-Chesapeake-Norfolk, VA-NC | NF1: Visalia, CA | NG1: Waco, TX | NH1: Walla Walla, WA | NI1: Warner Robins, GA | NJ1: Washington-Arlington-Alexandria, DC-VA-MD-WV | NK1: Waterbury-Shelton, CT | NL1: Waterloo-Cedar Falls, IA | NM1: Watertown-Fort Drum, NY | NN1: Wausau, WI | NO1: Weirton-Steubenville, WV-OH | NP1: Wenatchee-East Wenatchee, WA | NQ1: Wheeling, WV-OH | NR1: Wichita, KS | NS1: Wichita Falls, TX | NT1: Wildwood-The Villages, FL | NU1: Williamsport, PA | NV1: Wilmington, NC | NW1: Winchester, VA-WV | NX1: Winston-Salem, NC | NY1: Worcester, MA | NZ1: Yakima, WA | OA1: York-Hanover, PA | OB1: Youngstown-Warren, OH | OC1: Yuba City, CA | OD1: Yuma, AZ
A2: Total: | B2: 180408 | C2: 251769 | D2: 699820 | E2: 146018 | F2: 130706 | G2: 906052 | H2: 921482 | I2: 149622 | J2: 873603 | K2: 121277 | L2: 271917 | M2: 127134 | N2: 162028 | O2: 401964 | P2: 369822 | Q2: 116090 | R2: 245768 | S2: 180767 | T2: 414711 | U2: 220197 | V2: 6256377 | W2: 371211 | X2: 199825 | Y2: 624181 | Z2: 2426592 | AA2: 915075 | AB2: 2849436 | AC2: 154710 | AD2: 231668 | AE2: 875313 | AF2: 133778 | AG2: 103008 | AH2: 396827 | AI2: 112714 | AJ2: 230503 | AK2: 257814 | AL2: 189255 | AM2: 245242 | AN2: 1184613 | AO2: 136216 | AP2: 181664 | AQ2: 171556 | AR2: 162569 | AS2: 811115 | AT2: 4953354 | AU2: 328961 | AV2: 186959 | AW2: 124074 | AX2: 277881 | AY2: 956330 | AZ2: 426120 | BA2: 115074 | BB2: 1161343 | BC2: 176893 | BD2: 227846 | BE2: 400372 | BF2: 817666 | BG2: 98169 | BH2: 58384 | BI2: 79977 | BJ2: 276624 | BK2: 157379 | BL2: 238842 | BM2: 205398 | BN2: 834267 | BO2: 2768407 | BP2: 224335 | BQ2: 575812 | BR2: 101060 | BS2: 9371595 | BT2: 207929 | BU2: 2270706 | BV2: 334564 | BW2: 2171526 | BX2: 128963 | BY2: 181996 | BZ2: 278335 | CA2: 767824 | CB2: 215014 | CC2: 849181 | CD2: 325615 | CE2: 83536 | CF2: 2175788 | CG2: 448012 | CH2: 96303 | CI2: 299547 | CJ2: 7985590 | CK2: 144160 | CL2: 246989 | CM2: 381503 | CN2: 816080 | CO2: 157747 | CP2: 101849 | CQ2: 706150 | CR2: 3002721 | CS2: 731120 | CT2: 4376828 | CU2: 152674 | CV2: 187604 | CW2: 99030 | CX2: 280870 | CY2: 601724 | CZ2: 58082 | DA2: 173915 | DB2: 180202 | DC2: 127049 | DD2: 207132 | DE2: 82147 | DF2: 874182 | DG2: 62146 | DH2: 269052 | DI2: 384207 | DJ2: 270494 | DK2: 95460 | DL2: 259459 | DM2: 120942 | DN2: 392380 | DO2: 577726 | DP2: 144508 | DQ2: 403305 | DR2: 199675 | DS2: 153852 | DT2: 104137 | DU2: 367368 | DV2: 229899 | DW2: 455416 | DX2: 1177665 | DY2: 103105 | DZ2: 349923 | EA2: 212705 | EB2: 106115 | EC2: 126039 | ED2: 118652 | EE2: 103628 | EF2: 76794 | EG2: 158601 | EH2: 1162152 | EI2: 88179 | EJ2: 84606 | EK2: 350396 | EL2: 331145 | EM2: 786419 | EN2: 177193 | EO2: 961939 | EP2: 66202 | EQ2: 421201 | ER2: 302649 | ES2: 136738 | ET2: 153298 | EU2: 604155 | EV2: 136992 | EW2: 1153112 | EX2: 155434 | EY2: 93906 | EZ2: 368316 | FA2: 227455 | FB2: 85771 | FC2: 162472 | FD2: 100035 | FE2: 202438 | FF2: 7442788 | FG2: 370729 | FH2: 516951 | FI2: 165361 | FJ2: 2130055 | FK2: 179200 | FL2: 104537 | FM2: 160060 | FN2: 611324 | FO2: 181719 | FP2: 1683960 | FQ2: 207906 | FR2: 164350 | FS2: 150437 | FT2: 210729 | FU2: 131538 | FV2: 135792 | FW2: 203626 | FX2: 164589 | FY2: 262375 | FZ2: 106635 | GA2: 2218142 | GB2: 311807 | GC2: 168438 | GD2: 494360 | GE2: 310842 | GF2: 182601 | GG2: 704836 | GH2: 932241 | GI2: 83752 | GJ2: 170190 | GK2: 413428 | GL2: 226805 | GM2: 244027 | GN2: 220517 | GO2: 790694 | GP2: 557931 | GQ2: 472669 | GR2: 269294 | GS2: 224266 | GT2: 2329548 | GU2: 120302 | GV2: 127310 | GW2: 144186 | GX2: 65164 | GY2: 113423 | GZ2: 522560 | HA2: 209439 | HB2: 101348 | HC2: 344337 | HD2: 758629 | HE2: 155102 | HF2: 291044 | HG2: 112360 | HH2: 12974487 | HI2: 1372558 | HJ2: 358708 | HK2: 263798 | HL2: 234943 | HM2: 691830 | HN2: 426378 | HO2: 133965 | HP2: 104282 | HQ2: 125099 | HR2: 209892 | HS2: 891977 | HT2: 222645 | HU2: 1341924 | HV2: 290201 | HW2: 6249291 | HX2: 111917 | HY2: 83757 | HZ2: 180019 | IA2: 1568938 | IB2: 3713668 | IC2: 76484 | ID2: 125631 | IE2: 412590 | IF2: 553990 | IG2: 223674 | IH2: 155505 | II2: 386024 | IJ2: 141323 | IK2: 122533 | IL2: 131328 | IM2: 112280 | IN2: 175961 | IO2: 383016 | IP2: 134869 | IQ2: 398291 | IR2: 2079596 | IS2: 570598 | IT2: 981662 | IU2: 19798537 | IV2: 153288 | IW2: 889339 | IX2: 279971 | IY2: 400078 | IZ2: 164654 | JA2: 653374 | JB2: 1463267 | JC2: 299067 | JD2: 982064 | JE2: 2793746 | JF2: 171769 | JG2: 112762 | JH2: 837469 | JI2: 102748 | JJ2: 632780 | JK2: 211922 | JL2: 88460 | JM2: 524395 | JN2: 365202 | JO2: 6272014 | JP2: 5028754 | JQ2: 104876 | JR2: 2439940 | JS2: 129430 | JT2: 89454 | JU2: 270459 | JV2: 562843 | JW2: 2520987 | JX2: 522676 | JY2: 245480 | JZ2: 1684071 | KA2: 717986 | KB2: 169356 | KC2: 201064 | KD2: 197532 | KE2: 1487302 | KF2: 152950 | KG2: 433015 | KH2: 181436 | KI2: 563020 | KJ2: 1341248 | KK2: 4675704 | KL2: 314986 | KM2: 228522 | KN2: 1058413 | KO2: 336522 | KP2: 144952 | KQ2: 99693 | KR2: 2426388 | KS2: 188665 | KT2: 202458 | KU2: 196431 | KV2: 120012 | KW2: 2810850 | KX2: 438906 | KY2: 437613 | KZ2: 129736 | LA2: 1275870 | LB2: 120986 | LC2: 2662733 | LD2: 3288774 | LE2: 114575 | LF2: 4645029 | LG2: 1969337 | LH2: 2052186 | LI2: 281555 | LJ2: 264926 | LK2: 156105 | LL2: 443701 | LM2: 485040 | LN2: 418285 | LO2: 569788 | LP2: 4061920 | LQ2: 166936 | LR2: 105702 | LS2: 117991 | LT2: 143337 | LU2: 386819 | LV2: 125566 | LW2: 144682 | LX2: 298181 | LY2: 272421 | LZ2: 324560 | MA2: 374737 | MB2: 597123 | MC2: 207042 | MD2: 462815 | ME2: 486785 | MF2: 135158 | MG2: 158576 | MH2: 126822 | MI2: 797334 | MJ2: 104725 | MK2: 656410 | ML2: 391730 | MM2: 3304691 | MN2: 168719 | MO2: 146296 | MP2: 602322 | MQ2: 232468 | MR2: 155449 | MS2: 385864 | MT2: 1060490 | MU2: 1037534 | MV2: 278526 | MW2: 118907 | MX2: 241740 | MY2: 1001146 | MZ2: 288881 | NA2: 150188 | NB2: 451918 | NC2: 98554 | ND2: 153305 | NE2: 1787235 | NF2: 478693 | NG2: 302045 | NH2: 62161 | NI2: 198209 | NJ2: 6318377 | NK2: 454969 | NL2: 168637 | NM2: 115040 | NN2: 138403 | NO2: 114754 | NP2: 124538 | NQ2: 136920 | NR2: 652622 | NS2: 149358 | NT2: 143408 | NU2: 113489 | NV2: 453347 | NW2: 146386 | NX2: 689766 | NY2: 867788 | NZ2: 257152 | OA2: 462924 | OB2: 427420 | OC2: 183364 | OD2: 211741
A3: White alone | B3: 122818 | C3: 131441 | D3: 538312 | E3: 58490 | F3: 109727 | G3: 695032 | H3: 458742 | I3: 94383 | J3: 615933 | K3: 111706 | L3: 181703 | M3: 107930 | N3: 132861 | O3: 251199 | P3: 253992 | Q3: 81706 | R3: 212183 | S3: 66582 | T3: 341494 | U3: 146461 | V3: 2786510 | W3: 235875 | X3: 123219 | Y3: 332731 | Z3: 1373981 | AA3: 402035 | AB3: 1524516 | AC3: 141988 | AD3: 198817 | AE3: 473745 | AF3: 102224 | AG3: 93440 | AH3: 217977 | AI3: 100210 | AJ3: 179852 | AK3: 218752 | AL3: 163230 | AM3: 203147 | AN3: 738322 | AO3: 117650 | AP3: 155149 | AQ3: 133787 | AR3: 136172 | AS3: 647722 | AT3: 3334569 | AU3: 255881 | AV3: 149528 | AW3: 110173 | AX3: 208426 | AY3: 566565 | AZ3: 150891 | BA3: 78676 | BB3: 873962 | BC3: 106569 | BD3: 199832 | BE3: 341057 | BF3: 545381 | BG3: 83035 | BH3: 39667 | BI3: 70747 | BJ3: 235938 | BK3: 136565 | BL3: 161995 | BM3: 180662 | BN3: 534584 | BO3: 1620651 | BP3: 166173 | BQ3: 443701 | BR3: 81104 | BS3: 4956339 | BT3: 144544 | BU3: 1743212 | BV3: 220627 | BW3: 1508813 | BX3: 109065 | BY3: 158537 | BZ3: 176924 | CA3: 543653 | CB3: 168460 | CC3: 462561 | CD3: 145144 | CE3: 66196 | CF3: 1500632 | CG3: 220032 | CH3: 76292 | CI3: 225066 | CJ3: 3853944 | CK3: 100934 | CL3: 202133 | CM3: 297562 | CN3: 605523 | CO3: 117159 | CP3: 75616 | CQ3: 504728 | CR3: 1980991 | CS3: 583290 | CT3: 2825336 | CU3: 104830 | CV3: 108953 | CW3: 88050 | CX3: 252141 | CY3: 329630 | CZ3: 9998 | DA3: 156049 | DB3: 35716 | DC3: 98756 | DD3: 152453 | DE3: 69816 | DF3: 258775 | DG3: 45476 | DH3: 222619 | DI3: 310002 | DJ3: 229128 | DK3: 65695 | DL3: 215325 | DM3: 48274 | DN3: 164367 | DO3: 356428 | DP3: 80956 | DQ3: 290657 | DR3: 101892 | DS3: 124274 | DT3: 91257 | DU3: 302769 | DV3: 162152 | DW3: 337724 | DX3: 421311 | DY3: 79440 | DZ3: 227894 | EA3: 134591 | EB3: 94377 | EC3: 115271 | ED3: 60942 | EE3: 86922 | EF3: 53529 | EG3: 130703 | EH3: 910164 | EI3: 75554 | EJ3: 70806 | EK3: 254790 | EL3: 270257 | EM3: 441692 | EN3: 93301 | EO3: 687137 | EP3: 18922 | EQ3: 281878 | ER3: 237521 | ES3: 83696 | ET3: 58349 | EU3: 446382 | EV3: 106599 | EW3: 765905 | EX3: 99965 | EY3: 85151 | EZ3: 294009 | FA3: 150653 | FB3: 35737 | FC3: 142299 | FD3: 82699 | FE3: 140785 | FF3: 2989459 | FG3: 345709 | FH3: 337850 | FI3: 140613 | FJ3: 1471834 | FK3: 139991 | FL3: 78663 | FM3: 133048 | FN3: 278029 | FO3: 117160 | FP3: 1029353 | FQ3: 139725 | FR3: 134161 | FS3: 128095 | FT3: 187469 | FU3: 119720 | FV3: 100455 | FW3: 169111 | FX3: 49699 | FY3: 199261 | FZ3: 78270 | GA3: 1586138 | GB3: 193272 | GC3: 126687 | GD3: 257273 | GE3: 288718 | GF3: 136255 | GG3: 457249 | GH3: 790400 | GI3: 70905 | GJ3: 153057 | GK3: 276468 | GL3: 175382 | GM3: 165052 | GN3: 175733 | GO3: 438493 | GP3: 455405 | GQ3: 354191 | GR3: 55703 | GS3: 91627 | GT3: 1016671 | GU3: 93924 | GV3: 74473 | GW3: 116318 | GX3: 57272 | GY3: 99336 | GZ3: 393628 | HA3: 152848 | HB3: 81056 | HC3: 280053 | HD3: 490241 | HE3: 131102 | HF3: 184455 | HG3: 93447 | HH3: 4377828 | HI3: 1009069 | HJ3: 223499 | HK3: 196940 | HL3: 110240 | HM3: 552260 | HN3: 347760 | HO3: 99837 | HP3: 89471 | HQ3: 105826 | HR3: 88217 | HS3: 247551 | HT3: 180152 | HU3: 556025 | HV3: 91462 | HW3: 2291117 | HX3: 87406 | HY3: 75567 | HZ3: 101255 | IA3: 1033925 | IB3: 2692644 | IC3: 63130 | ID3: 109431 | IE3: 229432 | IF3: 237229 | IG3: 127432 | IH3: 139931 | II3: 179638 | IJ3: 123327 | IK3: 103679 | IL3: 98556 | IM3: 95719 | IN3: 135479 | IO3: 293496 | IP3: 75020 | IQ3: 259290 | IR3: 1458295 | IS3: 351364 | IT3: 425185 | IU3: 9075527 | IV3: 113353 | IW3: 685429 | IX3: 207385 | IY3: 276476 | IZ3: 79219 | JA3: 546171 | JB3: 942869 | JC3: 215637 | JD3: 737508 | JE3: 1342954 | JF3: 148625 | JG3: 97587 | JH3: 435268 | JI3: 87104 | JJ3: 464606 | JK3: 160250 | JL3: 83544 | JM3: 366424 | JN3: 293949 | JO3: 3770229 | JP3: 2962716 | JQ3: 81108 | JR3: 2032519 | JS3: 111145 | JT3: 74335 | JU3: 95220 | JV3: 497318 | JW3: 1789019 | JX3: 332138 | JY3: 197911 | JZ3: 1223023 | KA3: 584991 | KB3: 121602 | KC3: 167048 | KD3: 142655 | KE3: 878306 | KF3: 123954 | KG3: 301447 | KH3: 141949 | KI3: 360296 | KJ3: 749189 | KK3: 1655829 | KL3: 240895 | KM3: 186858 | KN3: 793224 | KO3: 226288 | KP3: 64174 | KQ3: 70982 | KR3: 1256183 | KS3: 133402 | KT3: 167566 | KU3: 166345 | KV3: 100680 | KW3: 2008568 | KX3: 301049 | KY3: 158316 | KZ3: 74969 | LA3: 908026 | LB3: 76422 | LC3: 1250733 | LD3: 1592607 | LE3: 97040 | LF3: 1751155 | LG3: 592755 | LH3: 373735 | LI3: 195251 | LJ3: 159010 | LK3: 88445 | LL3: 213134 | LM3: 299837 | LN3: 227158 | LO3: 448374 | LP3: 2388793 | LQ3: 125917 | LR3: 72316 | LS3: 98331 | LT3: 109325 | LU3: 197003 | LV3: 77951 | LW3: 100468 | LX3: 247866 | LY3: 201130 | LZ3: 237610 | MA3: 249166 | MB3: 494957 | MC3: 163816 | MD3: 295267 | ME3: 428476 | MF3: 111360 | MG3: 133022 | MH3: 107174 | MI3: 254518 | MJ3: 46981 | MK3: 522011 | ML3: 215876 | MM3: 2074981 | MN3: 148523 | MO3: 95894 | MP3: 444685 | MQ3: 181918 | MR3: 142380 | MS3: 178342 | MT3: 627672 | MU3: 660011 | MV3: 160260 | MW3: 90103 | MX3: 160640 | MY3: 184255 | MZ3: 238666 | NA3: 81107 | NB3: 176960 | NC3: 56996 | ND3: 71835 | NE3: 966859 | NF3: 177316 | NG3: 180706 | NH3: 45047 | NI3: 104271 | NJ3: 2745137 | NK3: 291451 | NL3: 139257 | NM3: 94857 | NN3: 120384 | NO3: 104236 | NP3: 80659 | NQ3: 124831 | NR3: 473047 | NS3: 109493 | NT3: 122135 | NU3: 100481 | NV3: 354069 | NW3: 114929 | NX3: 460011 | NY3: 630934 | NZ3: 120276 | OA3: 375793 | OB3: 340907 | OC3: 90171 | OD3: 79485
A4: Black or African American alone | B4: 14067 | C4: 7714 | D4: 83043 | E4: 77114 | F4: 664 | G4: 71274 | H4: 25452 | I4: 42596 | J4: 52808 | K4: 2423 | L4: 17637 | M4: 3103 | N4: 4236 | O4: 15793 | P4: 42421 | Q4: 25450 | R4: 3647 | S4: 4049 | T4: 16949 | U4: 40219 | V4: 2108390 | W4: 40639 | X4: 54555 | Y4: 218791 | Z4: 175014 | AA4: 46662 | AB4: 822419 | AC4: 1803 | AD4: 6467 | AE4: 297910 | AF4: 13067 | AG4: 1234 | AH4: 93619 | AI4: 6656 | AJ4: 2213 | AK4: 1162 | AL4: 1181 | AM4: 11716 | AN4: 336167 | AO4: 2577 | AP4: 7882 | AQ4: 14627 | AR4: 5168 | AS4: 8862 | AT4: 357326 | AU4: 2770 | AV4: 13120 | AW4: 555 | AX4: 6408 | AY4: 103039 | AZ4: 2563 | BA4: 24510 | BB4: 132532 | BC4: 34953 | BD4: 4086 | BE4: 26814 | BF4: 64421 | BG4: 7814 | BH4: 1037 | BI4: 426 | BJ4: 14356 | BK4: 4870 | BL4: 28390 | BM4: 8747 | BN4: 195114 | BO4: 608414 | BP4: 24184 | BQ4: 68293 | BR4: 2277 | BS4: 1497789 | BT4: 3823 | BU4: 260890 | BV4: 60030 | BW4: 402161 | BX4: 5054 | BY4: 644 | BZ4: 30391 | CA4: 43241 | CB4: 19783 | CC4: 283973 | CD4: 138406 | CE4: 1545 | CF4: 349540 | CG4: 14996 | CH4: 1260 | CI4: 23507 | CJ4: 1302457 | CK4: 3883 | CL4: 19909 | CM4: 29515 | CN4: 121892 | CO4: 19351 | CP4: 16552 | CQ4: 72886 | CR4: 169853 | CS4: 41787 | CT4: 934711 | CU4: 36188 | CV4: 50730 | CW4: 2932 | CX4: 4465 | CY4: 140671 | CZ4: 103 | DA4: 2443 | DB4: 3975 | DC4: 12853 | DD4: 10034 | DE4: 5355 | DF4: 29538 | DG4: 1486 | DH4: 19375 | DI4: 4587 | DJ4: 16765 | DK4: 3916 | DL4: 16713 | DM4: 759 | DN4: 145168 | DO4: 13298 | DP4: 2060 | DQ4: 77933 | DR4: 84543 | DS4: 17765 | DT4: 1770 | DU4: 3962 | DV4: 8234 | DW4: 41924 | DX4: 48698 | DY4: 15231 | DZ4: 59221 | EA4: 14600 | EB4: 1952 | EC4: 2290 | ED4: 35324 | EE4: 3424 | EF4: 2496 | EG4: 995 | EH4: 74260 | EI4: 367 | EJ4: 1108 | EK4: 5193 | EL4: 6886 | EM4: 210510 | EN4: 61982 | EO4: 138100 | EP4: 6094 | EQ4: 83819 | ER4: 27644 | ES4: 40109 | ET4: 9453 | EU4: 62152 | EV4: 5998 | EW4: 130373 | EX4: 43871 | EY4: 438 | EZ4: 23452 | FA4: 41317 | FB4: 32916 | FC4: 2912 | FD4: 7606 | FE4: 31994 | FF4: 1288022 | FG4: 7311 | FH4: 111240 | FI4: 611 | FJ4: 322753 | FK4: 12295 | FL4: 4358 | FM4: 11836 | FN4: 291844 | FO4: 46591 | FP4: 344158 | FQ4: 25041 | FR4: 7727 | FS4: 9626 | FT4: 6033 | FU4: 4024 | FV4: 20188 | FW4: 2934 | FX4: 1388 | FY4: 28850 | FZ4: 15265 | GA4: 260736 | GB4: 5451 | GC4: 10300 | GD4: 101629 | GE4: 6253 | GF4: 11342 | GG4: 76403 | GH4: 49740 | GI4: 6176 | GJ4: 1959 | GK4: 94140 | GL4: 11959 | GM4: 53283 | GN4: 2377 | GO4: 115178 | GP4: 22388 | GQ4: 41429 | GR4: 1282 | GS4: 3907 | GT4: 280163 | GU4: 5260 | GV4: 18098 | GW4: 3168 | GX4: 293 | GY4: 6347 | GZ4: 55057 | HA4: 28349 | HB4: 9744 | HC4: 12390 | HD4: 179065 | HE4: 1334 | HF4: 46843 | HG4: 759 | HH4: 803112 | HI4: 185149 | HJ4: 25222 | HK4: 42552 | HL4: 105204 | HM4: 31416 | HN4: 10520 | HO4: 10385 | HP4: 4946 | HQ4: 8947 | HR4: 6539 | HS4: 6207 | HT4: 1419 | HU4: 623600 | HV4: 8082 | HW4: 1239562 | HX4: 11828 | HY4: 1022 | HZ4: 12748 | IA4: 249446 | IB4: 340481 | IC4: 3316 | ID4: 527 | IE4: 147984 | IF4: 15171 | IG4: 83060 | IH4: 3386 | II4: 172240 | IJ4: 5744 | IK4: 2753 | IL4: 1020 | IM4: 5975 | IN4: 21276 | IO4: 45064 | IP4: 2684 | IQ4: 26111 | IR4: 290986 | IS4: 79061 | IT4: 372183 | IU4: 3136400 | IV4: 20232 | IW4: 51570 | IX4: 14996 | IY4: 48446 | IZ4: 7352 | JA4: 7494 | JB4: 141844 | JC4: 9947 | JD4: 72619 | JE4: 440762 | JF4: 4785 | JG4: 4333 | JH4: 15401 | JI4: 7941 | JJ4: 63258 | JK4: 21972 | JL4: 978 | JM4: 79230 | JN4: 33591 | JO4: 1259533 | JP4: 284480 | JQ4: 9406 | JR4: 191347 | JS4: 3426 | JT4: 832 | JU4: 11244 | JV4: 13305 | JW4: 75015 | JX4: 85735 | JY4: 1273 | JZ4: 87124 | KA4: 5448 | KB4: 3522 | KC4: 10406 | KD4: 20827 | KE4: 278425 | KF4: 1965 | KG4: 19969 | KH4: 1651 | KI4: 12764 | KJ4: 376305 | KK4: 329799 | KL4: 40623 | KM4: 12855 | KN4: 114672 | KO4: 35721 | KP4: 65769 | KQ4: 13764 | KR4: 163658 | KS4: 35003 | KT4: 16945 | KU4: 853 | KV4: 6057 | KW4: 482826 | KX4: 5027 | KY4: 9414 | KZ4: 37620 | LA4: 22737 | LB4: 4704 | LC4: 187136 | LD4: 152969 | LE4: 6669 | LF4: 317772 | LG4: 44556 | LH4: 150521 | LI4: 3267 | LJ4: 2200 | LK4: 1540 | LL4: 7570 | LM4: 7630 | LN4: 133561 | LO4: 23421 | LP4: 250061 | LQ4: 13043 | LR4: 10359 | LS4: 2547 | LT4: 7432 | LU4: 152548 | LV4: 4104 | LW4: 7267 | LX4: 15027 | LY4: 33305 | LZ4: 36135 | MA4: 74922 | MB4: 11605 | MC4: 24830 | MD4: 40334 | ME4: 10543 | MF4: 10868 | MG4: 5257 | MH4: 8866 | MI4: 54932 | MJ4: 48127 | MK4: 53399 | ML4: 122476 | MM4: 385576 | MN4: 6974 | MO4: 35921 | MP4: 85669 | MQ4: 12450 | MR4: 1223 | MS4: 71211 | MT4: 38431 | MU4: 77403 | MV4: 95236 | MW4: 858 | MX4: 39393 | MY4: 23615 | MZ4: 14844 | NA4: 52864 | NB4: 57384 | NC4: 5812 | ND4: 26429 | NE4: 528688 | NF4: 7451 | NG4: 40550 | NH4: 1032 | NI4: 66890 | NJ4: 1552724 | NK4: 52127 | NL4: 12495 | NM4: 5521 | NN4: 800 | NO4: 4116 | NP4: 618 | NQ4: 3523 | NR4: 43306 | NS4: 13979 | NT4: 9305 | NU4: 4828 | NV4: 46432 | NW4: 6677 | NX4: 118756 | NY4: 45228 | NZ4: 1804 | OA4: 29054 | OB4: 48039 | OC4: 5159 | OD4: 3578
A5: American Indian and Alaska Native alone | B5: 703 | C5: 297 | D5: 1046 | E5: 231 | F5: 887 | G5: 1734 | H5: 56590 | I5: 910 | J5: 2976 | K5: 37 | L5: 1893 | M5: 476 | N5: 333 | O5: 27391 | P5: 1007 | Q5: 450 | R5: 2355 | S5: 536 | T5: 2104 | U5: 968 | V5: 25706 | W5: 2315 | X5: 748 | Y5: 987 | Z5: 17373 | AA5: 12240 | AB5: 10063 | AC5: 1330 | AD5: 1025 | AE5: 1922 | AF5: 474 | AG5: 230 | AH5: 1861 | AI5: 22 | AJ5: 4102 | AK5: 5201 | AL5: 6743 | AM5: 321 | AN5: 3412 | AO5: 4876 | AP5: 235 | AQ5: 541 | AR5: 228 | AS5: 6764 | AT5: 10510 | AU5: 1121 | AV5: 768 | AW5: 755 | AX5: 2796 | AY5: 4201 | AZ5: 2250 | BA5: 288 | BB5: 5051 | BC5: 972 | BD5: 435 | BE5: 423 | BF5: 5333 | BG5: 258 | BH5: 1267 | BI5: 419 | BJ5: 550 | BK5: 590 | BL5: 399 | BM5: 131 | BN5: 3543 | BO5: 11344 | BP5: 521 | BQ5: 1581 | BR5: 1027 | BS5: 73798 | BT5: 2789 | BU5: 3851 | BV5: 903 | BW5: 3375 | BX5: 215 | BY5: 1493 | BZ5: 1729 | CA5: 7482 | CB5: 356 | CC5: 2103 | CD5: 774 | CE5: 70 | CF5: 4310 | CG5: 2867 | CH5: 1011 | CI5: 1780 | CJ5: 55368 | CK5: 2453 | CL5: 910 | CM5: 906 | CN5: 801 | CO5: 2244 | CP5: 99 | CQ5: 1581 | CR5: 29467 | CS5: 1965 | CT5: 10723 | CU5: 410 | CV5: 927 | CW5: 39 | CX5: 4970 | CY5: 3464 | CZ5: 1005 | DA5: 659 | DB5: 2795 | DC5: 245 | DD5: 1349 | DE5: 261 | DF5: 8259 | DG5: 1213 | DH5: 369 | DI5: 4718 | DJ5: 647 | DK5: 5931 | DL5: 2432 | DM5: 47935 | DN5: 7844 | DO5: 6695 | DP5: 36562 | DQ5: 1146 | DR5: 398 | DS5: 437 | DT5: 444 | DU5: 1914 | DV5: 9064 | DW5: 2265 | DX5: 18365 | DY5: 526 | DZ5: 614 | EA5: 910 | EB5: 347 | EC5: 59 | ED5: 112 | EE5: 1579 | EF5: 623 | EG5: 1327 | EH5: 5551 | EI5: 477 | EJ5: 2852 | EK5: 3797 | EL5: 5714 | EM5: 2569 | EN5: 663 | EO5: 5527 | EP5: 59 | EQ5: 1550 | ER5: 482 | ES5: 114 | ET5: 3316 | EU5: 971 | EV5: 598 | EW5: 2700 | EX5: 279 | EY5: 1243 | EZ5: 2046 | FA5: 835 | FB5: 358 | FC5: 439 | FD5: 421 | FE5: 8015 | FF5: 63024 | FG5: 194 | FH5: 3296 | FI5: 1149 | FJ5: 7986 | FK5: 275 | FL5: 266 | FM5: 495 | FN5: 1698 | FO5: 735 | FP5: 3249 | FQ5: 1465 | FR5: 564 | FS5: 440 | FT5: 382 | FU5: 62 | FV5: 355 | FW5: 2397 | FX5: 561 | FY5: 954 | FZ5: 487 | GA5: 10485 | GB5: 3579 | GC5: 663 | GD5: 4240 | GE5: 261 | GF5: 751 | GG5: 6050 | GH5: 1649 | GI5: 46 | GJ5: 490 | GK5: 487 | GL5: 383 | GM5: 777 | GN5: 3771 | GO5: 3459 | GP5: 1162 | GQ5: 2073 | GR5: 909 | GS5: 2749 | GT5: 27274 | GU5: 1549 | GV5: 6252 | GW5: 93 | GX5: 2143 | GY5: 189 | GZ5: 1337 | HA5: 355 | HB5: 286 | HC5: 2265 | HD5: 1988 | HE5: 375 | HF5: 1012 | HG5: 1452 | HH5: 168662 | HI5: 2616 | HJ5: 2204 | HK5: 505 | HL5: 512 | HM5: 1684 | HN5: 598 | HO5: 1106 | HP5: 337 | HQ5: 99 | HR5: 361 | HS5: 3751 | HT5: 1369 | HU5: 4334 | HV5: 4316 | HW5: 15608 | HX5: 234 | HY5: 159 | HZ5: 988 | IA5: 7522 | IB5: 19461 | IC5: 1314 | ID5: 2543 | IE5: 1747 | IF5: 7720 | IG5: 367 | IH5: 165 | II5: 821 | IJ5: 204 | IK5: 309 | IL5: 1862 | IM5: 172 | IN5: 920 | IO5: 1034 | IP5: 1546 | IQ5: 6207 | IR5: 6760 | IS5: 1652 | IT5: 7290 | IU5: 124046 | IV5: 409 | IW5: 4047 | IX5: 1791 | IY5: 1143 | IZ5: 942 | JA5: 3277 | JB5: 50351 | JC5: 3375 | JD5: 5663 | JE5: 8082 | JF5: 657 | JG5: 520 | JH5: 14035 | JI5: 154 | JJ5: 1401 | JK5: 1007 | JL5: 85 | JM5: 1755 | JN5: 763 | JO5: 16103 | JP5: 111006 | JQ5: 474 | JR5: 2238 | JS5: 565 | JT5: 2300 | JU5: 186 | JV5: 925 | JW5: 21715 | JX5: 2617 | JY5: 3727 | JZ5: 6753 | KA5: 4157 | KB5: 2968 | KC5: 184 | KD5: 920 | KE5: 5453 | KF5: 8425 | KG5: 2854 | KH5: 3088 | KI5: 7826 | KJ5: 4189 | KK5: 64727 | KL5: 836 | KM5: 417 | KN5: 1708 | KO5: 2043 | KP5: 808 | KQ5: 784 | KR5: 22016 | KS5: 533 | KT5: 303 | KU5: 1524 | KV5: 413 | KW5: 4459 | KX5: 5757 | KY5: 3800 | KZ5: 180 | LA5: 13146 | LB5: 589 | LC5: 28260 | LD5: 35126 | LE5: 115 | LF5: 44205 | LG5: 17836 | LH5: 5118 | LI5: 2632 | LJ5: 3172 | LK5: 5097 | LL5: 9181 | LM5: 6555 | LN5: 1130 | LO5: 580 | LP5: 33454 | LQ5: 669 | LR5: 751 | LS5: 229 | LT5: 1050 | LU5: 1266 | LV5: 1370 | LW5: 2788 | LX5: 4762 | LY5: 2079 | LZ5: 1349 | MA5: 741 | MB5: 7413 | MC5: 135 | MD5: 1292 | ME5: 1394 | MF5: 156 | MG5: 475 | MH5: 176 | MI5: 11882 | MJ5: 568 | MK5: 2632 | ML5: 1323 | MM5: 11500 | MN5: 293 | MO5: 800 | MP5: 1254 | MQ5: 1960 | MR5: 1424 | MS5: 5214 | MT5: 30810 | MU5: 73552 | MV5: 947 | MW5: 774 | MX5: 991 | MY5: 2034 | MZ5: 481 | NA5: 399 | NB5: 4002 | NC5: 254 | ND5: 2784 | NE5: 5399 | NF5: 7616 | NG5: 1207 | NH5: 756 | NI5: 545 | NJ5: 32750 | NK5: 943 | NL5: 452 | NM5: 432 | NN5: 251 | NO5: 51 | NP5: 1388 | NQ5: 107 | NR5: 5596 | NS5: 1093 | NT5: 254 | NU5: 235 | NV5: 1103 | NW5: 672 | NX5: 2515 | NY5: 2170 | NZ5: 8138 | OA5: 644 | OB5: 589 | OC5: 3409 | OD5: 2965
A6: Asian alone | B6: 3502 | C6: 89 | D6: 26948 | E6: 1610 | F6: 1372 | G6: 45067 | H6: 23257 | I6: 1618 | J6: 27064 | K6: 849 | L6: 8237 | M6: 6694 | N6: 8612 | O6: 30682 | P6: 34148 | Q6: 986 | R6: 8605 | S6: 568 | T6: 4640 | U6: 8254 | V6: 413563 | W6: 22368 | X6: 7917 | Y6: 13283 | Z6: 180792 | AA6: 48277 | AB6: 169762 | AC6: 1696 | AD6: 3422 | AE6: 17980 | AF6: 3495 | AG6: 525 | AH6: 10900 | AI6: 653 | AJ6: 10078 | AK6: 2435 | AL6: 1335 | AM6: 10543 | AN6: 18685 | AO6: 1037 | AP6: 7126 | AQ6: 9007 | AR6: 9767 | AS6: 16733 | AT6: 435389 | AU6: 15523 | AV6: 7312 | AW6: 1560 | AX6: 13655 | AY6: 51502 | AZ6: 3463 | BA6: 1246 | BB6: 49267 | BC6: 3241 | BD6: 7802 | BE6: 3370 | BF6: 13934 | BG6: 1387 | BH6: 1468 | BI6: 455 | BJ6: 5692 | BK6: 1632 | BL6: 24059 | BM6: 2082 | BN6: 17417 | BO6: 122074 | BP6: 10734 | BQ6: 9612 | BR6: 1148 | BS6: 689329 | BT6: 11629 | BU6: 67363 | BV6: 7140 | BW6: 51950 | BX6: 1350 | BY6: 1264 | BZ6: 14776 | CA6: 21625 | CB6: 9153 | CC6: 19985 | CD6: 6603 | CE6: 6174 | CF6: 109932 | CG6: 9256 | CH6: 6413 | CI6: 8362 | CJ6: 661199 | CK6: 1640 | CL6: 2552 | CM6: 9246 | CN6: 19308 | CO6: 895 | CP6: 1564 | CQ6: 14610 | CR6: 132482 | CS6: 31130 | CT6: 222693 | CU6: 1352 | CV6: 4694 | CW6: 1354 | CX6: 2603 | CY6: 31572 | CZ6: 270 | DA6: 5308 | DB6: 2764 | DC6: 2474 | DD6: 2043 | DE6: 1271 | DF6: 11128 | DG6: 798 | DH6: 5909 | DI6: 10121 | DJ6: 3704 | DK6: 2718 | DL6: 7278 | DM6: 962 | DN6: 9865 | DO6: 20303 | DP6: 2684 | DQ6: 4378 | DR6: 2594 | DS6: 875 | DT6: 1976 | DU6: 8205 | DV6: 6707 | DW6: 21016 | DX6: 117910 | DY6: 680 | DZ6: 17677 | EA6: 4710 | EB6: 1000 | EC6: 1058 | ED6: 1430 | EE6: 2267 | EF6: 728 | EG6: 1424 | EH6: 30331 | EI6: 703 | EJ6: 924 | EK6: 5766 | EL6: 9493 | EM6: 31828 | EN6: 3545 | EO6: 18665 | EP6: 0 | EQ6: 9006 | ER6: 3897 | ES6: 1083 | ET6: 5792 | EU6: 34636 | EV6: 2780 | EW6: 65064 | EX6: 1610 | EY6: 424 | EZ6: 10859 | FA6: 2600 | FB6: 1309 | FC6: 2204 | FD6: 671 | FE6: 1729 | FF6: 620556 | FG6: 2538 | FH6: 12327 | FI6: 1223 | FJ6: 84924 | FK6: 8936 | FL6: 10646 | FM6: 1239 | FN6: 7613 | FO6: 1274 | FP6: 70573 | FQ6: 3934 | FR6: 1779 | FS6: 1280 | FT6: 2223 | FU6: 754 | FV6: 1445 | FW6: 2714 | FX6: 46350 | FY6: 7470 | FZ6: 1067 | GA6: 66378 | GB6: 8488 | GC6: 3108 | GD6: 13699 | GE6: 1911 | GF6: 3913 | GG6: 22220 | GH6: 14677 | GI6: 1198 | GJ6: 5654 | GK6: 6415 | GL6: 15311 | GM6: 3152 | GN6: 2554 | GO6: 14302 | GP6: 13540 | GQ6: 21449 | GR6: 1339 | GS6: 2728 | GT6: 250287 | GU6: 5207 | GV6: 3356 | GW6: 2331 | GX6: 624 | GY6: 1359 | GZ6: 16164 | HA6: 4899 | HB6: 942 | HC6: 13430 | HD6: 12375 | HE6: 2469 | HF6: 2439 | HG6: 1351 | HH6: 2195202 | HI6: 30376 | HJ6: 7830 | HK6: 3736 | HL6: 4101 | HM6: 36151 | HN6: 18375 | HO6: 4217 | HP6: 2187 | HQ6: 957 | HR6: 393 | HS6: 9202 | HT6: 2411 | HU6: 30732 | HV6: 20971 | HW6: 161049 | HX6: 715 | HY6: 1804 | HZ6: 4202 | IA6: 65197 | IB6: 258764 | IC6: 1173 | ID6: 1934 | IE6: 8896 | IF6: 33935 | IG6: 1944 | IH6: 623 | II6: 8887 | IJ6: 3863 | IK6: 979 | IL6: 2739 | IM6: 1956 | IN6: 1147 | IO6: 5250 | IP6: 11077 | IQ6: 6132 | IR6: 61230 | IS6: 26087 | IT6: 31204 | IU6: 2375134 | IV6: 2761 | IW6: 18768 | IX6: 10721 | IY6: 7062 | IZ6: 2015 | JA6: 11508 | JB6: 47948 | JC6: 18347 | JD6: 32698 | JE6: 126528 | JF6: 5561 | JG6: 2201 | JH6: 60589 | JI6: 668 | JJ6: 15575 | JK6: 3998 | JL6: 376 | JM6: 13426 | JN6: 9869 | JO6: 408447 | JP6: 216580 | JQ6: 1322 | JR6: 64646 | JS6: 2461 | JT6: 1412 | JU6: 202 | JV6: 9359 | JW6: 180265 | JX6: 9293 | JY6: 2819 | JZ6: 53095 | KA6: 11125 | KB6: 1522 | KC6: 2737 | KD6: 2370 | KE6: 103546 | KF6: 1651 | KG6: 5859 | KH6: 6375 | KI6: 29527 | KJ6: 56107 | KK6: 359578 | KL6: 7839 | KM6: 10904 | KN6: 32624 | KO6: 8791 | KP6: 1162 | KQ6: 1463 | KR6: 367257 | KS6: 2225 | KT6: 3581 | KU6: 2314 | KV6: 1146 | KW6: 82044 | KX6: 8762 | KY6: 25129 | KZ6: 2759 | LA6: 51842 | LB6: 1669 | LC6: 77465 | LD6: 406933 | LE6: 814 | LF6: 1303966 | LG6: 772957 | LH6: 4241 | LI6: 10471 | LJ6: 12961 | LK6: 2271 | LL6: 23694 | LM6: 21865 | LN6: 11335 | LO6: 10485 | LP6: 651965 | LQ6: 2600 | LR6: 1598 | LS6: 6812 | LT6: 2168 | LU6: 5088 | LV6: 2423 | LW6: 3349 | LX6: 4488 | LY6: 3711 | LZ6: 7849 | MA6: 8428 | MB6: 12998 | MC6: 4495 | MD6: 12007 | ME6: 6973 | MF6: 814 | MG6: 9133 | MH6: 1142 | MI6: 148289 | MJ6: 1553 | MK6: 21197 | ML6: 11018 | MM6: 129341 | MN6: 2417 | MO6: 1656 | MP6: 10435 | MQ6: 2736 | MR6: 1013 | MS6: 48018 | MT6: 32648 | MU6: 30367 | MV6: 3992 | MW6: 1110 | MX6: 4265 | MY6: 422143 | MZ6: 10231 | NA6: 2943 | NB6: 73617 | NC6: 1161 | ND6: 2290 | NE6: 72969 | NF6: 17582 | NG6: 5637 | NH6: 1151 | NI6: 5214 | NJ6: 686556 | NK6: 17489 | NL6: 3850 | NM6: 2189 | NN6: 7850 | NO6: 665 | NP6: 1028 | NQ6: 686 | NR6: 24243 | NS6: 3110 | NT6: 1490 | NU6: 1077 | NV6: 4807 | NW6: 2530 | NX6: 12351 | NY6: 46238 | NZ6: 3182 | OA6: 6866 | OB6: 2960 | OC6: 24285 | OD6: 2233
A7: Native Hawaiian and Other Pacific Islander alone | B7: 124 | C7: 29 | D7: 75 | E7: 50 | F7: 217 | G7: 412 | H7: 890 | I7: 6 | J7: 232 | K7: 0 | L7: 481 | M7: 110 | N7: 45 | O7: 9517 | P7: 110 | Q7: 151 | R7: 47 | S7: 0 | T7: 336 | U7: 266 | V7: 3701 | W7: 29 | X7: 57 | Y7: 513 | Z7: 2090 | AA7: 1463 | AB7: 1209 | AC7: 82 | AD7: 0 | AE7: 227 | AF7: 65 | AG7: 60 | AH7: 167 | AI7: 25 | AJ7: 597 | AK7: 380 | AL7: 97 | AM7: 82 | AN7: 1383 | AO7: 570 | AP7: 192 | AQ7: 71 | AR7: 25 | AS7: 1759 | AT7: 1822 | AU7: 204 | AV7: 880 | AW7: 13 | AX7: 2683 | AY7: 442 | AZ7: 225 | BA7: 3 | BB7: 217 | BC7: 77 | BD7: 41 | BE7: 113 | BF7: 355 | BG7: 88 | BH7: 52 | BI7: 18 | BJ7: 53 | BK7: 19 | BL7: 43 | BM7: 195 | BN7: 688 | BO7: 796 | BP7: 65 | BQ7: 139 | BR7: 130 | BS7: 4007 | BT7: 659 | BU7: 1757 | BV7: 972 | BW7: 611 | BX7: 24 | BY7: 84 | BZ7: 235 | CA7: 2069 | CB7: 159 | CC7: 386 | CD7: 401 | CE7: 9 | CF7: 773 | CG7: 404 | CH7: 196 | CI7: 571 | CJ7: 7760 | CK7: 165 | CL7: 139 | CM7: 326 | CN7: 183 | CO7: 252 | CP7: 43 | CQ7: 280 | CR7: 4929 | CS7: 378 | CT7: 1579 | CU7: 50 | CV7: 105 | CW7: 802 | CX7: 25 | CY7: 275 | CZ7: 44 | DA7: 142 | DB7: 195 | DC7: 128 | DD7: 58 | DE7: 20 | DF7: 1460 | DG7: 2398 | DH7: 25 | DI7: 815 | DJ7: 569 | DK7: 653 | DL7: 48 | DM7: 37 | DN7: 1203 | DO7: 9699 | DP7: 241 | DQ7: 57 | DR7: 37 | DS7: 21 | DT7: 0 | DU7: 371 | DV7: 102 | DW7: 280 | DX7: 1989 | DY7: 43 | DZ7: 74 | EA7: 13 | EB7: 21 | EC7: 33 | ED7: 110 | EE7: 30 | EF7: 26 | EG7: 76 | EH7: 394 | EI7: 113 | EJ7: 5 | EK7: 389 | EL7: 87 | EM7: 309 | EN7: 37 | EO7: 828 | EP7: 0 | EQ7: 188 | ER7: 169 | ES7: 48 | ET7: 440 | EU7: 68 | EV7: 78 | EW7: 889 | EX7: 177 | EY7: 0 | EZ7: 173 | FA7: 0 | FB7: 454 | FC7: 69 | FD7: 122 | FE7: 28 | FF7: 5774 | FG7: 68 | FH7: 391 | FI7: 196 | FJ7: 584 | FK7: 35 | FL7: 54 | FM7: 54 | FN7: 328 | FO7: 87 | FP7: 1144 | FQ7: 328 | FR7: 9 | FS7: 25 | FT7: 36 | FU7: 5 | FV7: 39 | FW7: 1299 | FX7: 16601 | FY7: 41 | FZ7: 0 | GA7: 3639 | GB7: 666 | GC7: 12 | GD7: 3143 | GE7: 40 | GF7: 40 | GG7: 162 | GH7: 589 | GI7: 18 | GJ7: 26 | GK7: 452 | GL7: 22 | GM7: 126 | GN7: 411 | GO7: 330 | GP7: 454 | GQ7: 79 | GR7: 3 | GS7: 308 | GT7: 19077 | GU7: 16 | GV7: 730 | GW7: 57 | GX7: 109 | GY7: 16 | GZ7: 67 | HA7: 41 | HB7: 10 | HC7: 259 | HD7: 224 | HE7: 714 | HF7: 134 | HG7: 461 | HH7: 32089 | HI7: 490 | HJ7: 274 | HK7: 164 | HL7: 73 | HM7: 347 | HN7: 38 | HO7: 507 | HP7: 0 | HQ7: 145 | HR7: 0 | HS7: 301 | HT7: 149 | HU7: 1306 | HV7: 975 | HW7: 2511 | HX7: 46 | HY7: 13 | HZ7: 45 | IA7: 241 | IB7: 999 | IC7: 34 | ID7: 159 | IE7: 119 | IF7: 3743 | IG7: 45 | IH7: 25 | II7: 48 | IJ7: 1 | IK7: 377 | IL7: 450 | IM7: 23 | IN7: 89 | IO7: 330 | IP7: 490 | IQ7: 194 | IR7: 1794 | IS7: 234 | IT7: 231 | IU7: 9038 | IV7: 33 | IW7: 617 | IX7: 31 | IY7: 318 | IZ7: 346 | JA7: 3914 | JB7: 1279 | JC7: 3085 | JD7: 654 | JE7: 2354 | JF7: 66 | JG7: 39 | JH7: 1637 | JI7: 81 | JJ7: 418 | JK7: 174 | JL7: 89 | JM7: 797 | JN7: 147 | JO7: 2098 | JP7: 10835 | JQ7: 99 | JR7: 468 | JS7: 43 | JT7: 233 | JU7: 0 | JV7: 172 | JW7: 14040 | JX7: 180 | JY7: 298 | JZ7: 1005 | KA7: 5224 | KB7: 114 | KC7: 106 | KD7: 161 | KE7: 482 | KF7: 34 | KG7: 95 | KH7: 572 | KI7: 3842 | KJ7: 952 | KK7: 15771 | KL7: 205 | KM7: 42 | KN7: 431 | KO7: 118 | KP7: 57 | KQ7: 111 | KR7: 19967 | KS7: 61 | KT7: 94 | KU7: 1275 | KV7: 361 | KW7: 794 | KX7: 4336 | KY7: 1858 | KZ7: 20 | LA7: 19414 | LB7: 74 | LC7: 3445 | LD7: 13548 | LE7: 21 | LF7: 29670 | LG7: 7667 | LH7: 127 | LI7: 413 | LJ7: 442 | LK7: 155 | LL7: 397 | LM7: 1616 | LN7: 511 | LO7: 382 | LP7: 37259 | LQ7: 45 | LR7: 46 | LS7: 169 | LT7: 175 | LU7: 205 | LV7: 260 | LW7: 793 | LX7: 92 | LY7: 952 | LZ7: 246 | MA7: 164 | MB7: 4145 | MC7: 71 | MD7: 75 | ME7: 694 | MF7: 119 | MG7: 14 | MH7: 45 | MI7: 4735 | MJ7: 148 | MK7: 254 | ML7: 134 | MM7: 2173 | MN7: 60 | MO7: 168 | MP7: 346 | MQ7: 205 | MR7: 27 | MS7: 68 | MT7: 1606 | MU7: 1408 | MV7: 17 | MW7: 295 | MX7: 98 | MY7: 96063 | MZ7: 238 | NA7: 97 | NB7: 4428 | NC7: 67 | ND7: 25 | NE7: 1868 | NF7: 672 | NG7: 129 | NH7: 149 | NI7: 298 | NJ7: 3028 | NK7: 152 | NL7: 972 | NM7: 301 | NN7: 30 | NO7: 88 | NP7: 261 | NQ7: 32 | NR7: 517 | NS7: 196 | NT7: 30 | NU7: 22 | NV7: 66 | NW7: 42 | NX7: 327 | NY7: 261 | NZ7: 942 | OA7: 119 | OB7: 115 | OC7: 838 | OD7: 97
A8: Some Other Race alone | B8: 9782 | C8: 35602 | D8: 6881 | E8: 2424 | F8: 5891 | G8: 24736 | H8: 109163 | I8: 1687 | J8: 71211 | K8: 521 | L8: 14069 | M8: 1988 | N8: 3461 | O8: 11073 | P8: 6917 | Q8: 2389 | R8: 4337 | S8: 41041 | T8: 12982 | U8: 6760 | V8: 339928 | W8: 30011 | X8: 3683 | Y8: 15218 | Z8: 187274 | AA8: 177000 | AB8: 113986 | AC8: 1328 | AD8: 5531 | AE8: 27592 | AF8: 2106 | AG8: 1070 | AH8: 23433 | AI8: 648 | AJ8: 10418 | AK8: 8016 | AL8: 3234 | AM8: 4269 | AN8: 31144 | AO8: 1884 | AP8: 2802 | AQ8: 3616 | AR8: 1719 | AS8: 44317 | AT8: 285296 | AU8: 10773 | AV8: 4272 | AW8: 2563 | AX8: 7823 | AY8: 102573 | AZ8: 42760 | BA8: 3267 | BB8: 27377 | BC8: 16847 | BD8: 1674 | BE8: 2249 | BF8: 37180 | BG8: 681 | BH8: 5706 | BI8: 1597 | BJ8: 3347 | BK8: 4711 | BL8: 4545 | BM8: 913 | BN8: 25971 | BO8: 167459 | BP8: 6278 | BQ8: 14130 | BR8: 4987 | BS8: 957856 | BT8: 13661 | BU8: 43402 | BV8: 7698 | BW8: 47731 | BX8: 3539 | BY8: 3191 | BZ8: 14397 | CA8: 37278 | CB8: 2729 | CC8: 24849 | CD8: 10486 | CE8: 4525 | CF8: 51620 | CG8: 28315 | CH8: 2624 | CI8: 11122 | CJ8: 694695 | CK8: 20578 | CL8: 5754 | CM8: 11122 | CN8: 11686 | CO8: 6372 | CP8: 1144 | CQ8: 51918 | CR8: 209039 | CS8: 21823 | CT8: 88040 | CU8: 2148 | CV8: 4325 | CW8: 876 | CX8: 1694 | CY8: 42123 | CZ8: 6003 | DA8: 1524 | DB8: 74702 | DC8: 1998 | DD8: 20312 | DE8: 865 | DF8: 158357 | DG8: 4167 | DH8: 3700 | DI8: 12959 | DJ8: 4308 | DK8: 2309 | DL8: 2998 | DM8: 10447 | DN8: 19442 | DO8: 26412 | DP8: 7711 | DQ8: 4096 | DR8: 3040 | DS8: 2448 | DT8: 1903 | DU8: 10013 | DV8: 15861 | DW8: 16106 | DX8: 280746 | DY8: 2780 | DZ8: 9766 | EA8: 19608 | EB8: 3376 | EC8: 1572 | ED8: 3212 | EE8: 1535 | EF8: 10586 | EG8: 5060 | EH8: 35207 | EI8: 2245 | EJ8: 1662 | EK8: 30229 | EL8: 11640 | EM8: 36340 | EN8: 9001 | EO8: 30927 | EP8: 21253 | EQ8: 11849 | ER8: 8241 | ES8: 1639 | ET8: 34794 | EU8: 18254 | EV8: 6386 | EW8: 68635 | EX8: 2262 | EY8: 777 | EZ8: 14048 | FA8: 13739 | FB8: 3526 | FC8: 2509 | FD8: 1937 | FE8: 4411 | FF8: 855276 | FG8: 1794 | FH8: 12307 | FI8: 7699 | FJ8: 79618 | FK8: 4391 | FL8: 3206 | FM8: 1683 | FN8: 10823 | FO8: 4320 | FP8: 58909 | FQ8: 7661 | FR8: 4782 | FS8: 1658 | FT8: 2577 | FU8: 708 | FV8: 2989 | FW8: 4913 | FX8: 3355 | FY8: 5310 | FZ8: 3688 | GA8: 84255 | GB8: 40014 | GC8: 6330 | GD8: 32532 | GE8: 2355 | GF8: 8688 | GG8: 60613 | GH8: 14147 | GI8: 647 | GJ8: 1819 | GK8: 5370 | GL8: 6684 | GM8: 4479 | GN8: 11743 | GO8: 107305 | GP8: 23131 | GQ8: 10798 | GR8: 28285 | GS8: 50241 | GT8: 320213 | GU8: 1858 | GV8: 4194 | GW8: 10852 | GX8: 738 | GY8: 872 | GZ8: 15929 | HA8: 3764 | HB8: 1506 | HC8: 8051 | HD8: 24117 | HE8: 6567 | HF8: 10228 | HG8: 3330 | HH8: 2885041 | HI8: 27299 | HJ8: 28219 | HK8: 4463 | HL8: 4893 | HM8: 13739 | HN8: 10802 | HO8: 3880 | HP8: 1817 | HQ8: 1376 | HR8: 88382 | HS8: 96007 | HT8: 9525 | HU8: 50957 | HV8: 119779 | HW8: 482453 | HX8: 3654 | HY8: 1018 | HZ8: 22120 | IA8: 57785 | IB8: 119854 | IC8: 1693 | ID8: 1836 | IE8: 5863 | IF8: 96386 | IG8: 3171 | IH8: 1635 | II8: 5497 | IJ8: 1344 | IK8: 4788 | IL8: 13802 | IM8: 1460 | IN8: 2000 | IO8: 9235 | IP8: 21959 | IQ8: 18230 | IR8: 76407 | IS8: 51448 | IT8: 44946 | IU8: 2622200 | IV8: 4512 | IW8: 32101 | IX8: 14635 | IY8: 15237 | IZ8: 32878 | JA8: 23882 | JB8: 65447 | JC8: 9925 | JD8: 41420 | JE8: 290024 | JF8: 2203 | JG8: 2351 | JH8: 101055 | JI8: 846 | JJ8: 20942 | JK8: 5183 | JL8: 290 | JM8: 11500 | JN8: 5637 | JO8: 321875 | JP8: 471527 | JQ8: 3568 | JR8: 23870 | JS8: 2810 | JT8: 3851 | JU8: 29774 | JV8: 5148 | JW8: 124670 | JX8: 24918 | JY8: 11279 | JZ8: 121371 | KA8: 35558 | KB8: 13105 | KC8: 4523 | KD8: 7284 | KE8: 83404 | KF8: 2005 | KG8: 37970 | KH8: 5106 | KI8: 56500 | KJ8: 56940 | KK8: 1219503 | KL8: 6180 | KM8: 4186 | KN8: 34946 | KO8: 24184 | KP8: 6484 | KQ8: 4524 | KR8: 236365 | KS8: 4197 | KT8: 4069 | KU8: 9257 | KV8: 3055 | KW8: 42035 | KX8: 43955 | KY8: 169297 | KZ8: 3411 | LA8: 115071 | LB8: 8707 | LC8: 276487 | LD8: 388026 | LE8: 2449 | LF8: 563325 | LG8: 221039 | LH8: 737756 | LI8: 21592 | LJ8: 45229 | LK8: 18695 | LL8: 67486 | LM8: 72017 | LN8: 13865 | LO8: 35352 | LP8: 193732 | LQ8: 6127 | LR8: 7401 | LS8: 2045 | LT8: 6060 | LU8: 6163 | LV8: 8105 | LW8: 9369 | LX8: 5651 | LY8: 4729 | LZ8: 9495 | MA8: 10532 | MB8: 12397 | MC8: 2097 | MD8: 40504 | ME8: 7903 | MF8: 2853 | MG8: 1492 | MH8: 2567 | MI8: 155528 | MJ8: 2022 | MK8: 11240 | ML8: 10013 | MM8: 179158 | MN8: 1970 | MO8: 3468 | MP8: 15098 | MQ8: 9327 | MR8: 1225 | MS8: 41518 | MT8: 108197 | MU8: 40331 | MV8: 3968 | MW8: 10687 | MX8: 11099 | MY8: 15977 | MZ8: 6956 | NA8: 3588 | NB8: 60046 | NC8: 7077 | ND8: 21499 | NE8: 46489 | NF8: 144129 | NG8: 12104 | NH8: 5279 | NI8: 4264 | NJ8: 560313 | NK8: 35736 | NL8: 3764 | NM8: 2751 | NN8: 2319 | NO8: 745 | NP8: 21271 | NQ8: 1125 | NR8: 29873 | NS8: 4995 | NT8: 4249 | NU8: 745 | NV8: 17338 | NW8: 9533 | NX8: 36017 | NY8: 41159 | NZ8: 53847 | OA8: 16461 | OB8: 6210 | OC8: 25185 | OD8: 34803
A9: Two or More Races: | B9: 29412 | C9: 76597 | D9: 43515 | E9: 6099 | F9: 11948 | G9: 67797 | H9: 247388 | I9: 8422 | J9: 103379 | K9: 5741 | L9: 47897 | M9: 6833 | N9: 12480 | O9: 56309 | P9: 31227 | Q9: 4958 | R9: 14594 | S9: 67991 | T9: 36206 | U9: 17269 | V9: 578579 | W9: 39974 | X9: 9646 | Y9: 42658 | Z9: 490068 | AA9: 227398 | AB9: 207481 | AC9: 6483 | AD9: 16406 | AE9: 55937 | AF9: 12347 | AG9: 6449 | AH9: 48870 | AI9: 4500 | AJ9: 23243 | AK9: 21868 | AL9: 13435 | AM9: 15164 | AN9: 55500 | AO9: 7622 | AP9: 8278 | AQ9: 9907 | AR9: 9490 | AS9: 84958 | AT9: 528442 | AU9: 42689 | AV9: 11079 | AW9: 8455 | AX9: 36090 | AY9: 128008 | AZ9: 223968 | BA9: 7084 | BB9: 72937 | BC9: 14234 | BD9: 13976 | BE9: 26346 | BF9: 151062 | BG9: 4906 | BH9: 9187 | BI9: 6315 | BJ9: 16688 | BK9: 8992 | BL9: 19411 | BM9: 12668 | BN9: 56950 | BO9: 237669 | BP9: 16380 | BQ9: 38356 | BR9: 10387 | BS9: 1192477 | BT9: 30824 | BU9: 150231 | BV9: 37194 | BW9: 156885 | BX9: 9716 | BY9: 16783 | BZ9: 39883 | CA9: 112476 | CB9: 14374 | CC9: 55324 | CD9: 23801 | CE9: 5017 | CF9: 158981 | CG9: 172142 | CH9: 8507 | CI9: 29139 | CJ9: 1410167 | CK9: 14507 | CL9: 15592 | CM9: 32826 | CN9: 56687 | CO9: 11474 | CP9: 6831 | CQ9: 60147 | CR9: 475960 | CS9: 50747 | CT9: 293746 | CU9: 7696 | CV9: 17870 | CW9: 4977 | CX9: 14972 | CY9: 53989 | CZ9: 40659 | DA9: 7790 | DB9: 60055 | DC9: 10595 | DD9: 20883 | DE9: 4559 | DF9: 406665 | DG9: 6608 | DH9: 17055 | DI9: 41005 | DJ9: 15373 | DK9: 14238 | DL9: 14665 | DM9: 12528 | DN9: 44491 | DO9: 144891 | DP9: 14294 | DQ9: 25038 | DR9: 7171 | DS9: 8032 | DT9: 6787 | DU9: 40134 | DV9: 27779 | DW9: 36101 | DX9: 288646 | DY9: 4405 | DZ9: 34677 | EA9: 38273 | EB9: 5042 | EC9: 5756 | ED9: 17522 | EE9: 7871 | EF9: 8806 | EG9: 19016 | EH9: 106245 | EI9: 8720 | EJ9: 7249 | EK9: 50232 | EL9: 27068 | EM9: 63171 | EN9: 8664 | EO9: 80755 | EP9: 19874 | EQ9: 32911 | ER9: 24695 | ES9: 10049 | ET9: 41154 | EU9: 41692 | EV9: 14553 | EW9: 119546 | EX9: 7270 | EY9: 5873 | EZ9: 23729 | FA9: 18311 | FB9: 11471 | FC9: 12040 | FD9: 6579 | FE9: 15476 | FF9: 1620677 | FG9: 13115 | FH9: 39540 | FI9: 13870 | FJ9: 162356 | FK9: 13277 | FL9: 7344 | FM9: 11705 | FN9: 20989 | FO9: 11552 | FP9: 176574 | FQ9: 29752 | FR9: 15328 | FS9: 9313 | FT9: 12009 | FU9: 6265 | FV9: 10321 | FW9: 20258 | FX9: 46635 | FY9: 20489 | FZ9: 7858 | GA9: 206511 | GB9: 60337 | GC9: 21338 | GD9: 81844 | GE9: 11304 | GF9: 21612 | GG9: 82139 | GH9: 61039 | GI9: 4762 | GJ9: 7185 | GK9: 30096 | GL9: 17064 | GM9: 17158 | GN9: 23928 | GO9: 111627 | GP9: 41851 | GQ9: 42650 | GR9: 181773 | GS9: 72706 | GT9: 415863 | GU9: 12488 | GV9: 20207 | GW9: 11367 | GX9: 3985 | GY9: 5304 | GZ9: 40378 | HA9: 19183 | HB9: 7804 | HC9: 27889 | HD9: 50619 | HE9: 12541 | HF9: 45933 | HG9: 11560 | HH9: 2512553 | HI9: 117559 | HJ9: 71460 | HK9: 15438 | HL9: 9920 | HM9: 56233 | HN9: 38285 | HO9: 14033 | HP9: 5524 | HQ9: 7749 | HR9: 26000 | HS9: 528958 | HT9: 27620 | HU9: 74970 | HV9: 44616 | HW9: 2056991 | HX9: 8034 | HY9: 4174 | HZ9: 38661 | IA9: 154822 | IB9: 281465 | IC9: 5824 | ID9: 9201 | IE9: 18549 | IF9: 159806 | IG9: 7655 | IH9: 9740 | II9: 18893 | IJ9: 6840 | IK9: 9648 | IL9: 12899 | IM9: 6975 | IN9: 15050 | IO9: 28607 | IP9: 22093 | IQ9: 82127 | IR9: 184124 | IS9: 60752 | IT9: 100623 | IU9: 2456192 | IV9: 11988 | IW9: 96807 | IX9: 30412 | IY9: 51396 | IZ9: 41902 | JA9: 57128 | JB9: 213529 | JC9: 38751 | JD9: 91502 | JE9: 583042 | JF9: 9872 | JG9: 5731 | JH9: 209484 | JI9: 5954 | JJ9: 66580 | JK9: 19338 | JL9: 3098 | JM9: 51263 | JN9: 21246 | JO9: 493729 | JP9: 971610 | JQ9: 8899 | JR9: 124852 | JS9: 8980 | JT9: 6491 | JU9: 133833 | JV9: 36616 | JW9: 316263 | JX9: 67795 | JY9: 28173 | JZ9: 191700 | KA9: 71483 | KB9: 26523 | KC9: 16060 | KD9: 23315 | KE9: 137686 | KF9: 14916 | KG9: 64821 | KH9: 22695 | KI9: 92265 | KJ9: 97566 | KK9: 1030497 | KL9: 18408 | KM9: 13260 | KN9: 80808 | KO9: 39377 | KP9: 6498 | KQ9: 8065 | KR9: 360942 | KS9: 13244 | KT9: 9900 | KU9: 14863 | KV9: 8300 | KW9: 190124 | KX9: 70020 | KY9: 69799 | KZ9: 10777 | LA9: 145634 | LB9: 28821 | LC9: 839207 | LD9: 699565 | LE9: 7467 | LF9: 634936 | LG9: 312527 | LH9: 780688 | LI9: 47929 | LJ9: 41912 | LK9: 39902 | LL9: 122239 | LM9: 75520 | LN9: 30725 | LO9: 51194 | LP9: 506656 | LQ9: 18535 | LR9: 13231 | LS9: 7858 | LT9: 17127 | LU9: 24546 | LV9: 31353 | LW9: 20648 | LX9: 20295 | LY9: 26515 | LZ9: 31876 | MA9: 30784 | MB9: 53608 | MC9: 11598 | MD9: 73336 | ME9: 30802 | MF9: 8988 | MG9: 9183 | MH9: 6852 | MI9: 167450 | MJ9: 5326 | MK9: 45677 | ML9: 30890 | MM9: 521962 | MN9: 8482 | MO9: 8389 | MP9: 44835 | MQ9: 23872 | MR9: 8157 | MS9: 41493 | MT9: 221126 | MU9: 154462 | MV9: 14106 | MW9: 15080 | MX9: 25254 | MY9: 257059 | MZ9: 17465 | NA9: 9190 | NB9: 75481 | NC9: 27187 | ND9: 28443 | NE9: 164963 | NF9: 123927 | NG9: 61712 | NH9: 8747 | NI9: 16727 | NJ9: 737869 | NK9: 57071 | NL9: 7847 | NM9: 8989 | NN9: 6769 | NO9: 4853 | NP9: 19313 | NQ9: 6616 | NR9: 76040 | NS9: 16492 | NT9: 5945 | NU9: 6101 | NV9: 29532 | NW9: 12003 | NX9: 59789 | NY9: 101798 | NZ9: 68963 | OA9: 33987 | OB9: 28600 | OC9: 34317 | OD9: 88580
A10: Two races including Some Other Race | B10: 22624 | C10: 31157 | D10: 14884 | E10: 2019 | F10: 4863 | G10: 34587 | H10: 202537 | I10: 3527 | J10: 75844 | K10: 3219 | L10: 38406 | M10: 3003 | N10: 6930 | O10: 12948 | P10: 12632 | Q10: 1906 | R10: 7784 | S10: 65736 | T10: 21920 | U10: 9975 | V10: 341975 | W10: 24982 | X10: 4361 | Y10: 16872 | Z10: 381938 | AA10: 193478 | AB10: 89917 | AC10: 2773 | AD10: 10081 | AE10: 28319 | AF10: 4864 | AG10: 2535 | AH10: 38016 | AI10: 1144 | AJ10: 10073 | AK10: 11121 | AL10: 5675 | AM10: 6833 | AN10: 29990 | AO10: 3663 | AP10: 3515 | AQ10: 5089 | AR10: 3996 | AS10: 52793 | AT10: 343411 | AU10: 29225 | AV10: 4309 | AW10: 4719 | AX10: 12393 | AY10: 97223 | AZ10: 219646 | BA10: 2788 | BB10: 33293 | BC10: 6917 | BD10: 4969 | BE10: 10360 | BF10: 129789 | BG10: 1513 | BH10: 6704 | BI10: 2999 | BJ10: 5805 | BK10: 4021 | BL10: 11242 | BM10: 3330 | BN10: 27612 | BO10: 137754 | BP10: 7661 | BQ10: 17806 | BR10: 5801 | BS10: 893620 | BT10: 18562 | BU10: 61307 | BV10: 14262 | BW10: 80423 | BX10: 5440 | BY10: 9788 | BZ10: 31379 | CA10: 60719 | CB10: 5235 | CC10: 26309 | CD10: 9188 | CE10: 2175 | CF10: 66530 | CG10: 161596 | CH10: 3912 | CI10: 13615 | CJ10: 1109208 | CK10: 10744 | CL10: 8367 | CM10: 17469 | CN10: 19280 | CO10: 4819 | CP10: 1583 | CQ10: 38914 | CR10: 330552 | CS10: 27821 | CT10: 137540 | CU10: 3610 | CV10: 7723 | CW10: 2244 | CX10: 4343 | CY10: 30866 | CZ10: 40267 | DA10: 3500 | DB10: 55772 | DC10: 3754 | DD10: 12690 | DE10: 1950 | DF10: 383469 | DG10: 2087 | DH10: 7788 | DI10: 17398 | DJ10: 4158 | DK10: 4101 | DL10: 5580 | DM10: 7155 | DN10: 18003 | DO10: 119745 | DP10: 7332 | DQ10: 8579 | DR10: 2859 | DS10: 3047 | DT10: 3863 | DU10: 26759 | DV10: 9100 | DW10: 16881 | DX10: 237447 | DY10: 1595 | DZ10: 20856 | EA10: 31108 | EB10: 3022 | EC10: 3463 | ED10: 12620 | EE10: 3012 | EF10: 7364 | EG10: 13052 | EH10: 62594 | EI10: 3808 | EJ10: 2749 | EK10: 37522 | EL10: 13303 | EM10: 33537 | EN10: 3291 | EO10: 41106 | EP10: 18173 | EQ10: 12866 | ER10: 10408 | ES10: 6194 | ET10: 35003 | EU10: 16891 | EV10: 9254 | EW10: 69347 | EX10: 3124 | EY10: 2546 | EZ10: 12241 | FA10: 11959 | FB10: 5357 | FC10: 6300 | FD10: 2543 | FE10: 7354 | FF10: 1376566 | FG10: 4151 | FH10: 16410 | FI10: 8771 | FJ10: 78469 | FK10: 6015 | FL10: 3431 | FM10: 5575 | FN10: 8797 | FO10: 4331 | FP10: 104658 | FQ10: 12710 | FR10: 9422 | FS10: 3126 | FT10: 5835 | FU10: 2085 | FV10: 5549 | FW10: 9510 | FX10: 5791 | FY10: 8609 | FZ10: 4817 | GA10: 113514 | GB10: 48920 | GC10: 13633 | GD10: 47112 | GE10: 5141 | GF10: 15159 | GG10: 53778 | GH10: 33274 | GI10: 1138 | GJ10: 2736 | GK10: 18590 | GL10: 10408 | GM10: 7987 | GN10: 15824 | GO10: 84801 | GP10: 24019 | GQ10: 18846 | GR10: 180405 | GS10: 65465 | GT10: 265885 | GU10: 4429 | GV10: 6168 | GW10: 7085 | GX10: 1472 | GY10: 2261 | GZ10: 18347 | HA10: 8012 | HB10: 2020 | HC10: 11841 | HD10: 24958 | HE10: 6894 | HF10: 32249 | HG10: 5546 | HH10: 1954217 | HI10: 56816 | HJ10: 60291 | HK10: 6712 | HL10: 3583 | HM10: 30785 | HN10: 24146 | HO10: 6092 | HP10: 2836 | HQ10: 1283 | HR10: 20710 | HS10: 522441 | HT10: 15263 | HU10: 37925 | HV10: 33700 | HW10: 1878627 | HX10: 4084 | HY10: 2316 | HZ10: 33771 | IA10: 98728 | IB10: 118106 | IC10: 2129 | ID10: 3676 | IE10: 6718 | IF10: 131375 | IG10: 4260 | IH10: 4443 | II10: 8320 | IJ10: 2401 | IK10: 6287 | IL10: 6727 | IM10: 1827 | IN10: 6031 | IO10: 17793 | IP10: 15815 | IQ10: 74138 | IR10: 110521 | IS10: 41330 | IT10: 63378 | IU10: 1831878 | IV10: 5174 | IW10: 74151 | IX10: 15864 | IY10: 39116 | IZ10: 36657 | JA10: 34093 | JB10: 93811 | JC10: 15670 | JD10: 50861 | JE10: 481495 | JF10: 5011 | JG10: 1982 | JH10: 166396 | JI10: 2259 | JJ10: 40856 | JK10: 9136 | JL10: 1006 | JM10: 20257 | JN10: 9203 | JO10: 260349 | JP10: 724801 | JQ10: 3705 | JR10: 54145 | JS10: 3859 | JT10: 3262 | JU10: 129883 | JV10: 20796 | JW10: 161752 | JX10: 52914 | JY10: 19570 | JZ10: 130585 | KA10: 42005 | KB10: 19024 | KC10: 10709 | KD10: 14572 | KE10: 78517 | KF10: 4575 | KG10: 39673 | KH10: 10990 | KI10: 61767 | KJ10: 42726 | KK10: 808400 | KL10: 9115 | KM10: 6680 | KN10: 41833 | KO10: 22627 | KP10: 2598 | KQ10: 4539 | KR10: 191025 | KS10: 7427 | KT10: 3381 | KU10: 8101 | KV10: 3736 | KW10: 90683 | KX10: 42707 | KY10: 52935 | KZ10: 4716 | LA10: 89244 | LB10: 25189 | LC10: 723971 | LD10: 500847 | LE10: 4226 | LF10: 349444 | LG10: 217255 | LH10: 711525 | LI10: 33766 | LJ10: 29182 | LK10: 34904 | LL10: 100703 | LM10: 49451 | LN10: 14100 | LO10: 34032 | LP10: 200411 | LQ10: 13247 | LR10: 10142 | LS10: 4531 | LT10: 10477 | LU10: 11940 | LV10: 24849 | LW10: 15303 | LX10: 8919 | LY10: 16820 | LZ10: 17279 | MA10: 18090 | MB10: 20163 | MC10: 4116 | MD10: 53850 | ME10: 12137 | MF10: 2256 | MG10: 4151 | MH10: 2473 | MI10: 105505 | MJ10: 1362 | MK10: 20681 | ML10: 16019 | MM10: 392266 | MN10: 2615 | MO10: 3726 | MP10: 19726 | MQ10: 10593 | MR10: 3885 | MS10: 28552 | MT10: 165703 | MU10: 57398 | MV10: 5657 | MW10: 11612 | MX10: 17757 | MY10: 19527 | MZ10: 9961 | NA10: 4575 | NB10: 37102 | NC10: 24431 | ND10: 22389 | NE10: 66274 | NF10: 110392 | NG10: 51352 | NH10: 6080 | NI10: 6569 | NJ10: 426561 | NK10: 36433 | NL10: 2731 | NM10: 3316 | NN10: 2138 | NO10: 1773 | NP10: 14925 | NQ10: 2537 | NR10: 40563 | NS10: 10716 | NT10: 3720 | NU10: 2686 | NV10: 14126 | NW10: 6555 | NX10: 34961 | NY10: 72259 | NZ10: 57684 | OA10: 18615 | OB10: 12533 | OC10: 21429 | OD10: 82180
A11: Two races excluding Some Other Race, and three or more races | B11: 6788 | C11: 45440 | D11: 28631 | E11: 4080 | F11: 7085 | G11: 33210 | H11: 44851 | I11: 4895 | J11: 27535 | K11: 2522 | L11: 9491 | M11: 3830 | N11: 5550 | O11: 43361 | P11: 18595 | Q11: 3052 | R11: 6810 | S11: 2255 | T11: 14286 | U11: 7294 | V11: 236604 | W11: 14992 | X11: 5285 | Y11: 25786 | Z11: 108130 | AA11: 33920 | AB11: 117564 | AC11: 3710 | AD11: 6325 | AE11: 27618 | AF11: 7483 | AG11: 3914 | AH11: 10854 | AI11: 3356 | AJ11: 13170 | AK11: 10747 | AL11: 7760 | AM11: 8331 | AN11: 25510 | AO11: 3959 | AP11: 4763 | AQ11: 4818 | AR11: 5494 | AS11: 32165 | AT11: 185031 | AU11: 13464 | AV11: 6770 | AW11: 3736 | AX11: 23697 | AY11: 30785 | AZ11: 4322 | BA11: 4296 | BB11: 39644 | BC11: 7317 | BD11: 9007 | BE11: 15986 | BF11: 21273 | BG11: 3393 | BH11: 2483 | BI11: 3316 | BJ11: 10883 | BK11: 4971 | BL11: 8169 | BM11: 9338 | BN11: 29338 | BO11: 99915 | BP11: 8719 | BQ11: 20550 | BR11: 4586 | BS11: 298857 | BT11: 12262 | BU11: 88924 | BV11: 22932 | BW11: 76462 | BX11: 4276 | BY11: 6995 | BZ11: 8504 | CA11: 51757 | CB11: 9139 | CC11: 29015 | CD11: 14613 | CE11: 2842 | CF11: 92451 | CG11: 10546 | CH11: 4595 | CI11: 15524 | CJ11: 300959 | CK11: 3763 | CL11: 7225 | CM11: 15357 | CN11: 37407 | CO11: 6655 | CP11: 5248 | CQ11: 21233 | CR11: 145408 | CS11: 22926 | CT11: 156206 | CU11: 4086 | CV11: 10147 | CW11: 2733 | CX11: 10629 | CY11: 23123 | CZ11: 392 | DA11: 4290 | DB11: 4283 | DC11: 6841 | DD11: 8193 | DE11: 2609 | DF11: 23196 | DG11: 4521 | DH11: 9267 | DI11: 23607 | DJ11: 11215 | DK11: 10137 | DL11: 9085 | DM11: 5373 | DN11: 26488 | DO11: 25146 | DP11: 6962 | DQ11: 16459 | DR11: 4312 | DS11: 4985 | DT11: 2924 | DU11: 13375 | DV11: 18679 | DW11: 19220 | DX11: 51199 | DY11: 2810 | DZ11: 13821 | EA11: 7165 | EB11: 2020 | EC11: 2293 | ED11: 4902 | EE11: 4859 | EF11: 1442 | EG11: 5964 | EH11: 43651 | EI11: 4912 | EJ11: 4500 | EK11: 12710 | EL11: 13765 | EM11: 29634 | EN11: 5373 | EO11: 39649 | EP11: 1701 | EQ11: 20045 | ER11: 14287 | ES11: 3855 | ET11: 6151 | EU11: 24801 | EV11: 5299 | EW11: 50199 | EX11: 4146 | EY11: 3327 | EZ11: 11488 | FA11: 6352 | FB11: 6114 | FC11: 5740 | FD11: 4036 | FE11: 8122 | FF11: 244111 | FG11: 8964 | FH11: 23130 | FI11: 5099 | FJ11: 83887 | FK11: 7262 | FL11: 3913 | FM11: 6130 | FN11: 12192 | FO11: 7221 | FP11: 71916 | FQ11: 17042 | FR11: 5906 | FS11: 6187 | FT11: 6174 | FU11: 4180 | FV11: 4772 | FW11: 10748 | FX11: 40844 | FY11: 11880 | FZ11: 3041 | GA11: 92997 | GB11: 11417 | GC11: 7705 | GD11: 34732 | GE11: 6163 | GF11: 6453 | GG11: 28361 | GH11: 27765 | GI11: 3624 | GJ11: 4449 | GK11: 11506 | GL11: 6656 | GM11: 9171 | GN11: 8104 | GO11: 26826 | GP11: 17832 | GQ11: 23804 | GR11: 1368 | GS11: 7241 | GT11: 149978 | GU11: 8059 | GV11: 14039 | GW11: 4282 | GX11: 2513 | GY11: 3043 | GZ11: 22031 | HA11: 11171 | HB11: 5784 | HC11: 16048 | HD11: 25661 | HE11: 5647 | HF11: 13684 | HG11: 6014 | HH11: 558336 | HI11: 60743 | HJ11: 11169 | HK11: 8726 | HL11: 6337 | HM11: 25448 | HN11: 14139 | HO11: 7941 | HP11: 2688 | HQ11: 6466 | HR11: 5290 | HS11: 6517 | HT11: 12357 | HU11: 37045 | HV11: 10916 | HW11: 178364 | HX11: 3950 | HY11: 1858 | HZ11: 4890 | IA11: 56094 | IB11: 163359 | IC11: 3695 | ID11: 5525 | IE11: 11831 | IF11: 28431 | IG11: 3395 | IH11: 5297 | II11: 10573 | IJ11: 4439 | IK11: 3361 | IL11: 6172 | IM11: 5148 | IN11: 9019 | IO11: 10814 | IP11: 6278 | IQ11: 7989 | IR11: 73603 | IS11: 19422 | IT11: 37245 | IU11: 624314 | IV11: 6814 | IW11: 22656 | IX11: 14548 | IY11: 12280 | IZ11: 5245 | JA11: 23035 | JB11: 119718 | JC11: 23081 | JD11: 40641 | JE11: 101547 | JF11: 4861 | JG11: 3749 | JH11: 43088 | JI11: 3695 | JJ11: 25724 | JK11: 10202 | JL11: 2092 | JM11: 31006 | JN11: 12043 | JO11: 233380 | JP11: 246809 | JQ11: 5194 | JR11: 70707 | JS11: 5121 | JT11: 3229 | JU11: 3950 | JV11: 15820 | JW11: 154511 | JX11: 14881 | JY11: 8603 | JZ11: 61115 | KA11: 29478 | KB11: 7499 | KC11: 5351 | KD11: 8743 | KE11: 59169 | KF11: 10341 | KG11: 25148 | KH11: 11705 | KI11: 30498 | KJ11: 54840 | KK11: 222097 | KL11: 9293 | KM11: 6580 | KN11: 38975 | KO11: 16750 | KP11: 3900 | KQ11: 3526 | KR11: 169917 | KS11: 5817 | KT11: 6519 | KU11: 6762 | KV11: 4564 | KW11: 99441 | KX11: 27313 | KY11: 16864 | KZ11: 6061 | LA11: 56390 | LB11: 3632 | LC11: 115236 | LD11: 198718 | LE11: 3241 | LF11: 285492 | LG11: 95272 | LH11: 69163 | LI11: 14163 | LJ11: 12730 | LK11: 4998 | LL11: 21536 | LM11: 26069 | LN11: 16625 | LO11: 17162 | LP11: 306245 | LQ11: 5288 | LR11: 3089 | LS11: 3327 | LT11: 6650 | LU11: 12606 | LV11: 6504 | LW11: 5345 | LX11: 11376 | LY11: 9695 | LZ11: 14597 | MA11: 12694 | MB11: 33445 | MC11: 7482 | MD11: 19486 | ME11: 18665 | MF11: 6732 | MG11: 5032 | MH11: 4379 | MI11: 61945 | MJ11: 3964 | MK11: 24996 | ML11: 14871 | MM11: 129696 | MN11: 5867 | MO11: 4663 | MP11: 25109 | MQ11: 13279 | MR11: 4272 | MS11: 12941 | MT11: 55423 | MU11: 97064 | MV11: 8449 | MW11: 3468 | MX11: 7497 | MY11: 237532 | MZ11: 7504 | NA11: 4615 | NB11: 38379 | NC11: 2756 | ND11: 6054 | NE11: 98689 | NF11: 13535 | NG11: 10360 | NH11: 2667 | NI11: 10158 | NJ11: 311308 | NK11: 20638 | NL11: 5116 | NM11: 5673 | NN11: 4631 | NO11: 3080 | NP11: 4388 | NQ11: 4079 | NR11: 35477 | NS11: 5776 | NT11: 2225 | NU11: 3415 | NV11: 15406 | NW11: 5448 | NX11: 24828 | NY11: 29539 | NZ11: 11279 | OA11: 15372 | OB11: 16067 | OC11: 12888 | OD11: 6400

Sheet hispanic
A1: Label (Grouping) | B1: Abilene, TX | C1: Aguadilla, PR | D1: Akron, OH | E1: Albany, GA | F1: Albany, OR | G1: Albany-Schenectady-Troy, NY | H1: Albuquerque, NM | I1: Alexandria, LA | J1: Allentown-Bethlehem-Easton, PA-NJ | K1: Altoona, PA | L1: Amarillo, TX | M1: Ames, IA | N1: Amherst Town-Northampton, MA | O1: Anchorage, AK | P1: Ann Arbor, MI | Q1: Anniston-Oxford, AL | R1: Appleton, WI | S1: Arecibo, PR | T1: Asheville, NC | U1: Athens-Clarke County, GA | V1: Atlanta-Sandy Springs-Roswell, GA | W1: Atlantic City-Hammonton, NJ | X1: Auburn-Opelika, AL | Y1: Augusta-Richmond County, GA-SC | Z1: Austin-Round Rock-San Marcos, TX | AA1: Bakersfield-Delano, CA | AB1: Baltimore-Columbia-Towson, MD | AC1: Bangor, ME | AD1: Barnstable Town, MA | AE1: Baton Rouge, LA | AF1: Battle Creek, MI | AG1: Bay City, MI | AH1: Beaumont-Port Arthur, TX | AI1: Beckley, WV | AJ1: Bellingham, WA | AK1: Bend, OR | AL1: Billings, MT | AM1: Binghamton, NY | AN1: Birmingham, AL | AO1: Bismarck, ND | AP1: Blacksburg-Christiansburg-Radford, VA | AQ1: Bloomington, IL | AR1: Bloomington, IN | AS1: Boise City, ID | AT1: Boston-Cambridge-Newton, MA-NH | AU1: Boulder, CO | AV1: Bowling Green, KY | AW1: Bozeman, MT | AX1: Bremerton-Silverdale-Port Orchard, WA | AY1: Bridgeport-Stamford-Danbury, CT | AZ1: Brownsville-Harlingen, TX | BA1: Brunswick-St. Simons, GA | BB1: Buffalo-Cheektowaga, NY | BC1: Burlington, NC | BD1: Burlington-South Burlington, VT | BE1: Canton-Massillon, OH | BF1: Cape Coral-Fort Myers, FL | BG1: Cape Girardeau, MO-IL | BH1: Carson City, NV | BI1: Casper, WY | BJ1: Cedar Rapids, IA | BK1: Chambersburg, PA | BL1: Champaign-Urbana, IL | BM1: Charleston, WV | BN1: Charleston-North Charleston, SC | BO1: Charlotte-Concord-Gastonia, NC-SC | BP1: Charlottesville, VA | BQ1: Chattanooga, TN-GA | BR1: Cheyenne, WY | BS1: Chicago-Naperville-Elgin, IL-IN | BT1: Chico, CA | BU1: Cincinnati, OH-KY-IN | BV1: Clarksville, TN-KY | BW1: Cleveland, OH | BX1: Cleveland, TN | BY1: Coeur d'Alene, ID | BZ1: College Station-Bryan, TX | CA1: Colorado Springs, CO | CB1: Columbia, MO | CC1: Columbia, SC | CD1: Columbus, GA-AL | CE1: Columbus, IN | CF1: Columbus, OH | CG1: Corpus Christi, TX | CH1: Corvallis, OR | CI1: Crestview-Fort Walton Beach-Destin, FL | CJ1: Dallas-Fort Worth-Arlington, TX | CK1: Dalton, GA | CL1: Daphne-Fairhope-Foley, AL | CM1: Davenport-Moline-Rock Island, IA-IL | CN1: Dayton-Kettering-Beavercreek, OH | CO1: Decatur, AL | CP1: Decatur, IL | CQ1: Deltona-Daytona Beach-Ormond Beach, FL | CR1: Denver-Aurora-Centennial, CO | CS1: Des Moines-West Des Moines, IA | CT1: Detroit-Warren-Dearborn, MI | CU1: Dothan, AL | CV1: Dover, DE | CW1: Dubuque, IA | CX1: Duluth, MN-WI | CY1: Durham-Chapel Hill, NC | CZ1: Eagle Pass, TX | DA1: Eau Claire, WI | DB1: El Centro, CA | DC1: Elizabethtown, KY | DD1: Elkhart-Goshen, IN | DE1: Elmira, NY | DF1: El Paso, TX | DG1: Enid, OK | DH1: Erie, PA | DI1: Eugene-Springfield, OR | DJ1: Evansville, IN | DK1: Fairbanks-College, AK | DL1: Fargo, ND-MN | DM1: Farmington, NM | DN1: Fayetteville, NC | DO1: Fayetteville-Springdale-Rogers, AR | DP1: Flagstaff, AZ | DQ1: Flint, MI | DR1: Florence, SC | DS1: Florence-Muscle Shoals, AL | DT1: Fond du Lac, WI | DU1: Fort Collins-Loveland, CO | DV1: Fort Smith, AR-OK | DW1: Fort Wayne, IN | DX1: Fresno, CA | DY1: Gadsden, AL | DZ1: Gainesville, FL | EA1: Gainesville, GA | EB1: Gettysburg, PA | EC1: Glens Falls, NY | ED1: Goldsboro, NC | EE1: Grand Forks, ND-MN | EF1: Grand Island, NE | EG1: Grand Junction, CO | EH1: Grand Rapids-Wyoming-Kentwood, MI | EI1: Grants Pass, OR | EJ1: Great Falls, MT | EK1: Greeley, CO | EL1: Green Bay, WI | EM1: Greensboro-High Point, NC | EN1: Greenville, NC | EO1: Greenville-Anderson-Greer, SC | EP1: Guayama, PR | EQ1: Gulfport-Biloxi, MS | ER1: Hagerstown-Martinsburg, MD-WV | ES1: Hammond, LA | ET1: Hanford-Corcoran, CA | EU1: Harrisburg-Carlisle, PA | EV1: Harrisonburg, VA | EW1: Hartford-West Hartford-East Hartford, CT | EX1: Hattiesburg, MS | EY1: Helena, MT | EZ1: Hickory-Lenoir-Morganton, NC | FA1: Hilton Head Island-Bluffton-Port Royal, SC | FB1: Hinesville, GA | FC1: Homosassa Springs, FL | FD1: Hot Springs, AR | FE1: Houma-Bayou Cane-Thibodaux, LA | FF1: Houston-Pasadena-The Woodlands, TX | FG1: Huntington-Ashland, WV-KY-OH | FH1: Huntsville, AL | FI1: Idaho Falls, ID | FJ1: Indianapolis-Carmel-Greenwood, IN | FK1: Iowa City, IA | FL1: Ithaca, NY | FM1: Jackson, MI | FN1: Jackson, MS | FO1: Jackson, TN | FP1: Jacksonville, FL | FQ1: Jacksonville, NC | FR1: Janesville-Beloit, WI | FS1: Jefferson City, MO | FT1: Johnson City, TN | FU1: Johnstown, PA | FV1: Jonesboro, AR | FW1: Joplin, MO-KS | FX1: Kahului-Wailuku, HI | FY1: Kalamazoo-Portage, MI | FZ1: Kankakee, IL | GA1: Kansas City, MO-KS | GB1: Kennewick-Richland, WA | GC1: Kenosha, WI | GD1: Killeen-Temple, TX | GE1: Kingsport-Bristol, TN-VA | GF1: Kingston, NY | GG1: Kiryas Joel-Poughkeepsie-Newburgh, NY | GH1: Knoxville, TN | GI1: Kokomo, IN | GJ1: La Crosse-Onalaska, WI-MN | GK1: Lafayette, LA | GL1: Lafayette-West Lafayette, IN | GM1: Lake Charles, LA | GN1: Lake Havasu City-Kingman, AZ | GO1: Lakeland-Winter Haven, FL | GP1: Lancaster, PA | GQ1: Lansing-East Lansing, MI | GR1: Laredo, TX | GS1: Las Cruces, NM | GT1: Las Vegas-Henderson-North Las Vegas, NV | GU1: Lawrence, KS | GV1: Lawton, OK | GW1: Lebanon, PA | GX1: Lewiston, ID-WA | GY1: Lewiston-Auburn, ME | GZ1: Lexington-Fayette, KY | HA1: Lexington Park, MD | HB1: Lima, OH | HC1: Lincoln, NE | HD1: Little Rock-North Little Rock-Conway, AR | HE1: Logan, UT-ID | HF1: Longview, TX | HG1: Longview-Kelso, WA | HH1: Los Angeles-Long Beach-Anaheim, CA | HI1: Louisville/Jefferson County, KY-IN | HJ1: Lubbock, TX | HK1: Lynchburg, VA | HL1: Macon-Bibb County, GA | HM1: Madison, WI | HN1: Manchester-Nashua, NH | HO1: Manhattan, KS | HP1: Mankato, MN | HQ1: Mansfield, OH | HR1: Mayagüez, PR | HS1: McAllen-Edinburg-Mission, TX | HT1: Medford, OR | HU1: Memphis, TN-MS-AR | HV1: Merced, CA | HW1: Miami-Fort Lauderdale-West Palm Beach, FL | HX1: Michigan City-La Porte, IN | HY1: Midland, MI | HZ1: Midland, TX | IA1: Milwaukee-Waukesha, WI | IB1: Minneapolis-St. Paul-Bloomington, MN-WI | IC1: Minot, ND | ID1: Missoula, MT | IE1: Mobile, AL | IF1: Modesto, CA | IG1: Monroe, LA | IH1: Monroe, MI | II1: Montgomery, AL | IJ1: Morgantown, WV | IK1: Morristown, TN | IL1: Mount Vernon-Anacortes, WA | IM1: Muncie, IN | IN1: Muskegon-Norton Shores, MI | IO1: Myrtle Beach-Conway-North Myrtle Beach, SC | IP1: Napa, CA | IQ1: Naples-Marco Island, FL | IR1: Nashville-Davidson--Murfreesboro--Franklin, TN | IS1: New Haven, CT | IT1: New Orleans-Metairie, LA | IU1: New York-Newark-Jersey City, NY-NJ | IV1: Niles, MI | IW1: North Port-Bradenton-Sarasota, FL | IX1: Norwich-New London-Willimantic, CT | IY1: Ocala, FL | IZ1: Odessa, TX | JA1: Ogden, UT | JB1: Oklahoma City, OK | JC1: Olympia-Lacey-Tumwater, WA | JD1: Omaha, NE-IA | JE1: Orlando-Kissimmee-Sanford, FL | JF1: Oshkosh-Neenah, WI | JG1: Owensboro, KY | JH1: Oxnard-Thousand Oaks-Ventura, CA | JI1: Paducah, KY-IL | JJ1: Palm Bay-Melbourne-Titusville, FL | JK1: Panama City-Panama City Beach, FL | JL1: Parkersburg-Vienna, WV | JM1: Pensacola-Ferry Pass-Brent, FL | JN1: Peoria, IL | JO1: Philadelphia-Camden-Wilmington, PA-NJ-DE-MD | JP1: Phoenix-Mesa-Chandler, AZ | JQ1: Pinehurst-Southern Pines, NC | JR1: Pittsburgh, PA | JS1: Pittsfield, MA | JT1: Pocatello, ID | JU1: Ponce, PR | JV1: Portland-South Portland, ME | JW1: Portland-Vancouver-Hillsboro, OR-WA | JX1: Port St. Lucie, FL | JY1: Prescott Valley-Prescott, AZ | JZ1: Providence-Warwick, RI-MA | KA1: Provo-Orem-Lehi, UT | KB1: Pueblo, CO | KC1: Punta Gorda, FL | KD1: Racine-Mount Pleasant, WI | KE1: Raleigh-Cary, NC | KF1: Rapid City, SD | KG1: Reading, PA | KH1: Redding, CA | KI1: Reno, NV | KJ1: Richmond, VA | KK1: Riverside-San Bernardino-Ontario, CA | KL1: Roanoke, VA | KM1: Rochester, MN | KN1: Rochester, NY | KO1: Rockford, IL | KP1: Rocky Mount, NC | KQ1: Rome, GA | KR1: Sacramento-Roseville-Folsom, CA | KS1: Saginaw, MI | KT1: St. Cloud, MN | KU1: St. George, UT | KV1: St. Joseph, MO-KS | KW1: St. Louis, MO-IL | KX1: Salem, OR | KY1: Salinas, CA | KZ1: Salisbury, MD | LA1: Salt Lake City-Murray, UT | LB1: San Angelo, TX | LC1: San Antonio-New Braunfels, TX | LD1: San Diego-Chula Vista-Carlsbad, CA | LE1: Sandusky, OH | LF1: San Francisco-Oakland-Fremont, CA | LG1: San Jose-Sunnyvale-Santa Clara, CA | LH1: San Juan-Bayamón-Caguas, PR | LI1: San Luis Obispo-Paso Robles, CA | LJ1: Santa Cruz-Watsonville, CA | LK1: Santa Fe, NM | LL1: Santa Maria-Santa Barbara, CA | LM1: Santa Rosa-Petaluma, CA | LN1: Savannah, GA | LO1: Scranton--Wilkes-Barre, PA | LP1: Seattle-Tacoma-Bellevue, WA | LQ1: Sebastian-Vero Beach-West Vero Corridor, FL | LR1: Sebring, FL | LS1: Sheboygan, WI | LT1: Sherman-Denison, TX | LU1: Shreveport-Bossier City, LA | LV1: Sierra Vista-Douglas, AZ | LW1: Sioux City, IA-NE-SD | LX1: Sioux Falls, SD-MN | LY1: Slidell-Mandeville-Covington, LA | LZ1: South Bend-Mishawaka, IN-MI | MA1: Spartanburg, SC | MB1: Spokane-Spokane Valley, WA | MC1: Springfield, IL | MD1: Springfield, MA | ME1: Springfield, MO | MF1: Springfield, OH | MG1: State College, PA | MH1: Staunton-Stuarts Draft, VA | MI1: Stockton-Lodi, CA | MJ1: Sumter, SC | MK1: Syracuse, NY | ML1: Tallahassee, FL | MM1: Tampa-St. Petersburg-Clearwater, FL | MN1: Terre Haute, IN | MO1: Texarkana, TX-AR | MP1: Toledo, OH | MQ1: Topeka, KS | MR1: Traverse City, MI | MS1: Trenton-Princeton, NJ | MT1: Tucson, AZ | MU1: Tulsa, OK | MV1: Tuscaloosa, AL | MW1: Twin Falls, ID | MX1: Tyler, TX | MY1: Urban Honolulu, HI | MZ1: Utica-Rome, NY | NA1: Valdosta, GA | NB1: Vallejo, CA | NC1: Victoria, TX | ND1: Vineland, NJ | NE1: Virginia Beach-Chesapeake-Norfolk, VA-NC | NF1: Visalia, CA | NG1: Waco, TX | NH1: Walla Walla, WA | NI1: Warner Robins, GA | NJ1: Washington-Arlington-Alexandria, DC-VA-MD-WV | NK1: Waterbury-Shelton, CT | NL1: Waterloo-Cedar Falls, IA | NM1: Watertown-Fort Drum, NY | NN1: Wausau, WI | NO1: Weirton-Steubenville, WV-OH | NP1: Wenatchee-East Wenatchee, WA | NQ1: Wheeling, WV-OH | NR1: Wichita, KS | NS1: Wichita Falls, TX | NT1: Wildwood-The Villages, FL | NU1: Williamsport, PA | NV1: Wilmington, NC | NW1: Winchester, VA-WV | NX1: Winston-Salem, NC | NY1: Worcester, MA | NZ1: Yakima, WA | OA1: York-Hanover, PA | OB1: Youngstown-Warren, OH | OC1: Yuba City, CA | OD1: Yuma, AZ
A2: Total: | B2: 180408 | C2: 251769 | D2: 699820 | E2: 146018 | F2: 130706 | G2: 906052 | H2: 921482 | I2: 149622 | J2: 873603 | K2: 121277 | L2: 271917 | M2: 127134 | N2: 162028 | O2: 401964 | P2: 369822 | Q2: 116090 | R2: 245768 | S2: 180767 | T2: 414711 | U2: 220197 | V2: 6256377 | W2: 371211 | X2: 199825 | Y2: 624181 | Z2: 2426592 | AA2: 915075 | AB2: 2849436 | AC2: 154710 | AD2: 231668 | AE2: 875313 | AF2: 133778 | AG2: 103008 | AH2: 396827 | AI2: 112714 | AJ2: 230503 | AK2: 257814 | AL2: 189255 | AM2: 245242 | AN2: 1184613 | AO2: 136216 | AP2: 181664 | AQ2: 171556 | AR2: 162569 | AS2: 811115 | AT2: 4953354 | AU2: 328961 | AV2: 186959 | AW2: 124074 | AX2: 277881 | AY2: 956330 | AZ2: 426120 | BA2: 115074 | BB2: 1161343 | BC2: 176893 | BD2: 227846 | BE2: 400372 | BF2: 817666 | BG2: 98169 | BH2: 58384 | BI2: 79977 | BJ2: 276624 | BK2: 157379 | BL2: 238842 | BM2: 205398 | BN2: 834267 | BO2: 2768407 | BP2: 224335 | BQ2: 575812 | BR2: 101060 | BS2: 9371595 | BT2: 207929 | BU2: 2270706 | BV2: 334564 | BW2: 2171526 | BX2: 128963 | BY2: 181996 | BZ2: 278335 | CA2: 767824 | CB2: 215014 | CC2: 849181 | CD2: 325615 | CE2: 83536 | CF2: 2175788 | CG2: 448012 | CH2: 96303 | CI2: 299547 | CJ2: 7985590 | CK2: 144160 | CL2: 246989 | CM2: 381503 | CN2: 816080 | CO2: 157747 | CP2: 101849 | CQ2: 706150 | CR2: 3002721 | CS2: 731120 | CT2: 4376828 | CU2: 152674 | CV2: 187604 | CW2: 99030 | CX2: 280870 | CY2: 601724 | CZ2: 58082 | DA2: 173915 | DB2: 180202 | DC2: 127049 | DD2: 207132 | DE2: 82147 | DF2: 874182 | DG2: 62146 | DH2: 269052 | DI2: 384207 | DJ2: 270494 | DK2: 95460 | DL2: 259459 | DM2: 120942 | DN2: 392380 | DO2: 577726 | DP2: 144508 | DQ2: 403305 | DR2: 199675 | DS2: 153852 | DT2: 104137 | DU2: 367368 | DV2: 229899 | DW2: 455416 | DX2: 1177665 | DY2: 103105 | DZ2: 349923 | EA2: 212705 | EB2: 106115 | EC2: 126039 | ED2: 118652 | EE2: 103628 | EF2: 76794 | EG2: 158601 | EH2: 1162152 | EI2: 88179 | EJ2: 84606 | EK2: 350396 | EL2: 331145 | EM2: 786419 | EN2: 177193 | EO2: 961939 | EP2: 66202 | EQ2: 421201 | ER2: 302649 | ES2: 136738 | ET2: 153298 | EU2: 604155 | EV2: 136992 | EW2: 1153112 | EX2: 155434 | EY2: 93906 | EZ2: 368316 | FA2: 227455 | FB2: 85771 | FC2: 162472 | FD2: 100035 | FE2: 202438 | FF2: 7442788 | FG2: 370729 | FH2: 516951 | FI2: 165361 | FJ2: 2130055 | FK2: 179200 | FL2: 104537 | FM2: 160060 | FN2: 611324 | FO2: 181719 | FP2: 1683960 | FQ2: 207906 | FR2: 164350 | FS2: 150437 | FT2: 210729 | FU2: 131538 | FV2: 135792 | FW2: 203626 | FX2: 164589 | FY2: 262375 | FZ2: 106635 | GA2: 2218142 | GB2: 311807 | GC2: 168438 | GD2: 494360 | GE2: 310842 | GF2: 182601 | GG2: 704836 | GH2: 932241 | GI2: 83752 | GJ2: 170190 | GK2: 413428 | GL2: 226805 | GM2: 244027 | GN2: 220517 | GO2: 790694 | GP2: 557931 | GQ2: 472669 | GR2: 269294 | GS2: 224266 | GT2: 2329548 | GU2: 120302 | GV2: 127310 | GW2: 144186 | GX2: 65164 | GY2: 113423 | GZ2: 522560 | HA2: 209439 | HB2: 101348 | HC2: 344337 | HD2: 758629 | HE2: 155102 | HF2: 291044 | HG2: 112360 | HH2: 12974487 | HI2: 1372558 | HJ2: 358708 | HK2: 263798 | HL2: 234943 | HM2: 691830 | HN2: 426378 | HO2: 133965 | HP2: 104282 | HQ2: 125099 | HR2: 209892 | HS2: 891977 | HT2: 222645 | HU2: 1341924 | HV2: 290201 | HW2: 6249291 | HX2: 111917 | HY2: 83757 | HZ2: 180019 | IA2: 1568938 | IB2: 3713668 | IC2: 76484 | ID2: 125631 | IE2: 412590 | IF2: 553990 | IG2: 223674 | IH2: 155505 | II2: 386024 | IJ2: 141323 | IK2: 122533 | IL2: 131328 | IM2: 112280 | IN2: 175961 | IO2: 383016 | IP2: 134869 | IQ2: 398291 | IR2: 2079596 | IS2: 570598 | IT2: 981662 | IU2: 19798537 | IV2: 153288 | IW2: 889339 | IX2: 279971 | IY2: 400078 | IZ2: 164654 | JA2: 653374 | JB2: 1463267 | JC2: 299067 | JD2: 982064 | JE2: 2793746 | JF2: 171769 | JG2: 112762 | JH2: 837469 | JI2: 102748 | JJ2: 632780 | JK2: 211922 | JL2: 88460 | JM2: 524395 | JN2: 365202 | JO2: 6272014 | JP2: 5028754 | JQ2: 104876 | JR2: 2439940 | JS2: 129430 | JT2: 89454 | JU2: 270459 | JV2: 562843 | JW2: 2520987 | JX2: 522676 | JY2: 245480 | JZ2: 1684071 | KA2: 717986 | KB2: 169356 | KC2: 201064 | KD2: 197532 | KE2: 1487302 | KF2: 152950 | KG2: 433015 | KH2: 181436 | KI2: 563020 | KJ2: 1341248 | KK2: 4675704 | KL2: 314986 | KM2: 228522 | KN2: 1058413 | KO2: 336522 | KP2: 144952 | KQ2: 99693 | KR2: 2426388 | KS2: 188665 | KT2: 202458 | KU2: 196431 | KV2: 120012 | KW2: 2810850 | KX2: 438906 | KY2: 437613 | KZ2: 129736 | LA2: 1275870 | LB2: 120986 | LC2: 2662733 | LD2: 3288774 | LE2: 114575 | LF2: 4645029 | LG2: 1969337 | LH2: 2052186 | LI2: 281555 | LJ2: 264926 | LK2: 156105 | LL2: 443701 | LM2: 485040 | LN2: 418285 | LO2: 569788 | LP2: 4061920 | LQ2: 166936 | LR2: 105702 | LS2: 117991 | LT2: 143337 | LU2: 386819 | LV2: 125566 | LW2: 144682 | LX2: 298181 | LY2: 272421 | LZ2: 324560 | MA2: 374737 | MB2: 597123 | MC2: 207042 | MD2: 462815 | ME2: 486785 | MF2: 135158 | MG2: 158576 | MH2: 126822 | MI2: 797334 | MJ2: 104725 | MK2: 656410 | ML2: 391730 | MM2: 3304691 | MN2: 168719 | MO2: 146296 | MP2: 602322 | MQ2: 232468 | MR2: 155449 | MS2: 385864 | MT2: 1060490 | MU2: 1037534 | MV2: 278526 | MW2: 118907 | MX2: 241740 | MY2: 1001146 | MZ2: 288881 | NA2: 150188 | NB2: 451918 | NC2: 98554 | ND2: 153305 | NE2: 1787235 | NF2: 478693 | NG2: 302045 | NH2: 62161 | NI2: 198209 | NJ2: 6318377 | NK2: 454969 | NL2: 168637 | NM2: 115040 | NN2: 138403 | NO2: 114754 | NP2: 124538 | NQ2: 136920 | NR2: 652622 | NS2: 149358 | NT2: 143408 | NU2: 113489 | NV2: 453347 | NW2: 146386 | NX2: 689766 | NY2: 867788 | NZ2: 257152 | OA2: 462924 | OB2: 427420 | OC2: 183364 | OD2: 211741
A3: Not Hispanic or Latino | B3: 136353 | C3: 4866 | D3: 681468 | E3: 141448 | F3: 116769 | G3: 849312 | H3: 474836 | I3: 142847 | J3: 699474 | K3: 119352 | L3: 189026 | M3: 121167 | N3: 150064 | O3: 368445 | P3: 348419 | Q3: 110702 | R3: 232575 | S3: 884 | T3: 374933 | U3: 199013 | V3: 5479120 | W3: 307072 | X3: 189638 | Y3: 582935 | Z3: 1645409 | AA3: 398413 | AB3: 2617469 | AC3: 151487 | AD3: 223107 | AE3: 817914 | AF3: 125864 | AG3: 96891 | AH3: 323435 | AI3: 110867 | AJ3: 206042 | AK3: 231336 | AL3: 177455 | AM3: 233132 | AN3: 1113806 | AO3: 131336 | AP3: 174822 | AQ3: 160494 | AR3: 155500 | AS3: 689453 | AT3: 4339175 | AU3: 280495 | AV3: 175462 | AW3: 117416 | AX3: 251863 | AY3: 739778 | AZ3: 45596 | BA3: 107563 | BB3: 1091966 | BC3: 149881 | BD3: 221812 | BE3: 388658 | BF3: 615397 | BG3: 95522 | BH3: 42999 | BI3: 72400 | BJ3: 266092 | BK3: 145549 | BL3: 220615 | BM3: 202448 | BN3: 769479 | BO3: 2421901 | BP3: 208985 | BQ3: 538776 | BR3: 85056 | BS3: 7115062 | BT3: 166269 | BU3: 2166737 | BV3: 300856 | BW3: 2024934 | BX3: 119255 | BY3: 171698 | BZ3: 203843 | CA3: 626708 | CB3: 205970 | CC3: 789489 | CD3: 300507 | CE3: 75826 | CF3: 2053288 | CG3: 181152 | CH3: 87272 | CI3: 267821 | CJ3: 5614538 | CK3: 99064 | CL3: 232713 | CM3: 344396 | CN3: 785357 | CO3: 143543 | CP3: 98934 | CQ3: 596932 | CR3: 2283757 | CS3: 667439 | CT3: 4146725 | CU3: 145863 | CV3: 172388 | CW3: 95796 | CX3: 275403 | CY3: 519858 | CZ3: 3033 | DA3: 169220 | DB3: 25316 | DC3: 119274 | DD3: 165513 | DE3: 79062 | DF3: 151754 | DG3: 52695 | DH3: 256201 | DI3: 343982 | DJ3: 261648 | DK3: 87393 | DL3: 249216 | DM3: 96966 | DN3: 340970 | DO3: 472560 | DP3: 122181 | DQ3: 386129 | DR3: 193532 | DS3: 148486 | DT3: 97008 | DU3: 319847 | DV3: 201991 | DW3: 417918 | DX3: 525192 | DY3: 97712 | DZ3: 307792 | EA3: 150723 | EB3: 97902 | EC3: 122304 | ED3: 102372 | EE3: 97587 | EF3: 55858 | EG3: 134082 | EH3: 1045015 | EI3: 80402 | EJ3: 80136 | EK3: 241898 | EL3: 301571 | EM3: 704208 | EN3: 163245 | EO3: 875666 | EP3: 186 | EQ3: 393054 | ER3: 281748 | ES3: 128814 | ET3: 64050 | EU3: 555150 | EV3: 116907 | EW3: 966577 | EX3: 149371 | EY3: 90351 | EZ3: 334661 | FA3: 197626 | FB3: 74831 | FC3: 151169 | FD3: 92551 | FE3: 189064 | FF3: 4597130 | FG3: 365672 | FH3: 481079 | FI3: 142781 | FJ3: 1940330 | FK3: 166897 | FL3: 97651 | FM3: 153518 | FN3: 589611 | FO3: 172637 | FP3: 1496893 | FQ3: 178754 | FR3: 147704 | FS3: 145488 | FT3: 201440 | FU3: 128742 | FV3: 127787 | FW3: 186781 | FX3: 147145 | FY3: 246892 | FZ3: 93112 | GA3: 1975459 | GB3: 202597 | GC3: 142856 | GD3: 370431 | GE3: 303649 | GF3: 160337 | GG3: 561595 | GH3: 881356 | GI3: 80314 | GJ3: 166084 | GK3: 390398 | GL3: 205554 | GM3: 232094 | GN3: 182809 | GO3: 559853 | GP3: 493605 | GQ3: 436825 | GR3: 13464 | GS3: 72065 | GT3: 1587473 | GU3: 111662 | GV3: 109003 | GW3: 122268 | GX3: 62251 | GY3: 110928 | GZ3: 480296 | HA3: 197504 | HB3: 97666 | HC3: 316038 | HD3: 703687 | HE3: 137555 | HF3: 240771 | HG3: 100585 | HH3: 7139282 | HI3: 1276386 | HJ3: 223158 | HK3: 254225 | HL3: 225522 | HM3: 642589 | HN3: 389964 | HO3: 119120 | HP3: 99042 | HQ3: 122262 | HR3: 2173 | HS3: 71993 | HT3: 190075 | HU3: 1241387 | HV3: 106268 | HW3: 3328255 | HX3: 103419 | HY3: 80875 | HZ3: 97190 | IA3: 1379494 | IB3: 3459976 | IC3: 71407 | ID3: 119350 | IE3: 398346 | IF3: 276783 | IG3: 215706 | IH3: 148675 | II3: 369451 | IJ3: 137265 | IK3: 109959 | IL3: 105961 | IM3: 108623 | IN3: 164951 | IO3: 355015 | IP3: 85823 | IQ3: 286102 | IR3: 1869924 | IS3: 459058 | IT3: 853218 | IU3: 14708500 | IV3: 143591 | IW3: 761711 | IX3: 237860 | IY3: 331949 | IZ3: 60124 | JA3: 557732 | JB3: 1233399 | JC3: 267319 | JD3: 861516 | JE3: 1864099 | JF3: 163033 | JG3: 108147 | JH3: 466110 | JI3: 99539 | JJ3: 555527 | JK3: 193835 | JL3: 87229 | JM3: 488047 | JN3: 349541 | JO3: 5596850 | JP3: 3466524 | JQ3: 96680 | JR3: 2380974 | JS3: 121839 | JT3: 80585 | JU3: 1368 | JV3: 548703 | JW3: 2170484 | JX3: 418092 | JY3: 207732 | JZ3: 1429767 | KA3: 614882 | KB3: 97989 | KC3: 184563 | KD3: 167778 | KE3: 1303463 | KF3: 144743 | KG3: 325484 | KH3: 160090 | KI3: 420813 | KJ3: 1228254 | KK3: 2192127 | KL3: 297986 | KM3: 216409 | KN3: 967199 | KO3: 278857 | KP3: 134022 | KQ3: 87310 | KR3: 1873496 | KS3: 171284 | KT3: 193298 | KU3: 172641 | KV3: 112706 | KW3: 2700098 | KX3: 323752 | KY3: 168123 | KZ3: 121129 | LA3: 1017057 | LB3: 72068 | LC3: 1206244 | LD3: 2149711 | LE3: 109052 | LF3: 3567351 | LG3: 1451550 | LH3: 21922 | LI3: 211237 | LJ3: 171580 | LK3: 81365 | LL3: 229709 | LM3: 339522 | LN3: 384783 | LO3: 491104 | LP3: 3588087 | LQ3: 143803 | LR3: 82237 | LS3: 108843 | LT3: 119904 | LU3: 366379 | LV3: 82035 | LW3: 114665 | LX3: 281594 | LY3: 250014 | LZ3: 293445 | MA3: 341856 | MB3: 556234 | MC3: 201117 | MD3: 337627 | ME3: 465360 | MF3: 129425 | MG3: 152752 | MH3: 120239 | MI3: 458173 | MJ3: 100070 | MK3: 622779 | ML3: 359472 | MM3: 2585463 | MN3: 164156 | MO3: 136130 | MP3: 556200 | MQ3: 205551 | MR3: 150351 | MS3: 296765 | MT3: 674380 | MU3: 908101 | MV3: 264457 | MW3: 92122 | MX3: 191149 | MY3: 906806 | MZ3: 270984 | NA3: 138984 | NB3: 317965 | NC3: 52251 | ND3: 98501 | NE3: 1643688 | NF3: 159717 | NG3: 222384 | NH3: 47345 | NI3: 182663 | NJ3: 5178733 | NK3: 364297 | NL3: 161029 | NM3: 106383 | NN3: 133510 | NO3: 112705 | NP3: 85562 | NQ3: 134989 | NR3: 555976 | NS3: 120927 | NT3: 134245 | NU3: 110798 | NV3: 420430 | NW3: 128286 | NX3: 605371 | NY3: 748820 | NZ3: 122507 | OA3: 418512 | OB3: 407391 | OC3: 124829 | OD3: 74304
A4: Hispanic or Latino: | B4: 44055 | C4: 246903 | D4: 18352 | E4: 4570 | F4: 13937 | G4: 56740 | H4: 446646 | I4: 6775 | J4: 174129 | K4: 1925 | L4: 82891 | M4: 5967 | N4: 11964 | O4: 33519 | P4: 21403 | Q4: 5388 | R4: 13193 | S4: 179883 | T4: 39778 | U4: 21184 | V4: 777257 | W4: 64139 | X4: 10187 | Y4: 41246 | Z4: 781183 | AA4: 516662 | AB4: 231967 | AC4: 3223 | AD4: 8561 | AE4: 57399 | AF4: 7914 | AG4: 6117 | AH4: 73392 | AI4: 1847 | AJ4: 24461 | AK4: 26478 | AL4: 11800 | AM4: 12110 | AN4: 70807 | AO4: 4880 | AP4: 6842 | AQ4: 11062 | AR4: 7069 | AS4: 121662 | AT4: 614179 | AU4: 48466 | AV4: 11497 | AW4: 6658 | AX4: 26018 | AY4: 216552 | AZ4: 380524 | BA4: 7511 | BB4: 69377 | BC4: 27012 | BD4: 6034 | BE4: 11714 | BF4: 202269 | BG4: 2647 | BH4: 15385 | BI4: 7577 | BJ4: 10532 | BK4: 11830 | BL4: 18227 | BM4: 2950 | BN4: 64788 | BO4: 346506 | BP4: 15350 | BQ4: 37036 | BR4: 16004 | BS4: 2256533 | BT4: 41660 | BU4: 103969 | BV4: 33708 | BW4: 146592 | BX4: 9708 | BY4: 10298 | BZ4: 74492 | CA4: 141116 | CB4: 9044 | CC4: 59692 | CD4: 25108 | CE4: 7710 | CF4: 122500 | CG4: 266860 | CH4: 9031 | CI4: 31726 | CJ4: 2371052 | CK4: 45096 | CL4: 14276 | CM4: 37107 | CN4: 30723 | CO4: 14204 | CP4: 2915 | CQ4: 109218 | CR4: 718964 | CS4: 63681 | CT4: 230103 | CU4: 6811 | CV4: 15216 | CW4: 3234 | CX4: 5467 | CY4: 81866 | CZ4: 55049 | DA4: 4695 | DB4: 154886 | DC4: 7775 | DD4: 41619 | DE4: 3085 | DF4: 722428 | DG4: 9451 | DH4: 12851 | DI4: 40225 | DJ4: 8846 | DK4: 8067 | DL4: 10243 | DM4: 23976 | DN4: 51410 | DO4: 105166 | DP4: 22327 | DQ4: 17176 | DR4: 6143 | DS4: 5366 | DT4: 7129 | DU4: 47521 | DV4: 27908 | DW4: 37498 | DX4: 652473 | DY4: 5393 | DZ4: 42131 | EA4: 61982 | EB4: 8213 | EC4: 3735 | ED4: 16280 | EE4: 6041 | EF4: 20936 | EG4: 24519 | EH4: 117137 | EI4: 7777 | EJ4: 4470 | EK4: 108498 | EL4: 29574 | EM4: 82211 | EN4: 13948 | EO4: 86273 | EP4: 66016 | EQ4: 28147 | ER4: 20901 | ES4: 7924 | ET4: 89248 | EU4: 49005 | EV4: 20085 | EW4: 186535 | EX4: 6063 | EY4: 3555 | EZ4: 33655 | FA4: 29829 | FB4: 10940 | FC4: 11303 | FD4: 7484 | FE4: 13374 | FF4: 2845658 | FG4: 5057 | FH4: 35872 | FI4: 22580 | FJ4: 189725 | FK4: 12303 | FL4: 6886 | FM4: 6542 | FN4: 21713 | FO4: 9082 | FP4: 187067 | FQ4: 29152 | FR4: 16646 | FS4: 4949 | FT4: 9289 | FU4: 2796 | FV4: 8005 | FW4: 16845 | FX4: 17444 | FY4: 15483 | FZ4: 13523 | GA4: 242683 | GB4: 109210 | GC4: 25582 | GD4: 123929 | GE4: 7193 | GF4: 22264 | GG4: 143241 | GH4: 50885 | GI4: 3438 | GJ4: 4106 | GK4: 23030 | GL4: 21251 | GM4: 11933 | GN4: 37708 | GO4: 230841 | GP4: 64326 | GQ4: 35844 | GR4: 255830 | GS4: 152201 | GT4: 742075 | GU4: 8640 | GV4: 18307 | GW4: 21918 | GX4: 2913 | GY4: 2495 | GZ4: 42264 | HA4: 11935 | HB4: 3682 | HC4: 28299 | HD4: 54942 | HE4: 17547 | HF4: 50273 | HG4: 11775 | HH4: 5835205 | HI4: 96172 | HJ4: 135550 | HK4: 9573 | HL4: 9421 | HM4: 49241 | HN4: 36414 | HO4: 14845 | HP4: 5240 | HQ4: 2837 | HR4: 207719 | HS4: 819984 | HT4: 32570 | HU4: 100537 | HV4: 183933 | HW4: 2921036 | HX4: 8498 | HY4: 2882 | HZ4: 82829 | IA4: 189444 | IB4: 253692 | IC4: 5077 | ID4: 6281 | IE4: 14244 | IF4: 277207 | IG4: 7968 | IH4: 6830 | II4: 16573 | IJ4: 4058 | IK4: 12574 | IL4: 25367 | IM4: 3657 | IN4: 11010 | IO4: 28001 | IP4: 49046 | IQ4: 112189 | IR4: 209672 | IS4: 111540 | IT4: 128444 | IU4: 5090037 | IV4: 9697 | IW4: 127628 | IX4: 42111 | IY4: 68129 | IZ4: 104530 | JA4: 95642 | JB4: 229868 | JC4: 31748 | JD4: 120548 | JE4: 929647 | JF4: 8736 | JG4: 4615 | JH4: 371359 | JI4: 3209 | JJ4: 77253 | JK4: 18087 | JL4: 1231 | JM4: 36348 | JN4: 15661 | JO4: 675164 | JP4: 1562230 | JQ4: 8196 | JR4: 58966 | JS4: 7591 | JT4: 8869 | JU4: 269091 | JV4: 14140 | JW4: 350503 | JX4: 104584 | JY4: 37748 | JZ4: 254304 | KA4: 103104 | KB4: 71367 | KC4: 16501 | KD4: 29754 | KE4: 183839 | KF4: 8207 | KG4: 107531 | KH4: 21346 | KI4: 142207 | KJ4: 112994 | KK4: 2483577 | KL4: 17000 | KM4: 12113 | KN4: 91214 | KO4: 57665 | KP4: 10930 | KQ4: 12383 | KR4: 552892 | KS4: 17381 | KT4: 9160 | KU4: 23790 | KV4: 7306 | KW4: 110752 | KX4: 115154 | KY4: 269490 | KZ4: 8607 | LA4: 258813 | LB4: 48918 | LC4: 1456489 | LD4: 1139063 | LE4: 5523 | LF4: 1077678 | LG4: 517787 | LH4: 2030264 | LI4: 70318 | LJ4: 93346 | LK4: 74740 | LL4: 213992 | LM4: 145518 | LN4: 33502 | LO4: 78684 | LP4: 473833 | LQ4: 23133 | LR4: 23465 | LS4: 9148 | LT4: 23433 | LU4: 20440 | LV4: 43531 | LW4: 30017 | LX4: 16587 | LY4: 22407 | LZ4: 31115 | MA4: 32881 | MB4: 40889 | MC4: 5925 | MD4: 125188 | ME4: 21425 | MF4: 5733 | MG4: 5824 | MH4: 6583 | MI4: 339161 | MJ4: 4655 | MK4: 33631 | ML4: 32258 | MM4: 719228 | MN4: 4563 | MO4: 10166 | MP4: 46122 | MQ4: 26917 | MR4: 5098 | MS4: 89099 | MT4: 386110 | MU4: 129433 | MV4: 14069 | MW4: 26785 | MX4: 50591 | MY4: 94340 | MZ4: 17897 | NA4: 11204 | NB4: 133953 | NC4: 46303 | ND4: 54804 | NE4: 143547 | NF4: 318976 | NG4: 79661 | NH4: 14816 | NI4: 15546 | NJ4: 1139644 | NK4: 90672 | NL4: 7608 | NM4: 8657 | NN4: 4893 | NO4: 2049 | NP4: 38976 | NQ4: 1931 | NR4: 96646 | NS4: 28431 | NT4: 9163 | NU4: 2691 | NV4: 32917 | NW4: 18100 | NX4: 84395 | NY4: 118968 | NZ4: 134645 | OA4: 44412 | OB4: 20029 | OC4: 58535 | OD4: 137437
A5: Mexican | B5: 38120 | C5: 765 | D5: 7896 | E5: 2103 | F5: 11128 | G5: 6913 | H5: 270969 | I5: 3477 | J5: 12268 | K5: 205 | L5: 71754 | M5: 3541 | N5: 1409 | O5: 16716 | P5: 10017 | Q5: 3599 | R5: 9483 | S5: 215 | T5: 22084 | U5: 11960 | V5: 361131 | W5: 16434 | X5: 4488 | Y5: 17577 | Z5: 594873 | AA5: 461006 | AB5: 46372 | AC5: 1309 | AD5: 1428 | AE5: 15893 | AF5: 5915 | AG5: 4994 | AH5: 56413 | AI5: 444 | AJ5: 16974 | AK5: 20825 | AL5: 8446 | AM5: 1558 | AN5: 45227 | AO5: 1880 | AP5: 2786 | AQ5: 8298 | AR5: 2940 | AS5: 96127 | AT5: 39977 | AU5: 32550 | AV5: 6027 | AW5: 3491 | AX5: 15707 | AY5: 23194 | AZ5: 356804 | BA5: 3679 | BB5: 9191 | BC5: 16228 | BD5: 1283 | BE5: 3252 | BF5: 38545 | BG5: 1589 | BH5: 12451 | BI5: 5560 | BJ5: 7399 | BK5: 3276 | BL5: 11151 | BM5: 1557 | BN5: 28653 | BO5: 136928 | BP5: 4810 | BQ5: 14772 | BR5: 12007 | BS5: 1727884 | BT5: 35424 | BU5: 42760 | BV5: 17053 | BW5: 34754 | BX5: 6065 | BY5: 6793 | BZ5: 61164 | CA5: 85820 | CB5: 5875 | CC5: 25642 | CD5: 8943 | CE5: 6490 | CF5: 54989 | CG5: 238033 | CH5: 6200 | CI5: 10582 | CJ5: 1838097 | CK5: 33209 | CL5: 7245 | CM5: 31501 | CN5: 13622 | CO5: 8940 | CP5: 1957 | CQ5: 20184 | CR5: 522701 | CS5: 42668 | CT5: 149325 | CU5: 4134 | CV5: 3166 | CW5: 2056 | CX5: 3179 | CY5: 38607 | CZ5: 52955 | DA5: 2715 | DB5: 149370 | DC5: 3519 | DD5: 27920 | DE5: 810 | DF5: 674622 | DG5: 7999 | DH5: 2103 | DI5: 29167 | DJ5: 6019 | DK5: 4693 | DL5: 7271 | DM5: 12492 | DN5: 18599 | DO5: 71465 | DP5: 15710 | DQ5: 11396 | DR5: 3230 | DS5: 4065 | DT5: 5031 | DU5: 33799 | DV5: 17941 | DW5: 25592 | DX5: 601444 | DY5: 2788 | DZ5: 6138 | EA5: 41357 | EB5: 4838 | EC5: 725 | ED5: 8489 | EE5: 4219 | EF5: 11063 | EG5: 15324 | EH5: 78131 | EI5: 5594 | EJ5: 2675 | EK5: 86677 | EL5: 20959 | EM5: 48132 | EN5: 9509 | EO5: 33587 | EP5: 215 | EQ5: 9096 | ER5: 5684 | ES5: 3057 | ET5: 83201 | EU5: 9574 | EV5: 5672 | EW5: 11952 | EX5: 2957 | EY5: 2190 | EZ5: 15755 | FA5: 14798 | FB5: 4003 | FC5: 1554 | FD5: 5808 | FE5: 6807 | FF5: 1942584 | FG5: 2651 | FH5: 19455 | FI5: 18635 | FJ5: 113115 | FK5: 7427 | FL5: 1321 | FM5: 5098 | FN5: 11173 | FO5: 5743 | FP5: 32830 | FQ5: 12250 | FR5: 13597 | FS5: 3638 | FT5: 4219 | FU5: 760 | FV5: 6512 | FW5: 8229 | FX5: 7651 | FY5: 10085 | FZ5: 11477 | GA5: 168523 | GB5: 97351 | GC5: 18326 | GD5: 82373 | GE5: 3877 | GF5: 3977 | GG5: 28621 | GH5: 25915 | GI5: 1949 | GJ5: 2250 | GK5: 7965 | GL5: 14822 | GM5: 5017 | GN5: 29858 | GO5: 58817 | GP5: 5414 | GQ5: 25426 | GR5: 242013 | GS5: 133052 | GT5: 526609 | GU5: 5728 | GV5: 11150 | GW5: 1465 | GX5: 2138 | GY5: 925 | GZ5: 26825 | HA5: 4293 | HB5: 2121 | HC5: 18421 | HD5: 34910 | HE5: 12402 | HF5: 43456 | HG5: 8991 | HH5: 4356284 | HI5: 37086 | HJ5: 113046 | HK5: 3681 | HL5: 4104 | HM5: 29418 | HN5: 5230 | HO5: 9090 | HP5: 3785 | HQ5: 1658 | HR5: 315 | HS5: 779106 | HT5: 26385 | HU5: 56572 | HV5: 175488 | HW5: 151906 | HX5: 5845 | HY5: 1201 | HZ5: 71103 | IA5: 121993 | IB5: 151117 | IC5: 2519 | ID5: 3797 | IE5: 5579 | IF5: 254678 | IG5: 3922 | IH5: 4892 | II5: 10155 | IJ5: 1204 | IK5: 8493 | IL5: 21503 | IM5: 2599 | IN5: 8879 | IO5: 13631 | IP5: 41157 | IQ5: 40632 | IR5: 104325 | IS5: 16232 | IT5: 19478 | IU5: 600679 | IV5: 7166 | IW5: 45395 | IX5: 5658 | IY5: 10796 | IZ5: 93437 | JA5: 68989 | JB5: 175669 | JC5: 18591 | JD5: 86035 | JE5: 75848 | JF5: 5792 | JG5: 2568 | JH5: 322303 | JI5: 1681 | JJ5: 11880 | JK5: 5618 | JL5: 646 | JM5: 13738 | JN5: 10968 | JO5: 128574 | JP5: 1322316 | JQ5: 4208 | JR5: 19566 | JS5: 534 | JT5: 6787 | JU5: 486 | JV5: 3770 | JW5: 260395 | JX5: 21501 | JY5: 31359 | JZ5: 15373 | KA5: 59809 | KB5: 44956 | KC5: 2701 | KD5: 23645 | KE5: 86138 | KF5: 5147 | KG5: 16889 | KH5: 16024 | KI5: 107442 | KJ5: 26257 | KK5: 2118368 | KL5: 5663 | KM5: 7490 | KN5: 9331 | KO5: 46946 | KP5: 7865 | KQ5: 7046 | KR5: 437691 | KS5: 14438 | KT5: 5604 | KU5: 15985 | KV5: 4139 | KW5: 66337 | KX5: 100418 | KY5: 246333 | KZ5: 3608 | LA5: 175791 | LB5: 44152 | LC5: 1205294 | LD5: 975588 | LE5: 3305 | LF5: 671068 | LG5: 416636 | LH5: 4772 | LI5: 59002 | LJ5: 80460 | LK5: 40374 | LL5: 191409 | LM5: 117693 | LN5: 12975 | LO5: 11571 | LP5: 313554 | LQ5: 8294 | LR5: 9487 | LS5: 6813 | LT5: 19682 | LU5: 12995 | LV5: 38609 | LW5: 22985 | LX5: 7144 | LY5: 5537 | LZ5: 23662 | MA5: 18743 | MB5: 28045 | MC5: 2674 | MD5: 3446 | ME5: 12058 | MF5: 3395 | MG5: 1749 | MH5: 3370 | MI5: 296751 | MJ5: 2214 | MK5: 4269 | ML5: 8412 | MM5: 121978 | MN5: 2656 | MO5: 7840 | MP5: 34717 | MQ5: 21747 | MR5: 3500 | MS5: 5106 | MT5: 339179 | MU5: 93883 | MV5: 7741 | MW5: 23392 | MX5: 45128 | MY5: 31736 | MZ5: 2442 | NA5: 5539 | NB5: 100502 | NC5: 41287 | ND5: 20534 | NE5: 47470 | NF5: 297217 | NG5: 70832 | NH5: 11955 | NI5: 7566 | NJ5: 161817 | NK5: 5451 | NL5: 4376 | NM5: 2793 | NN5: 3364 | NO5: 1041 | NP5: 34892 | NQ5: 635 | NR5: 76869 | NS5: 24975 | NT5: 2845 | NU5: 981 | NV5: 15978 | NW5: 6338 | NX5: 49585 | NY5: 7761 | NZ5: 125522 | OA5: 7127 | OB5: 4076 | OC5: 50201 | OD5: 131603
A6: Puerto Rican | B6: 975 | C6: 238336 | D6: 3593 | E6: 550 | F6: 224 | G6: 25811 | H6: 6403 | I6: 556 | J6: 77863 | K6: 465 | L6: 578 | M6: 415 | N6: 5362 | O6: 4678 | P6: 2398 | Q6: 665 | R6: 1052 | S6: 178229 | T6: 3306 | U6: 1114 | V6: 76675 | W6: 22793 | X6: 1343 | Y6: 9119 | Z6: 23329 | AA6: 4629 | AB6: 35750 | AC6: 612 | AD6: 1549 | AE6: 2679 | AF6: 641 | AG6: 212 | AH6: 1193 | AI6: 243 | AJ6: 1017 | AK6: 482 | AL6: 436 | AM6: 4791 | AN6: 4393 | AO6: 1326 | AP6: 862 | AQ6: 786 | AR6: 877 | AS6: 3232 | AT6: 129188 | AU6: 1664 | AV6: 466 | AW6: 346 | AX6: 2530 | AY6: 49257 | AZ6: 1756 | BA6: 507 | BB6: 39226 | BC6: 1727 | BD6: 900 | BE6: 2416 | BF6: 35954 | BG6: 261 | BH6: 89 | BI6: 206 | BJ6: 859 | BK6: 3507 | BL6: 1455 | BM6: 485 | BN6: 9200 | BO6: 32026 | BP6: 1493 | BQ6: 3295 | BR6: 324 | BS6: 207529 | BT6: 719 | BU6: 12020 | BV6: 7750 | BW6: 78462 | BX6: 1120 | BY6: 595 | BZ6: 1202 | CA6: 10795 | CB6: 402 | CC6: 9975 | CD6: 7369 | CE6: 435 | CF6: 18915 | CG6: 2640 | CH6: 363 | CI6: 5506 | CJ6: 70610 | CK6: 1178 | CL6: 1184 | CM6: 1439 | CN6: 5305 | CO6: 670 | CP6: 320 | CQ6: 48504 | CR6: 20699 | CS6: 3770 | CT6: 25313 | CU6: 859 | CV6: 6757 | CW6: 417 | CX6: 395 | CY6: 5179 | CZ6: 429 | DA6: 407 | DB6: 434 | DC6: 2255 | DD6: 2910 | DE6: 1180 | DF6: 8535 | DG6: 300 | DH6: 7572 | DI6: 1745 | DJ6: 401 | DK6: 1296 | DL6: 1042 | DM6: 175 | DN6: 17314 | DO6: 3403 | DP6: 567 | DQ6: 1139 | DR6: 1206 | DS6: 148 | DT6: 429 | DU6: 1973 | DV6: 481 | DW6: 2952 | DX6: 4784 | DY6: 448 | DZ6: 9829 | EA6: 2334 | EB6: 2059 | EC6: 962 | ED6: 784 | EE6: 262 | EF6: 253 | EG6: 597 | EH6: 9781 | EI6: 259 | EJ6: 513 | EK6: 2284 | EL6: 3377 | EM6: 9331 | EN6: 1747 | EO6: 11062 | EP6: 65217 | EQ6: 5921 | ER6: 3646 | ES6: 560 | ET6: 1011 | EU6: 22895 | EV6: 3339 | EW6: 112347 | EX6: 626 | EY6: 286 | EZ6: 3779 | FA6: 4334 | FB6: 4065 | FC6: 4527 | FD6: 148 | FE6: 615 | FF6: 59852 | FG6: 526 | FH6: 5010 | FI6: 556 | FJ6: 14134 | FK6: 869 | FL6: 1401 | FM6: 571 | FN6: 978 | FO6: 588 | FP6: 57152 | FQ6: 7105 | FR6: 820 | FS6: 354 | FT6: 947 | FU6: 1120 | FV6: 574 | FW6: 1214 | FX6: 4821 | FY6: 1121 | FZ6: 494 | GA6: 13238 | GB6: 762 | GC6: 2863 | GD6: 22451 | GE6: 1078 | GF6: 8025 | GG6: 50783 | GH6: 4723 | GI6: 391 | GJ6: 644 | GK6: 1111 | GL6: 1000 | GM6: 617 | GN6: 1257 | GO6: 95449 | GP6: 38167 | GQ6: 2456 | GR6: 1202 | GS6: 1159 | GT6: 26569 | GU6: 881 | GV6: 3625 | GW6: 14057 | GX6: 188 | GY6: 690 | GZ6: 2856 | HA6: 2083 | HB6: 563 | HC6: 1076 | HD6: 2200 | HE6: 710 | HF6: 894 | HG6: 180 | HH6: 60208 | HI6: 8148 | HJ6: 1307 | HK6: 1410 | HL6: 1378 | HM6: 4268 | HN6: 11375 | HO6: 2125 | HP6: 134 | HQ6: 489 | HR6: 203565 | HS6: 3148 | HT6: 1037 | HU6: 4573 | HV6: 975 | HW6: 224306 | HX6: 1103 | HY6: 233 | HZ6: 1025 | IA6: 40714 | IB6: 13241 | IC6: 1047 | ID6: 227 | IE6: 1458 | IF6: 3124 | IG6: 625 | IH6: 417 | II6: 1290 | IJ6: 609 | IK6: 1422 | IL6: 478 | IM6: 308 | IN6: 810 | IO6: 3284 | IP6: 810 | IQ6: 7999 | IR6: 15178 | IS6: 55115 | IT6: 5850 | IU6: 1077573 | IV6: 854 | IW6: 20989 | IX6: 21709 | IY6: 31215 | IZ6: 856 | JA6: 2546 | JB6: 7422 | JC6: 4220 | JD6: 3893 | JE6: 399412 | JF6: 1466 | JG6: 609 | JH6: 4555 | JI6: 422 | JJ6: 26963 | JK6: 4126 | JL6: 151 | JM6: 6412 | JN6: 1081 | JO6: 285299 | JP6: 37011 | JQ6: 1352 | JR6: 13543 | JS6: 2744 | JT6: 384 | JU6: 266782 | JV6: 2596 | JW6: 11027 | JX6: 25468 | JY6: 1116 | JZ6: 71643 | KA6: 2772 | KB6: 1489 | KC6: 4280 | KD6: 2989 | KE6: 21182 | KF6: 923 | KG6: 45598 | KH6: 632 | KI6: 3150 | KJ6: 17609 | KK6: 32683 | KL6: 2327 | KM6: 741 | KN6: 57277 | KO6: 3632 | KP6: 923 | KQ6: 364 | KR6: 16112 | KS6: 940 | KT6: 790 | KU6: 899 | KV6: 805 | KW6: 8250 | KX6: 1483 | KY6: 2419 | KZ6: 1018 | LA6: 6417 | LB6: 572 | LC6: 40245 | LD6: 26187 | LE6: 1009 | LF6: 31112 | LG6: 8331 | LH6: 1939182 | LI6: 1199 | LJ6: 1310 | LK6: 661 | LL6: 1654 | LM6: 2213 | LN6: 7549 | LO6: 20729 | LP6: 24619 | LQ6: 4466 | LR6: 7289 | LS6: 1023 | LT6: 310 | LU6: 1037 | LV6: 1541 | LW6: 528 | LX6: 733 | LY6: 1605 | LZ6: 1981 | MA6: 3496 | MB6: 2899 | MC6: 909 | MD6: 100672 | ME6: 3113 | MF6: 823 | MG6: 1472 | MH6: 762 | MI6: 5820 | MJ6: 1068 | MK6: 14931 | ML6: 5091 | MM6: 205150 | MN6: 577 | MO6: 374 | MP6: 3902 | MQ6: 2139 | MR6: 435 | MS6: 19121 | MT6: 9820 | MU6: 5661 | MV6: 1471 | MW6: 84 | MX6: 438 | MY6: 30837 | MZ6: 7831 | NA6: 2309 | NB6: 3739 | NC6: 495 | ND6: 24561 | NE6: 38374 | NF6: 1427 | NG6: 1923 | NH6: 307 | NI6: 1917 | NJ6: 77582 | NK6: 49037 | NL6: 588 | NM6: 2523 | NN6: 302 | NO6: 271 | NP6: 142 | NQ6: 350 | NR6: 4396 | NS6: 691 | NT6: 1781 | NU6: 943 | NV6: 4364 | NW6: 2077 | NX6: 8520 | NY6: 60311 | NZ6: 941 | OA6: 22920 | OB6: 11715 | OC6: 1586 | OD6: 1022
A7: Cuban | B7: 287 | C7: 274 | D7: 586 | E7: 183 | F7: 191 | G7: 1926 | H7: 4269 | I7: 334 | J7: 3372 | K7: 142 | L7: 1107 | M7: 168 | N7: 280 | O7: 1412 | P7: 649 | Q7: 148 | R7: 214 | S7: 252 | T7: 1183 | U7: 995 | V7: 26862 | W7: 1747 | X7: 724 | Y7: 1467 | Z7: 16821 | AA7: 1432 | AB7: 7695 | AC7: 116 | AD7: 115 | AE7: 1947 | AF7: 243 | AG7: 124 | AH7: 889 | AI7: 316 | AJ7: 168 | AK7: 191 | AL7: 87 | AM7: 449 | AN7: 2111 | AO7: 22 | AP7: 112 | AQ7: 287 | AR7: 267 | AS7: 751 | AT7: 12100 | AU7: 697 | AV7: 771 | AW7: 205 | AX7: 358 | AY7: 5317 | AZ7: 670 | BA7: 261 | BB7: 2035 | BC7: 444 | BD7: 432 | BE7: 620 | BF7: 59171 | BG7: 15 | BH7: 124 | BI7: 137 | BJ7: 167 | BK7: 81 | BL7: 271 | BM7: 119 | BN7: 2822 | BO7: 12478 | BP7: 824 | BQ7: 1471 | BR7: 25 | BS7: 28965 | BT7: 275 | BU7: 3378 | BV7: 818 | BW7: 3170 | BX7: 197 | BY7: 151 | BZ7: 1193 | CA7: 3038 | CB7: 256 | CC7: 2141 | CD7: 903 | CE7: 36 | CF7: 2171 | CG7: 1968 | CH7: 112 | CI7: 1600 | CJ7: 30660 | CK7: 1126 | CL7: 716 | CM7: 206 | CN7: 686 | CO7: 397 | CP7: 47 | CQ7: 8876 | CR7: 9159 | CS7: 795 | CT7: 5426 | CU7: 276 | CV7: 535 | CW7: 70 | CX7: 189 | CY7: 2397 | CZ7: 0 | DA7: 196 | DB7: 121 | DC7: 376 | DD7: 97 | DE7: 44 | DF7: 1795 | DG7: 10 | DH7: 413 | DI7: 630 | DJ7: 255 | DK7: 88 | DL7: 129 | DM7: 307 | DN7: 1655 | DO7: 1308 | DP7: 552 | DQ7: 2286 | DR7: 151 | DS7: 375 | DT7: 103 | DU7: 776 | DV7: 251 | DW7: 287 | DX7: 791 | DY7: 103 | DZ7: 7052 | EA7: 1139 | EB7: 197 | EC7: 115 | ED7: 144 | EE7: 101 | EF7: 1933 | EG7: 131 | EH7: 5020 | EI7: 43 | EJ7: 16 | EK7: 1101 | EL7: 469 | EM7: 1749 | EN7: 302 | EO7: 2974 | EP7: 197 | EQ7: 802 | ER7: 267 | ES7: 469 | ET7: 194 | EU7: 949 | EV7: 888 | EW7: 3862 | EX7: 125 | EY7: 117 | EZ7: 724 | FA7: 469 | FB7: 663 | FC7: 2123 | FD7: 17 | FE7: 252 | FF7: 70058 | FG7: 241 | FH7: 1217 | FI7: 245 | FJ7: 4129 | FK7: 89 | FL7: 408 | FM7: 247 | FN7: 842 | FO7: 204 | FP7: 25309 | FQ7: 930 | FR7: 55 | FS7: 59 | FT7: 506 | FU7: 159 | FV7: 55 | FW7: 85 | FX7: 219 | FY7: 387 | FZ7: 120 | GA7: 5591 | GB7: 1111 | GC7: 145 | GD7: 1889 | GE7: 335 | GF7: 1696 | GG7: 3208 | GH7: 2042 | GI7: 186 | GJ7: 140 | GK7: 817 | GL7: 622 | GM7: 1089 | GN7: 735 | GO7: 18764 | GP7: 2485 | GQ7: 2164 | GR7: 366 | GS7: 64 | GT7: 39173 | GU7: 106 | GV7: 320 | GW7: 187 | GX7: 74 | GY7: 92 | GZ7: 1983 | HA7: 426 | HB7: 14 | HC7: 691 | HD7: 534 | HE7: 107 | HF7: 54 | HG7: 96 | HH7: 45450 | HI7: 28503 | HJ7: 503 | HK7: 227 | HL7: 776 | HM7: 1272 | HN7: 598 | HO7: 186 | HP7: 40 | HQ7: 105 | HR7: 363 | HS7: 1297 | HT7: 176 | HU7: 2714 | HV7: 88 | HW7: 1155991 | HX7: 89 | HY7: 424 | HZ7: 2020 | IA7: 2097 | IB7: 4623 | IC7: 252 | ID7: 218 | IE7: 1054 | IF7: 625 | IG7: 260 | IH7: 211 | II7: 486 | IJ7: 252 | IK7: 346 | IL7: 103 | IM7: 40 | IN7: 98 | IO7: 769 | IP7: 251 | IQ7: 25204 | IR7: 8288 | IS7: 2638 | IT7: 8746 | IU7: 151078 | IV7: 249 | IW7: 18955 | IX7: 1001 | IY7: 8313 | IZ7: 3594 | JA7: 484 | JB7: 2455 | JC7: 581 | JD7: 2786 | JE7: 76266 | JF7: 111 | JG7: 71 | JH7: 2681 | JI7: 79 | JJ7: 10400 | JK7: 1368 | JL7: 67 | JM7: 2598 | JN7: 359 | JO7: 17515 | JP7: 19511 | JQ7: 334 | JR7: 2652 | JS7: 210 | JT7: 43 | JU7: 508 | JV7: 512 | JW7: 7251 | JX7: 14281 | JY7: 329 | JZ7: 3350 | KA7: 706 | KB7: 332 | KC7: 4511 | KD7: 309 | KE7: 6369 | KF7: 133 | KG7: 1025 | KH7: 248 | KI7: 1519 | KJ7: 3967 | KK7: 15429 | KL7: 954 | KM7: 168 | KN7: 3632 | KO7: 875 | KP7: 269 | KQ7: 77 | KR7: 3620 | KS7: 165 | KT7: 515 | KU7: 215 | KV7: 695 | KW7: 3653 | KX7: 715 | KY7: 751 | KZ7: 136 | LA7: 2713 | LB7: 274 | LC7: 9988 | LD7: 7915 | LE7: 55 | LF7: 9063 | LG7: 3395 | LH7: 10266 | LI7: 683 | LJ7: 493 | LK7: 315 | LL7: 557 | LM7: 842 | LN7: 1958 | LO7: 865 | LP7: 7484 | LQ7: 2761 | LR7: 3156 | LS7: 12 | LT7: 122 | LU7: 233 | LV7: 242 | LW7: 144 | LX7: 315 | LY7: 673 | LZ7: 360 | MA7: 1537 | MB7: 666 | MC7: 107 | MD7: 705 | ME7: 363 | MF7: 70 | MG7: 336 | MH7: 130 | MI7: 953 | MJ7: 124 | MK7: 2703 | ML7: 4560 | MM7: 153077 | MN7: 189 | MO7: 50 | MP7: 1123 | MQ7: 213 | MR7: 120 | MS7: 1364 | MT7: 2839 | MU7: 1605 | MV7: 812 | MW7: 64 | MX7: 143 | MY7: 1765 | MZ7: 682 | NA7: 648 | NB7: 662 | NC7: 23 | ND7: 705 | NE7: 5753 | NF7: 691 | NG7: 540 | NH7: 37 | NI7: 829 | NJ7: 21393 | NK7: 1741 | NL7: 218 | NM7: 90 | NN7: 68 | NO7: 102 | NP7: 38 | NQ7: 10 | NR7: 1139 | NS7: 315 | NT7: 1409 | NU7: 35 | NV7: 1001 | NW7: 287 | NX7: 1882 | NY7: 1762 | NZ7: 211 | OA7: 979 | OB7: 455 | OC7: 262 | OD7: 112
